Workbook

Sheet Leia-me
A1: Base de dados da clínica — estrutura e orientações
A2: Planilha-base para alimentar o SaaS e o painel da reunião semanal.
A4: Legenda
A5: Célula amarela | B5: Preencher (dado coletado)
A6: Célula branca | B6: Calculada automaticamente — não editar
A8: Fluxo de uso
A9: 1. Config: confirme os nomes dos fisioterapeutas (Fisio 1 / Fisio 2), as metas semanais e mensais e as listas de opções.
A10: 2. Base_Semanal: ao fim de cada semana, preencha a linha da semana (leads, avaliações, contratos, atendimentos, agenda, tempos).
A11: 3. Contratos: registre cada avaliação ou protocolo contratado com valor, condição e forma de pagamento e canal de ingresso.
A12: 4. Financeiro: registre receitas, gastos, impostos e marketing; use o status para pendências (Pendente) e inadimplência (Atrasado).
A13: 5. Leads_Canal: distribua os leads da semana por canal (meios de comunicação de ingresso).
A14: 6. Reuniao_Semanal e Plano_Acao: registre o qualitativo da reunião e as ações 5W2H.
A15: 7. Painel_Semanal: escolha a semana na célula C3 e conduza a reunião pelo painel. Resumo_Semanal e Resumo_Mensal consolidam tudo.
A17: Premissas
A18: Semanas seguem o padrão ISO (segunda a domingo), identificadas como AAAA-Sww; o mês de uma semana é o mês da sua data de início.
A19: Contratos e lançamentos financeiros recebem semana e mês automaticamente pela data informada.
A20: As linhas marcadas como 'Exemplo' (semanas 2026-S39, S40 e S41) são ilustrativas e devem ser substituídas pelos dados reais.
... A26: Dicionário de dados (para modelagem do SaaS)
A27: Aba (tabela) | B27: Campo | C27: Origem | D27: Descrição
A28: Base_Semanal | B28: id_semana | C28: preenchido | D28: Identificador da semana (AAAA-Sww), pré-preenchido a partir do Calendário
A29: Base_Semanal | B29: Início | C29: automático | D29: Data de início da semana (automático)
A30: Base_Semanal | B30: Fim | C30: automático | D30: Data de fim da semana (automático)
A31: Base_Semanal | B31: Mês | C31: automático | D31: Mês de referência AAAA-MM (automático)
A32: Base_Semanal | B32: Leads recebidos | C32: preenchido | D32: Total de leads recebidos na semana
A33: Base_Semanal | B33: Aval. agendadas | C33: preenchido | D33: Avaliações agendadas na semana
A34: Base_Semanal | B34: Aval. canceladas | C34: preenchido | D34: Avaliações canceladas na semana
A35: Base_Semanal | B35: Aval. realizadas Fisio 1 | C35: preenchido | D35: Avaliações realizadas pelo Fisio 1
A36: Base_Semanal | B36: Aval. realizadas Fisio 2 | C36: preenchido | D36: Avaliações realizadas pelo Fisio 2
A37: Base_Semanal | B37: Contratos fechados Fisio 1 | C37: preenchido | D37: Contratos (tratamentos) fechados pelo Fisio 1
A38: Base_Semanal | B38: Contratos fechados Fisio 2 | C38: preenchido | D38: Contratos (tratamentos) fechados pelo Fisio 2
... A185: Resumo_Mensal | B185: CAC (marketing / novos pac.) | C185: automático | D185: Calculado por mês

Sheet Painel_Semanal
A1: Painel de resultados — reunião semanal
A2: Escolha a semana na célula amarela (C3). Tudo o mais é calculado.
B3: Semana selecionada | C3: 2026-S40 | D3: Semana anterior | E3: =IFERROR(INDEX(Calendario!$A$4:$A$107,MATCH($C$3,Calendario!$A$4:$A$107,0)-1),"") -> 2026-S39 | F3: Próxima semana | G3: =IFERROR(INDEX(Calendario!$A$4:$A$107,MATCH($C$3,Calendario!$A$4:$A$107,0)+1),"") -> 2026-S41
B4: Período | C4: =IFERROR(INDEX(Calendario!$B$4:$B$107,MATCH($C$3,Calendario!$A$4:$A$107,0)),"") -> 46293 | D4: =IFERROR(INDEX(Calendario!$C$4:$C$107,MATCH($C$3,Calendario!$A$4:$A$107,0)),"") -> 46299
B5: Mês | C5: =IFERROR(INDEX(Calendario!$D$4:$D$107,MATCH($C$3,Calendario!$A$4:$A$107,0)),"") -> 2026-09
B7: 1. ABERTURA
B8: Resultado geral (automático — leads, avaliações, contratos, atendimentos, receita e gastos vs. semana anterior) | C8: =IF($C$3="","",IF((SIGN(N(IFERROR(INDEX(Resumo_Semanal!$E$4:$E$107,MATCH($C$3,Resumo_Semanal!$A$4:$A$107,0)),""))-N(IFERROR(INDEX(Resumo_Semanal!$E$4:$E$107,MATCH($E$3,Resumo_Semanal!$A$4:$A$107,0)),"")))+SIGN(N(IFERROR(INDEX(Resumo_Semanal!$J$4:$J$107,MATCH($C$3,Resumo_Semanal!$A$4:$A$107,0)),""))-N(IFERROR(INDEX(Resumo_Semanal!$J$4:$J$107,MATCH($E$3,Resumo_Semanal!$A$4:$A$107,0)),"")))+SIGN(N(IFERROR(INDEX(Resumo_Semanal!$N$4:$N$107,MATCH($C$3,Resumo_Semanal!$A$4:$A$107,0)),""))-N(IFERROR(INDEX(Resumo_Semanal!$N$4:$N$107,MATCH($E$3,Resumo_Semanal!$A$4:$A$107,0)),"")))+SIGN(N(IFERROR(INDEX(Resumo_Semanal!$R$4:$R$107,MATCH($C$3,Resumo_Semanal!$A$4:$A$107,0)),""))-N(IFERROR(INDEX(Resumo_Semanal!$R$4:$R$107,MATCH($E$3,Resumo_Semanal!$A$4:$A$107,0)),"")))+SIGN(N(IFERROR(INDEX(Resumo_Semanal!$AI$4:$AI$107,MATCH($C$3,Resumo_Semanal!$A$4:$A$107,0)),""))-N(IFERROR(INDEX(Resumo_Semanal!$AI$4:$AI$107,MATCH($E$3,Resumo_Semanal!$A$4:$A$107,0)),"")))-SIGN(N(IFERROR(INDEX(Resumo_Semanal!$AJ$4:$AJ$107,MATCH($C$3,Resumo_Semanal!$A$4:$A$107,0)),""))-N(IFERROR(INDEX(Resumo_Semanal!$AJ$4:$AJ$107,MATCH($E$3,Resumo_Semanal!$A$4:$A$107,0)),""))))>0,"Melhor",IF((SIGN(N(IFERROR(INDEX(Resumo_Semanal!$E$4:$E$107,MATCH($C$3,Resumo_Semanal!$A$4:$A$107,0)),""))-N(IFERROR(INDEX(Resumo_Semanal!$E$4:$E$107,MATCH($E$3,Resumo_Semanal!$A$4:$A$107,0)),"")))+SIGN(N(IFERROR(INDEX(Resumo_Semanal!$J$4:$J$107,MATCH($C$3,Resumo_Semanal!$A$4:$A$107,0)),""))-N(IFERROR(INDEX(Resumo_Semanal!$J$4:$J$107,MATCH($E$3,Resumo_Semanal!$A$4:$A$107,0)),"")))+SIGN(N(IFERROR(INDEX(Resumo_Semanal!$N$4:$N$107,MATCH($C$3,Resumo_Semanal!$A$4:$A$107,0)),""))-N(IFERROR(INDEX(Resumo_Semanal!$N$4:$N$107,MATCH($E$3,Resumo_Semanal!$A$4:$A$107,0)),"")))+SIGN(N(IFERROR(INDEX(Resumo_Semanal!$R$4:$R$107,MATCH($C$3,Resumo_Semanal!$A$4:$A$107,0)),""))-N(IFERROR(INDEX(Resumo_Semanal!$R$4:$R$107,MATCH($E$3,Resumo_Semanal!$A$4:$A$107,0)),"")))+SIGN(N(IFERROR(INDEX(Resumo_Semanal!$AI$4:$AI$107,MATCH($C$3,Resumo_Semanal!$A$4:$A$107,0)),""))-N(IFERROR(INDEX(Resumo_Semanal!$AI$4:$AI$107,MATCH($E$3,Resumo_Semanal!$A$4:$A$107,0)),"")))-SIGN(N(IFERROR(INDEX(Resumo_Semanal!$AJ$4:$AJ$107,MATCH($C$3,Resumo_Semanal!$A$4:$A$107,0)),""))-N(IFERROR(INDEX(Resumo_Semanal!$AJ$4:$AJ$107,MATCH($E$3,Resumo_Semanal!$A$4:$A$107,0)),""))))<0,"Pior","Igual"))) -> Melhor
B9: Resultado geral (registrado na reunião) | C9: =IFERROR(INDEX(Reuniao_Semanal!$B$4:$B$203,MATCH($C$3,Reuniao_Semanal!$A$4:$A$203,0)),"") -> Melhor
B10: Pontos positivos | C10: =IFERROR(INDEX(Reuniao_Semanal!$C$4:$C$203,MATCH($C$3,Reuniao_Semanal!$A$4:$A$203,0)),"") -> Receita acima da meta; 4 protocolos fechados por indicação
B11: Pontos a melhorar | C11: =IFERROR(INDEX(Reuniao_Semanal!$D$4:$D$203,MATCH($C$3,Reuniao_Semanal!$A$4:$A$203,0)),"") -> Taxa de ocupação da tarde abaixo de 90%; 5 cancelamentos de atendimento
B13: 2. INDICADORES-CHAVE — CRESCIMENTO
B14: Indicador | C14: Semana atual | D14: Semana anterior | E14: Variação | F14: Meta semanal | G14: % da meta | H14: Acumulado no mês | I14: Meta mensal
B15: Leads recebidos | C15: =IFERROR(INDEX(Resumo_Semanal!$E$4:$E$107,MATCH($C$3,Resumo_Semanal!$A$4:$A$107,0)),"") -> 45 | D15: =IFERROR(INDEX(Resumo_Semanal!$E$4:$E$107,MATCH($E$3,Resumo_Semanal!$A$4:$A$107,0)),"") -> 38 | E15: =IF(OR(C15="",D15=""),"",C15-D15) -> 7 | F15: =Config!$B$10 -> 40 | G15: =IF(OR(C15="",F15=0),"",C15/F15) -> 1.125 | H15: =SUMIFS(Resumo_Semanal!$E$4:$E$107,Resumo_Semanal!$D$4:$D$107,$C$5,Resumo_Semanal!$B$4:$B$107,"<="&$C$4) -> 83 | I15: =Config!$C$10 -> 170
B16: Novos pacientes | C16: =IFERROR(INDEX(Resumo_Semanal!$T$4:$T$107,MATCH($C$3,Resumo_Semanal!$A$4:$A$107,0)),"") -> 9 | D16: =IFERROR(INDEX(Resumo_Semanal!$T$4:$T$107,MATCH($E$3,Resumo_Semanal!$A$4:$A$107,0)),"") -> 6 | E16: =IF(OR(C16="",D16=""),"",C16-D16) -> 3 | F16: =Config!$B$11 -> 8 | G16: =IF(OR(C16="",F16=0),"",C16/F16) -> 1.125 | H16: =SUMIFS(Resumo_Semanal!$T$4:$T$107,Resumo_Semanal!$D$4:$D$107,$C$5,Resumo_Semanal!$B$4:$B$107,"<="&$C$4) -> 15 | I16: =Config!$C$11 -> 32
B17: Avaliações agendadas | C17: =IFERROR(INDEX(Resumo_Semanal!$F$4:$F$107,MATCH($C$3,Resumo_Semanal!$A$4:$A$107,0)),"") -> 16 | D17: =IFERROR(INDEX(Resumo_Semanal!$F$4:$F$107,MATCH($E$3,Resumo_Semanal!$A$4:$A$107,0)),"") -> 14 | E17: =IF(OR(C17="",D17=""),"",C17-D17) -> 2 | H17: =SUMIFS(Resumo_Semanal!$F$4:$F$107,Resumo_Semanal!$D$4:$D$107,$C$5,Resumo_Semanal!$B$4:$B$107,"<="&$C$4) -> 30
B18: Avaliações canceladas | C18: =IFERROR(INDEX(Resumo_Semanal!$G$4:$G$107,MATCH($C$3,Resumo_Semanal!$A$4:$A$107,0)),"") -> 1 | D18: =IFERROR(INDEX(Resumo_Semanal!$G$4:$G$107,MATCH($E$3,Resumo_Semanal!$A$4:$A$107,0)),"") -> 2 | E18: =IF(OR(C18="",D18=""),"",C18-D18) -> -1 | H18: =SUMIFS(Resumo_Semanal!$G$4:$G$107,Resumo_Semanal!$D$4:$D$107,$C$5,Resumo_Semanal!$B$4:$B$107,"<="&$C$4) -> 3
B19: Taxa de cancelamento de avaliações | C19: =IFERROR(INDEX(Resumo_Semanal!$K$4:$K$107,MATCH($C$3,Resumo_Semanal!$A$4:$A$107,0)),"") -> 0.0625 | D19: =IFERROR(INDEX(Resumo_Semanal!$K$4:$K$107,MATCH($E$3,Resumo_Semanal!$A$4:$A$107,0)),"") -> 0.14285714 | E19: =IF(OR(C19="",D19=""),"",C19-D19) -> -0.080357143 | F19: =Config!$B$20 -> 0.15 | G19: =IF(OR(C19="",F19=0),"",C19/F19) -> 0.41666667 | I19: =Config!$C$20 -> 0.15
B20: Avaliações realizadas — total | C20: =IFERROR(INDEX(Resumo_Semanal!$J$4:$J$107,MATCH($C$3,Resumo_Semanal!$A$4:$A$107,0)),"") -> 14 | D20: =IFERROR(INDEX(Resumo_Semanal!$J$4:$J$107,MATCH($E$3,Resumo_Semanal!$A$4:$A$107,0)),"") -> 11 | E20: =IF(OR(C20="",D20=""),"",C20-D20) -> 3 | F20: =Config!$B$12 -> 12 | G20: =IF(OR(C20="",F20=0),"",C20/F20) -> 1.1666667 | H20: =SUMIFS(Resumo_Semanal!$J$4:$J$107,Resumo_Semanal!$D$4:$D$107,$C$5,Resumo_Semanal!$B$4:$B$107,"<="&$C$4) -> 25 | I20: =Config!$C$12 -> 50
B21: ="Avaliações realizadas — "&Config!$B$5 -> Avaliações realizadas — Ariosto | C21: =IFERROR(INDEX(Resumo_Semanal!$H$4:$H$107,MATCH($C$3,Resumo_Semanal!$A$4:$A$107,0)),"") -> 8 | D21: =IFERROR(INDEX(Resumo_Semanal!$H$4:$H$107,MATCH($E$3,Resumo_Semanal!$A$4:$A$107,0)),"") -> 6 | E21: =IF(OR(C21="",D21=""),"",C21-D21) -> 2 | H21: =SUMIFS(Resumo_Semanal!$H$4:$H$107,Resumo_Semanal!$D$4:$D$107,$C$5,Resumo_Semanal!$B$4:$B$107,"<="&$C$4) -> 14
B22: ="Avaliações realizadas — "&Config!$B$6 -> Avaliações realizadas — Tássia | C22: =IFERROR(INDEX(Resumo_Semanal!$I$4:$I$107,MATCH($C$3,Resumo_Semanal!$A$4:$A$107,0)),"") -> 6 | D22: =IFERROR(INDEX(Resumo_Semanal!$I$4:$I$107,MATCH($E$3,Resumo_Semanal!$A$4:$A$107,0)),"") -> 5 | E22: =IF(OR(C22="",D22=""),"",C22-D22) -> 1 | H22: =SUMIFS(Resumo_Semanal!$I$4:$I$107,Resumo_Semanal!$D$4:$D$107,$C$5,Resumo_Semanal!$B$4:$B$107,"<="&$C$4) -> 11
B23: Tratamentos contratados — total | C23: =IFERROR(INDEX(Resumo_Semanal!$N$4:$N$107,MATCH($C$3,Resumo_Semanal!$A$4:$A$107,0)),"") -> 10 | D23: =IFERROR(INDEX(Resumo_Semanal!$N$4:$N$107,MATCH($E$3,Resumo_Semanal!$A$4:$A$107,0)),"") -> 7 | E23: =IF(OR(C23="",D23=""),"",C23-D23) -> 3 | F23: =Config!$B$13 -> 8 | G23: =IF(OR(C23="",F23=0),"",C23/F23) -> 1.25 | H23: =SUMIFS(Resumo_Semanal!$N$4:$N$107,Resumo_Semanal!$D$4:$D$107,$C$5,Resumo_Semanal!$B$4:$B$107,"<="&$C$4) -> 17 | I23: =Config!$C$13 -> 32
B24: ="Tratamentos contratados — "&Config!$B$5 -> Tratamentos contratados — Ariosto | C24: =IFERROR(INDEX(Resumo_Semanal!$L$4:$L$107,MATCH($C$3,Resumo_Semanal!$A$4:$A$107,0)),"") -> 6 | D24: =IFERROR(INDEX(Resumo_Semanal!$L$4:$L$107,MATCH($E$3,Resumo_Semanal!$A$4:$A$107,0)),"") -> 4 | E24: =IF(OR(C24="",D24=""),"",C24-D24) -> 2 | H24: =SUMIFS(Resumo_Semanal!$L$4:$L$107,Resumo_Semanal!$D$4:$D$107,$C$5,Resumo_Semanal!$B$4:$B$107,"<="&$C$4) -> 10
B25: ="Tratamentos contratados — "&Config!$B$6 -> Tratamentos contratados — Tássia | C25: =IFERROR(INDEX(Resumo_Semanal!$M$4:$M$107,MATCH($C$3,Resumo_Semanal!$A$4:$A$107,0)),"") -> 4 | D25: =IFERROR(INDEX(Resumo_Semanal!$M$4:$M$107,MATCH($E$3,Resumo_Semanal!$A$4:$A$107,0)),"") -> 3 | E25: =IF(OR(C25="",D25=""),"",C25-D25) -> 1 | H25: =SUMIFS(Resumo_Semanal!$M$4:$M$107,Resumo_Semanal!$D$4:$D$107,$C$5,Resumo_Semanal!$B$4:$B$107,"<="&$C$4) -> 7
B26: Conversão avaliação → contrato | C26: =IFERROR(INDEX(Resumo_Semanal!$O$4:$O$107,MATCH($C$3,Resumo_Semanal!$A$4:$A$107,0)),"") -> 0.71428571 | D26: =IFERROR(INDEX(Resumo_Semanal!$O$4:$O$107,MATCH($E$3,Resumo_Semanal!$A$4:$A$107,0)),"") -> 0.63636364 | E26: =IF(OR(C26="",D26=""),"",C26-D26) -> 0.077922078 | F26: =Config!$B$19 -> 0.6 | G26: =IF(OR(C26="",F26=0),"",C26/F26) -> 1.1904762 | I26: =Config!$C$19 -> 0.6
B27: Avaliações contratadas (qtd) | C27: =IFERROR(INDEX(Resumo_Semanal!$AB$4:$AB$107,MATCH($C$3,Resumo_Semanal!$A$4:$A$107,0)),"") -> 2 | D27: =IFERROR(INDEX(Resumo_Semanal!$AB$4:$AB$107,MATCH($E$3,Resumo_Semanal!$A$4:$A$107,0)),"") -> 1 | E27: =IF(OR(C27="",D27=""),"",C27-D27) -> 1 | H27: =SUMIFS(Resumo_Semanal!$AB$4:$AB$107,Resumo_Semanal!$D$4:$D$107,$C$5,Resumo_Semanal!$B$4:$B$107,"<="&$C$4) -> 3
B28: Valor de avaliações contratadas | C28: =IFERROR(INDEX(Resumo_Semanal!$AC$4:$AC$107,MATCH($C$3,Resumo_Semanal!$A$4:$A$107,0)),"") -> 300 | D28: =IFERROR(INDEX(Resumo_Semanal!$AC$4:$AC$107,MATCH($E$3,Resumo_Semanal!$A$4:$A$107,0)),"") -> 150 | E28: =IF(OR(C28="",D28=""),"",C28-D28) -> 150 | H28: =SUMIFS(Resumo_Semanal!$AC$4:$AC$107,Resumo_Semanal!$D$4:$D$107,$C$5,Resumo_Semanal!$B$4:$B$107,"<="&$C$4) -> 450
B29: Protocolos contratados (qtd) | C29: =IFERROR(INDEX(Resumo_Semanal!$AD$4:$AD$107,MATCH($C$3,Resumo_Semanal!$A$4:$A$107,0)),"") -> 2 | D29: =IFERROR(INDEX(Resumo_Semanal!$AD$4:$AD$107,MATCH($E$3,Resumo_Semanal!$A$4:$A$107,0)),"") -> 2 | E29: =IF(OR(C29="",D29=""),"",C29-D29) -> 0 | H29: =SUMIFS(Resumo_Semanal!$AD$4:$AD$107,Resumo_Semanal!$D$4:$D$107,$C$5,Resumo_Semanal!$B$4:$B$107,"<="&$C$4) -> 4
B30: Valor de protocolos contratados | C30: =IFERROR(INDEX(Resumo_Semanal!$AE$4:$AE$107,MATCH($C$3,Resumo_Semanal!$A$4:$A$107,0)),"") -> 6800 | D30: =IFERROR(INDEX(Resumo_Semanal!$AE$4:$AE$107,MATCH($E$3,Resumo_Semanal!$A$4:$A$107,0)),"") -> 6200 | E30: =IF(OR(C30="",D30=""),"",C30-D30) -> 600 | H30: =SUMIFS(Resumo_Semanal!$AE$4:$AE$107,Resumo_Semanal!$D$4:$D$107,$C$5,Resumo_Semanal!$B$4:$B$107,"<="&$C$4) -> 13000
B31: Contratos à vista (qtd) | C31: =IFERROR(INDEX(Resumo_Semanal!$AG$4:$AG$107,MATCH($C$3,Resumo_Semanal!$A$4:$A$107,0)),"") -> 2 | D31: =IFERROR(INDEX(Resumo_Semanal!$AG$4:$AG$107,MATCH($E$3,Resumo_Semanal!$A$4:$A$107,0)),"") -> 2 | E31: =IF(OR(C31="",D31=""),"",C31-D31) -> 0 | H31: =SUMIFS(Resumo_Semanal!$AG$4:$AG$107,Resumo_Semanal!$D$4:$D$107,$C$5,Resumo_Semanal!$B$4:$B$107,"<="&$C$4) -> 4
B32: Contratos parcelados (qtd) | C32: =IFERROR(INDEX(Resumo_Semanal!$AH$4:$AH$107,MATCH($C$3,Resumo_Semanal!$A$4:$A$107,0)),"") -> 2 | D32: =IFERROR(INDEX(Resumo_Semanal!$AH$4:$AH$107,MATCH($E$3,Resumo_Semanal!$A$4:$A$107,0)),"") -> 1 | E32: =IF(OR(C32="",D32=""),"",C32-D32) -> 1 | H32: =SUMIFS(Resumo_Semanal!$AH$4:$AH$107,Resumo_Semanal!$D$4:$D$107,$C$5,Resumo_Semanal!$B$4:$B$107,"<="&$C$4) -> 3
B34: Meios de comunicação de ingresso (leads por canal)
B35: Canal | C35: Semana atual | D35: Semana anterior | E35: Variação | F35: % do total (atual)
B36: =Config!$I$10 -> Instagram | C36: =SUMIFS(Leads_Canal!$C$4:$C$503,Leads_Canal!$A$4:$A$503,$C$3,Leads_Canal!$B$4:$B$503,Config!$I$10) -> 20 | D36: =SUMIFS(Leads_Canal!$C$4:$C$503,Leads_Canal!$A$4:$A$503,$E$3,Leads_Canal!$B$4:$B$503,Config!$I$10) -> 16 | E36: =C36-D36 -> 4 | F36: =IF(SUM($C$36:$C$44)=0,"",C36/SUM($C$36:$C$44)) -> 0.44444444
B37: =Config!$I$11 -> Google | C37: =SUMIFS(Leads_Canal!$C$4:$C$503,Leads_Canal!$A$4:$A$503,$C$3,Leads_Canal!$B$4:$B$503,Config!$I$11) -> 12 | D37: =SUMIFS(Leads_Canal!$C$4:$C$503,Leads_Canal!$A$4:$A$503,$E$3,Leads_Canal!$B$4:$B$503,Config!$I$11) -> 10 | E37: =C37-D37 -> 2 | F37: =IF(SUM($C$36:$C$44)=0,"",C37/SUM($C$36:$C$44)) -> 0.26666667
B38: =Config!$I$12 -> WhatsApp direto | C38: =SUMIFS(Leads_Canal!$C$4:$C$503,Leads_Canal!$A$4:$A$503,$C$3,Leads_Canal!$B$4:$B$503,Config!$I$12) -> 5 | D38: =SUMIFS(Leads_Canal!$C$4:$C$503,Leads_Canal!$A$4:$A$503,$E$3,Leads_Canal!$B$4:$B$503,Config!$I$12) -> 5 | E38: =C38-D38 -> 0 | F38: =IF(SUM($C$36:$C$44)=0,"",C38/SUM($C$36:$C$44)) -> 0.11111111
B39: =Config!$I$13 -> Indicação | C39: =SUMIFS(Leads_Canal!$C$4:$C$503,Leads_Canal!$A$4:$A$503,$C$3,Leads_Canal!$B$4:$B$503,Config!$I$13) -> 8 | D39: =SUMIFS(Leads_Canal!$C$4:$C$503,Leads_Canal!$A$4:$A$503,$E$3,Leads_Canal!$B$4:$B$503,Config!$I$13) -> 7 | E39: =C39-D39 -> 1 | F39: =IF(SUM($C$36:$C$44)=0,"",C39/SUM($C$36:$C$44)) -> 0.17777778
B40: =Config!$I$14 -> Facebook | C40: =SUMIFS(Leads_Canal!$C$4:$C$503,Leads_Canal!$A$4:$A$503,$C$3,Leads_Canal!$B$4:$B$503,Config!$I$14) -> 0 | D40: =SUMIFS(Leads_Canal!$C$4:$C$503,Leads_Canal!$A$4:$A$503,$E$3,Leads_Canal!$B$4:$B$503,Config!$I$14) -> 0 | E40: =C40-D40 -> 0 | F40: =IF(SUM($C$36:$C$44)=0,"",C40/SUM($C$36:$C$44)) -> 0
B41: =Config!$I$15 -> Site | C41: =SUMIFS(Leads_Canal!$C$4:$C$503,Leads_Canal!$A$4:$A$503,$C$3,Leads_Canal!$B$4:$B$503,Config!$I$15) -> 0 | D41: =SUMIFS(Leads_Canal!$C$4:$C$503,Leads_Canal!$A$4:$A$503,$E$3,Leads_Canal!$B$4:$B$503,Config!$I$15) -> 0 | E41: =C41-D41 -> 0 | F41: =IF(SUM($C$36:$C$44)=0,"",C41/SUM($C$36:$C$44)) -> 0
B42: =Config!$I$16 -> Convênio/Parceria | C42: =SUMIFS(Leads_Canal!$C$4:$C$503,Leads_Canal!$A$4:$A$503,$C$3,Leads_Canal!$B$4:$B$503,Config!$I$16) -> 0 | D42: =SUMIFS(Leads_Canal!$C$4:$C$503,Leads_Canal!$A$4:$A$503,$E$3,Leads_Canal!$B$4:$B$503,Config!$I$16) -> 0 | E42: =C42-D42 -> 0 | F42: =IF(SUM($C$36:$C$44)=0,"",C42/SUM($C$36:$C$44)) -> 0
B43: =Config!$I$17 -> Passante/Fachada | C43: =SUMIFS(Leads_Canal!$C$4:$C$503,Leads_Canal!$A$4:$A$503,$C$3,Leads_Canal!$B$4:$B$503,Config!$I$17) -> 0 | D43: =SUMIFS(Leads_Canal!$C$4:$C$503,Leads_Canal!$A$4:$A$503,$E$3,Leads_Canal!$B$4:$B$503,Config!$I$17) -> 0 | E43: =C43-D43 -> 0 | F43: =IF(SUM($C$36:$C$44)=0,"",C43/SUM($C$36:$C$44)) -> 0
B44: =Config!$I$18 -> Outro | C44: =SUMIFS(Leads_Canal!$C$4:$C$503,Leads_Canal!$A$4:$A$503,$C$3,Leads_Canal!$B$4:$B$503,Config!$I$18) -> 0 | D44: =SUMIFS(Leads_Canal!$C$4:$C$503,Leads_Canal!$A$4:$A$503,$E$3,Leads_Canal!$B$4:$B$503,Config!$I$18) -> 0 | E44: =C44-D44 -> 0 | F44: =IF(SUM($C$36:$C$44)=0,"",C44/SUM($C$36:$C$44)) -> 0
B46: 3. AGENDA E ATENDIMENTOS
B47: Indicador | C47: Semana atual | D47: Semana anterior | E47: Variação | F47: Meta semanal | G47: % da meta | H47: Acumulado no mês | I47: Meta mensal
B48: ="Atendimentos realizados — "&Config!$B$5 -> Atendimentos realizados — Ariosto | C48: =IFERROR(INDEX(Resumo_Semanal!$P$4:$P$107,MATCH($C$3,Resumo_Semanal!$A$4:$A$107,0)),"") -> 63 | D48: =IFERROR(INDEX(Resumo_Semanal!$P$4:$P$107,MATCH($E$3,Resumo_Semanal!$A$4:$A$107,0)),"") -> 58 | E48: =IF(OR(C48="",D48=""),"",C48-D48) -> 5 | H48: =SUMIFS(Resumo_Semanal!$P$4:$P$107,Resumo_Semanal!$D$4:$D$107,$C$5,Resumo_Semanal!$B$4:$B$107,"<="&$C$4) -> 121
B49: ="Atendimentos realizados — "&Config!$B$6 -> Atendimentos realizados — Tássia | C49: =IFERROR(INDEX(Resumo_Semanal!$Q$4:$Q$107,MATCH($C$3,Resumo_Semanal!$A$4:$A$107,0)),"") -> 57 | D49: =IFERROR(INDEX(Resumo_Semanal!$Q$4:$Q$107,MATCH($E$3,Resumo_Semanal!$A$4:$A$107,0)),"") -> 52 | E49: =IF(OR(C49="",D49=""),"",C49-D49) -> 5 | H49: =SUMIFS(Resumo_Semanal!$Q$4:$Q$107,Resumo_Semanal!$D$4:$D$107,$C$5,Resumo_Semanal!$B$4:$B$107,"<="&$C$4) -> 109
B50: Atendimentos realizados — total | C50: =IFERROR(INDEX(Resumo_Semanal!$R$4:$R$107,MATCH($C$3,Resumo_Semanal!$A$4:$A$107,0)),"") -> 120 | D50: =IFERROR(INDEX(Resumo_Semanal!$R$4:$R$107,MATCH($E$3,Resumo_Semanal!$A$4:$A$107,0)),"") -> 110 | E50: =IF(OR(C50="",D50=""),"",C50-D50) -> 10 | F50: =Config!$B$14 -> 120 | G50: =IF(OR(C50="",F50=0),"",C50/F50) -> 1 | H50: =SUMIFS(Resumo_Semanal!$R$4:$R$107,Resumo_Semanal!$D$4:$D$107,$C$5,Resumo_Semanal!$B$4:$B$107,"<="&$C$4) -> 230 | I50: =Config!$C$14 -> 500
B51: Cancelamentos de atendimentos | C51: =IFERROR(INDEX(Resumo_Semanal!$S$4:$S$107,MATCH($C$3,Resumo_Semanal!$A$4:$A$107,0)),"") -> 5 | D51: =IFERROR(INDEX(Resumo_Semanal!$S$4:$S$107,MATCH($E$3,Resumo_Semanal!$A$4:$A$107,0)),"") -> 7 | E51: =IF(OR(C51="",D51=""),"",C51-D51) -> -2 | H51: =SUMIFS(Resumo_Semanal!$S$4:$S$107,Resumo_Semanal!$D$4:$D$107,$C$5,Resumo_Semanal!$B$4:$B$107,"<="&$C$4) -> 12
B52: Taxa de ocupação — manhã | C52: =IFERROR(INDEX(Resumo_Semanal!$U$4:$U$107,MATCH($C$3,Resumo_Semanal!$A$4:$A$107,0)),"") -> 0.95 | D52: =IFERROR(INDEX(Resumo_Semanal!$U$4:$U$107,MATCH($E$3,Resumo_Semanal!$A$4:$A$107,0)),"") -> 0.9 | E52: =IF(OR(C52="",D52=""),"",C52-D52) -> 0.05 | F52: =Config!$B$15 -> 0.85 | G52: =IF(OR(C52="",F52=0),"",C52/F52) -> 1.1176471 | I52: =Config!$C$15 -> 0.85
B53: Taxa de ocupação — tarde | C53: =IFERROR(INDEX(Resumo_Semanal!$V$4:$V$107,MATCH($C$3,Resumo_Semanal!$A$4:$A$107,0)),"") -> 0.91666667 | D53: =IFERROR(INDEX(Resumo_Semanal!$V$4:$V$107,MATCH($E$3,Resumo_Semanal!$A$4:$A$107,0)),"") -> 0.83333333 | E53: =IF(OR(C53="",D53=""),"",C53-D53) -> 0.083333333 | F53: =Config!$B$15 -> 0.85 | G53: =IF(OR(C53="",F53=0),"",C53/F53) -> 1.0784314 | I53: =Config!$C$15 -> 0.85
B54: Taxa de ocupação — total | C54: =IFERROR(INDEX(Resumo_Semanal!$W$4:$W$107,MATCH($C$3,Resumo_Semanal!$A$4:$A$107,0)),"") -> 0.93333333 | D54: =IFERROR(INDEX(Resumo_Semanal!$W$4:$W$107,MATCH($E$3,Resumo_Semanal!$A$4:$A$107,0)),"") -> 0.86666667 | E54: =IF(OR(C54="",D54=""),"",C54-D54) -> 0.066666667 | F54: =Config!$B$15 -> 0.85 | G54: =IF(OR(C54="",F54=0),"",C54/F54) -> 1.0980392 | I54: =Config!$C$15 -> 0.85
B55: ="Tempo médio de atendimento (min) — "&Config!$B$5 -> Tempo médio de atendimento (min) — Ariosto | C55: =IFERROR(INDEX(Resumo_Semanal!$X$4:$X$107,MATCH($C$3,Resumo_Semanal!$A$4:$A$107,0)),"") -> 41.2 | D55: =IFERROR(INDEX(Resumo_Semanal!$X$4:$X$107,MATCH($E$3,Resumo_Semanal!$A$4:$A$107,0)),"") -> 42.5 | E55: =IF(OR(C55="",D55=""),"",C55-D55) -> -1.3
B56: ="Desvio padrão (min) — "&Config!$B$5 -> Desvio padrão (min) — Ariosto | C56: =IFERROR(INDEX(Resumo_Semanal!$Y$4:$Y$107,MATCH($C$3,Resumo_Semanal!$A$4:$A$107,0)),"") -> 5.8 | D56: =IFERROR(INDEX(Resumo_Semanal!$Y$4:$Y$107,MATCH($E$3,Resumo_Semanal!$A$4:$A$107,0)),"") -> 6.1 | E56: =IF(OR(C56="",D56=""),"",C56-D56) -> -0.3
B57: ="Tempo médio de atendimento (min) — "&Config!$B$6 -> Tempo médio de atendimento (min) — Tássia | C57: =IFERROR(INDEX(Resumo_Semanal!$Z$4:$Z$107,MATCH($C$3,Resumo_Semanal!$A$4:$A$107,0)),"") -> 40.5 | D57: =IFERROR(INDEX(Resumo_Semanal!$Z$4:$Z$107,MATCH($E$3,Resumo_Semanal!$A$4:$A$107,0)),"") -> 39.8 | E57: =IF(OR(C57="",D57=""),"",C57-D57) -> 0.7
B58: ="Desvio padrão (min) — "&Config!$B$6 -> Desvio padrão (min) — Tássia | C58: =IFERROR(INDEX(Resumo_Semanal!$AA$4:$AA$107,MATCH($C$3,Resumo_Semanal!$A$4:$A$107,0)),"") -> 4.9 | D58: =IFERROR(INDEX(Resumo_Semanal!$AA$4:$AA$107,MATCH($E$3,Resumo_Semanal!$A$4:$A$107,0)),"") -> 5.4 | E58: =IF(OR(C58="",D58=""),"",C58-D58) -> -0.5
B60: 4. INDICADORES FINANCEIROS
B61: Indicador | C61: Semana atual | D61: Semana anterior | E61: Variação | F61: Meta semanal | G61: % da meta | H61: Acumulado no mês | I61: Meta mensal
B62: Receita semanal | C62: =IFERROR(INDEX(Resumo_Semanal!$AI$4:$AI$107,MATCH($C$3,Resumo_Semanal!$A$4:$A$107,0)),"") -> 2860 | D62: =IFERROR(INDEX(Resumo_Semanal!$AI$4:$AI$107,MATCH($E$3,Resumo_Semanal!$A$4:$A$107,0)),"") -> 3183.33 | E62: =IF(OR(C62="",D62=""),"",C62-D62) -> -323.33 | F62: =Config!$B$16 -> 30000 | G62: =IF(OR(C62="",F62=0),"",C62/F62) -> 0.095333333 | H62: =SUMIFS(Resumo_Semanal!$AI$4:$AI$107,Resumo_Semanal!$D$4:$D$107,$C$5,Resumo_Semanal!$B$4:$B$107,"<="&$C$4) -> 6043.33 | I62: =Config!$C$16 -> 120000
B63: Gastos semanais | C63: =IFERROR(INDEX(Resumo_Semanal!$AJ$4:$AJ$107,MATCH($C$3,Resumo_Semanal!$A$4:$A$107,0)),"") -> 4880 | D63: =IFERROR(INDEX(Resumo_Semanal!$AJ$4:$AJ$107,MATCH($E$3,Resumo_Semanal!$A$4:$A$107,0)),"") -> 2800 | E63: =IF(OR(C63="",D63=""),"",C63-D63) -> 2080 | F63: =Config!$B$17 -> 18000 | G63: =IF(OR(C63="",F63=0),"",C63/F63) -> 0.27111111 | H63: =SUMIFS(Resumo_Semanal!$AJ$4:$AJ$107,Resumo_Semanal!$D$4:$D$107,$C$5,Resumo_Semanal!$B$4:$B$107,"<="&$C$4) -> 7680 | I63: =Config!$C$17 -> 72000
B64: Impostos | C64: =IFERROR(INDEX(Resumo_Semanal!$AK$4:$AK$107,MATCH($C$3,Resumo_Semanal!$A$4:$A$107,0)),"") -> 1850 | D64: =IFERROR(INDEX(Resumo_Semanal!$AK$4:$AK$107,MATCH($E$3,Resumo_Semanal!$A$4:$A$107,0)),"") -> 0 | E64: =IF(OR(C64="",D64=""),"",C64-D64) -> 1850 | H64: =SUMIFS(Resumo_Semanal!$AK$4:$AK$107,Resumo_Semanal!$D$4:$D$107,$C$5,Resumo_Semanal!$B$4:$B$107,"<="&$C$4) -> 1850
B65: Investimento em marketing | C65: =IFERROR(INDEX(Resumo_Semanal!$AL$4:$AL$107,MATCH($C$3,Resumo_Semanal!$A$4:$A$107,0)),"") -> 700 | D65: =IFERROR(INDEX(Resumo_Semanal!$AL$4:$AL$107,MATCH($E$3,Resumo_Semanal!$A$4:$A$107,0)),"") -> 600 | E65: =IF(OR(C65="",D65=""),"",C65-D65) -> 100 | F65: =Config!$B$18 -> 2500 | G65: =IF(OR(C65="",F65=0),"",C65/F65) -> 0.28 | H65: =SUMIFS(Resumo_Semanal!$AL$4:$AL$107,Resumo_Semanal!$D$4:$D$107,$C$5,Resumo_Semanal!$B$4:$B$107,"<="&$C$4) -> 1300 | I65: =Config!$C$18 -> 10000
B66: Resultado (receita − gastos − impostos − marketing) | C66: =IFERROR(INDEX(Resumo_Semanal!$AM$4:$AM$107,MATCH($C$3,Resumo_Semanal!$A$4:$A$107,0)),"") -> -4570 | D66: =IFERROR(INDEX(Resumo_Semanal!$AM$4:$AM$107,MATCH($E$3,Resumo_Semanal!$A$4:$A$107,0)),"") -> -216.67 | E66: =IF(OR(C66="",D66=""),"",C66-D66) -> -4353.33 | H66: =SUMIFS(Resumo_Semanal!$AM$4:$AM$107,Resumo_Semanal!$D$4:$D$107,$C$5,Resumo_Semanal!$B$4:$B$107,"<="&$C$4) -> -4786.67
B67: CAC (marketing / novos pacientes) | C67: =IFERROR(INDEX(Resumo_Semanal!$AP$4:$AP$107,MATCH($C$3,Resumo_Semanal!$A$4:$A$107,0)),"") -> 77.777778 | D67: =IFERROR(INDEX(Resumo_Semanal!$AP$4:$AP$107,MATCH($E$3,Resumo_Semanal!$A$4:$A$107,0)),"") -> 100 | E67: =IF(OR(C67="",D67=""),"",C67-D67) -> -22.222222
B68: Pendências — receitas a receber (status Pendente) | C68: =SUMIFS(Financeiro!$G$4:$G$503,Financeiro!$D$4:$D$503,"Receita",Financeiro!$H$4:$H$503,"Pendente") -> 950 | D68: =COUNTIFS(Financeiro!$D$4:$D$503,"Receita",Financeiro!$H$4:$H$503,"Pendente")&" lançamento(s)" -> 1 lançamento(s)
B69: Inadimplência — receitas em atraso (status Atrasado) | C69: =SUMIFS(Financeiro!$G$4:$G$503,Financeiro!$D$4:$D$503,"Receita",Financeiro!$H$4:$H$503,"Atrasado") -> 760 | D69: =COUNTIFS(Financeiro!$D$4:$D$503,"Receita",Financeiro!$H$4:$H$503,"Atrasado")&" lançamento(s)" -> 1 lançamento(s)
B70: Pendências e inadimplência consideram todos os lançamentos em aberto, independentemente da semana.
B72: 5. EXPERIÊNCIA DO PACIENTE
B73: Pacientes críticos | riscos de desistência | C73: =IFERROR(INDEX(Reuniao_Semanal!$E$4:$E$203,MATCH($C$3,Reuniao_Semanal!$A$4:$A$203,0)),"") -> Roberto A. — 2 faltas seguidas e parcela em atraso; Ana R. — reclamou de espera
B74: Pontos pertinentes | C74: =IFERROR(INDEX(Reuniao_Semanal!$F$4:$F$203,MATCH($C$3,Reuniao_Semanal!$A$4:$A$203,0)),"") -> Pacientes elogiaram o novo protocolo de alongamento
B75: Problemas no atendimento | C75: =IFERROR(INDEX(Reuniao_Semanal!$G$4:$G$203,MATCH($C$3,Reuniao_Semanal!$A$4:$A$203,0)),"") -> Espera de 15 min na recepção em dois dias (acúmulo às 8h)
B76: Existe algo prejudicando a experiência do paciente? | C76: =IFERROR(INDEX(Reuniao_Semanal!$H$4:$H$203,MATCH($C$3,Reuniao_Semanal!$A$4:$A$203,0)),"") -> Sim
B77: Descrição | C77: =IFERROR(INDEX(Reuniao_Semanal!$I$4:$I$203,MATCH($C$3,Reuniao_Semanal!$A$4:$A$203,0)),"") -> Atraso na abertura da recepção às 7h50
B79: 6. OPERAÇÃO DA SEMANA | PRÓXIMA SEMANA
B80: Agenda da próxima semana | C80: Ocupação já agendada | D80: Meta
B81: Taxa de ocupação — manhã | C81: =IFERROR(INDEX(Resumo_Semanal!$U$4:$U$107,MATCH($G$3,Resumo_Semanal!$A$4:$A$107,0)),"") -> 0.73333333 | D81: =Config!$B$15 -> 0.85
B82: Taxa de ocupação — tarde | C82: =IFERROR(INDEX(Resumo_Semanal!$V$4:$V$107,MATCH($G$3,Resumo_Semanal!$A$4:$A$107,0)),"") -> 0.63333333 | D82: =Config!$B$15 -> 0.85
B83: Taxa de ocupação — total | C83: =IFERROR(INDEX(Resumo_Semanal!$W$4:$W$107,MATCH($G$3,Resumo_Semanal!$A$4:$A$107,0)),"") -> 0.68333333 | D83: =Config!$B$15 -> 0.85
B84: Preencha os horários disponíveis/ocupados da próxima semana na Base_Semanal para ver a ocupação já agendada.
B85: Demandas da recepção e equipe | C85: =IFERROR(INDEX(Reuniao_Semanal!$J$4:$J$203,MATCH($C$3,Reuniao_Semanal!$A$4:$A$203,0)),"") -> Recepção pede roteiro de confirmação de consulta por WhatsApp
B86: Pontos relevantes | C86: =IFERROR(INDEX(Reuniao_Semanal!$K$4:$K$203,MATCH($C$3,Reuniao_Semanal!$A$4:$A$203,0)),"") -> Agenda da manhã já com 73% ocupada; reforçar captação para a tarde
B88: 7. O QUE MAIS OCORRER
B89: Outros pontos | C89: =IFERROR(INDEX(Reuniao_Semanal!$L$4:$L$203,MATCH($C$3,Reuniao_Semanal!$A$4:$A$203,0)),"") -> Manutenção do ar-condicionado da sala 2 agendada para quinta
B91: 8. PLANO DE AÇÃO
B92: Metas da semana | C92: =IFERROR(INDEX(Reuniao_Semanal!$M$4:$M$203,MATCH($C$3,Reuniao_Semanal!$A$4:$A$203,0)),"") -> Receita R$ 32.000; 10 avaliações; ocupação total ≥ 85%
B93: Soluções para os problemas identificados | C93: =IFERROR(INDEX(Reuniao_Semanal!$N$4:$N$203,MATCH($C$3,Reuniao_Semanal!$A$4:$A$203,0)),"") -> Confirmação de consulta 24h antes por WhatsApp; escala da recepção a partir de 7h40
B94: Ações para executar (5W2H) — até 8 ações da semana; lista completa na aba Plano_Acao
B95: Problema / meta | C95: O quê | D95: Por quê | E95: Onde | F95: Quando | G95: Quem | H95: Como | I95: Status
B96: =IFERROR(INDEX(Plano_Acao!$C$4:$C$503,MATCH($C$3&"-1",Plano_Acao!$L$4:$L$503,0)),"") -> Espera na recepção às 8h | C96: =IFERROR(INDEX(Plano_Acao!$D$4:$D$503,MATCH($C$3&"-1",Plano_Acao!$L$4:$L$503,0)),"") -> Antecipar abertura da recepção | D96: =IFERROR(INDEX(Plano_Acao!$E$4:$E$503,MATCH($C$3&"-1",Plano_Acao!$L$4:$L$503,0)),"") -> Reduzir espera e reclamações | E96: =IFERROR(INDEX(Plano_Acao!$F$4:$F$503,MATCH($C$3&"-1",Plano_Acao!$L$4:$L$503,0)),"") -> Recepção | F96: =IFERROR(INDEX(Plano_Acao!$G$4:$G$503,MATCH($C$3&"-1",Plano_Acao!$L$4:$L$503,0)),"") -> 46301 | G96: =IFERROR(INDEX(Plano_Acao!$H$4:$H$503,MATCH($C$3&"-1",Plano_Acao!$L$4:$L$503,0)),"") -> Recepção | H96: =IFERROR(INDEX(Plano_Acao!$I$4:$I$503,MATCH($C$3&"-1",Plano_Acao!$L$4:$L$503,0)),"") -> Escala iniciando às 7h40; check-in antecipado | I96: =IFERROR(INDEX(Plano_Acao!$K$4:$K$503,MATCH($C$3&"-1",Plano_Acao!$L$4:$L$503,0)),"") -> Em andamento
B97: =IFERROR(INDEX(Plano_Acao!$C$4:$C$503,MATCH($C$3&"-2",Plano_Acao!$L$4:$L$503,0)),"") -> Cancelamentos de atendimento | C97: =IFERROR(INDEX(Plano_Acao!$D$4:$D$503,MATCH($C$3&"-2",Plano_Acao!$L$4:$L$503,0)),"") -> Confirmar consultas 24h antes por WhatsApp | D97: =IFERROR(INDEX(Plano_Acao!$E$4:$E$503,MATCH($C$3&"-2",Plano_Acao!$L$4:$L$503,0)),"") -> Reduzir faltas e liberar horários | E97: =IFERROR(INDEX(Plano_Acao!$F$4:$F$503,MATCH($C$3&"-2",Plano_Acao!$L$4:$L$503,0)),"") -> Recepção | F97: =IFERROR(INDEX(Plano_Acao!$G$4:$G$503,MATCH($C$3&"-2",Plano_Acao!$L$4:$L$503,0)),"") -> 46304 | G97: =IFERROR(INDEX(Plano_Acao!$H$4:$H$503,MATCH($C$3&"-2",Plano_Acao!$L$4:$L$503,0)),"") -> Recepção | H97: =IFERROR(INDEX(Plano_Acao!$I$4:$I$503,MATCH($C$3&"-2",Plano_Acao!$L$4:$L$503,0)),"") -> Modelo de mensagem + lista diária de confirmação | I97: =IFERROR(INDEX(Plano_Acao!$K$4:$K$503,MATCH($C$3&"-2",Plano_Acao!$L$4:$L$503,0)),"") -> A fazer
B98: =IFERROR(INDEX(Plano_Acao!$C$4:$C$503,MATCH($C$3&"-3",Plano_Acao!$L$4:$L$503,0)),"") -> Ocupação da tarde < 90% | C98: =IFERROR(INDEX(Plano_Acao!$D$4:$D$503,MATCH($C$3&"-3",Plano_Acao!$L$4:$L$503,0)),"") -> Campanha de captação para horários da tarde | D98: =IFERROR(INDEX(Plano_Acao!$E$4:$E$503,MATCH($C$3&"-3",Plano_Acao!$L$4:$L$503,0)),"") -> Elevar taxa de ocupação | E98: =IFERROR(INDEX(Plano_Acao!$F$4:$F$503,MATCH($C$3&"-3",Plano_Acao!$L$4:$L$503,0)),"") -> Marketing | F98: =IFERROR(INDEX(Plano_Acao!$G$4:$G$503,MATCH($C$3&"-3",Plano_Acao!$L$4:$L$503,0)),"") -> 46311 | G98: =IFERROR(INDEX(Plano_Acao!$H$4:$H$503,MATCH($C$3&"-3",Plano_Acao!$L$4:$L$503,0)),"") -> Ariosto | H98: =IFERROR(INDEX(Plano_Acao!$I$4:$I$503,MATCH($C$3&"-3",Plano_Acao!$L$4:$L$503,0)),"") -> Anúncio segmentado + oferta de avaliação à tarde | I98: =IFERROR(INDEX(Plano_Acao!$K$4:$K$503,MATCH($C$3&"-3",Plano_Acao!$L$4:$L$503,0)),"") -> A fazer
B99: =IFERROR(INDEX(Plano_Acao!$C$4:$C$503,MATCH($C$3&"-4",Plano_Acao!$L$4:$L$503,0)),"") | C99: =IFERROR(INDEX(Plano_Acao!$D$4:$D$503,MATCH($C$3&"-4",Plano_Acao!$L$4:$L$503,0)),"") | D99: =IFERROR(INDEX(Plano_Acao!$E$4:$E$503,MATCH($C$3&"-4",Plano_Acao!$L$4:$L$503,0)),"") | E99: =IFERROR(INDEX(Plano_Acao!$F$4:$F$503,MATCH($C$3&"-4",Plano_Acao!$L$4:$L$503,0)),"") | F99: =IFERROR(INDEX(Plano_Acao!$G$4:$G$503,MATCH($C$3&"-4",Plano_Acao!$L$4:$L$503,0)),"") | G99: =IFERROR(INDEX(Plano_Acao!$H$4:$H$503,MATCH($C$3&"-4",Plano_Acao!$L$4:$L$503,0)),"") | H99: =IFERROR(INDEX(Plano_Acao!$I$4:$I$503,MATCH($C$3&"-4",Plano_Acao!$L$4:$L$503,0)),"") | I99: =IFERROR(INDEX(Plano_Acao!$K$4:$K$503,MATCH($C$3&"-4",Plano_Acao!$L$4:$L$503,0)),"")
B100: =IFERROR(INDEX(Plano_Acao!$C$4:$C$503,MATCH($C$3&"-5",Plano_Acao!$L$4:$L$503,0)),"") | C100: =IFERROR(INDEX(Plano_Acao!$D$4:$D$503,MATCH($C$3&"-5",Plano_Acao!$L$4:$L$503,0)),"") | D100: =IFERROR(INDEX(Plano_Acao!$E$4:$E$503,MATCH($C$3&"-5",Plano_Acao!$L$4:$L$503,0)),"") | E100: =IFERROR(INDEX(Plano_Acao!$F$4:$F$503,MATCH($C$3&"-5",Plano_Acao!$L$4:$L$503,0)),"") | F100: =IFERROR(INDEX(Plano_Acao!$G$4:$G$503,MATCH($C$3&"-5",Plano_Acao!$L$4:$L$503,0)),"") | G100: =IFERROR(INDEX(Plano_Acao!$H$4:$H$503,MATCH($C$3&"-5",Plano_Acao!$L$4:$L$503,0)),"") | H100: =IFERROR(INDEX(Plano_Acao!$I$4:$I$503,MATCH($C$3&"-5",Plano_Acao!$L$4:$L$503,0)),"") | I100: =IFERROR(INDEX(Plano_Acao!$K$4:$K$503,MATCH($C$3&"-5",Plano_Acao!$L$4:$L$503,0)),"")
B101: =IFERROR(INDEX(Plano_Acao!$C$4:$C$503,MATCH($C$3&"-6",Plano_Acao!$L$4:$L$503,0)),"") | C101: =IFERROR(INDEX(Plano_Acao!$D$4:$D$503,MATCH($C$3&"-6",Plano_Acao!$L$4:$L$503,0)),"") | D101: =IFERROR(INDEX(Plano_Acao!$E$4:$E$503,MATCH($C$3&"-6",Plano_Acao!$L$4:$L$503,0)),"") | E101: =IFERROR(INDEX(Plano_Acao!$F$4:$F$503,MATCH($C$3&"-6",Plano_Acao!$L$4:$L$503,0)),"") | F101: =IFERROR(INDEX(Plano_Acao!$G$4:$G$503,MATCH($C$3&"-6",Plano_Acao!$L$4:$L$503,0)),"") | G101: =IFERROR(INDEX(Plano_Acao!$H$4:$H$503,MATCH($C$3&"-6",Plano_Acao!$L$4:$L$503,0)),"") | H101: =IFERROR(INDEX(Plano_Acao!$I$4:$I$503,MATCH($C$3&"-6",Plano_Acao!$L$4:$L$503,0)),"") | I101: =IFERROR(INDEX(Plano_Acao!$K$4:$K$503,MATCH($C$3&"-6",Plano_Acao!$L$4:$L$503,0)),"")
B102: =IFERROR(INDEX(Plano_Acao!$C$4:$C$503,MATCH($C$3&"-7",Plano_Acao!$L$4:$L$503,0)),"") | C102: =IFERROR(INDEX(Plano_Acao!$D$4:$D$503,MATCH($C$3&"-7",Plano_Acao!$L$4:$L$503,0)),"") | D102: =IFERROR(INDEX(Plano_Acao!$E$4:$E$503,MATCH($C$3&"-7",Plano_Acao!$L$4:$L$503,0)),"") | E102: =IFERROR(INDEX(Plano_Acao!$F$4:$F$503,MATCH($C$3&"-7",Plano_Acao!$L$4:$L$503,0)),"") | F102: =IFERROR(INDEX(Plano_Acao!$G$4:$G$503,MATCH($C$3&"-7",Plano_Acao!$L$4:$L$503,0)),"") | G102: =IFERROR(INDEX(Plano_Acao!$H$4:$H$503,MATCH($C$3&"-7",Plano_Acao!$L$4:$L$503,0)),"") | H102: =IFERROR(INDEX(Plano_Acao!$I$4:$I$503,MATCH($C$3&"-7",Plano_Acao!$L$4:$L$503,0)),"") | I102: =IFERROR(INDEX(Plano_Acao!$K$4:$K$503,MATCH($C$3&"-7",Plano_Acao!$L$4:$L$503,0)),"")
B103: =IFERROR(INDEX(Plano_Acao!$C$4:$C$503,MATCH($C$3&"-8",Plano_Acao!$L$4:$L$503,0)),"") | C103: =IFERROR(INDEX(Plano_Acao!$D$4:$D$503,MATCH($C$3&"-8",Plano_Acao!$L$4:$L$503,0)),"") | D103: =IFERROR(INDEX(Plano_Acao!$E$4:$E$503,MATCH($C$3&"-8",Plano_Acao!$L$4:$L$503,0)),"") | E103: =IFERROR(INDEX(Plano_Acao!$F$4:$F$503,MATCH($C$3&"-8",Plano_Acao!$L$4:$L$503,0)),"") | F103: =IFERROR(INDEX(Plano_Acao!$G$4:$G$503,MATCH($C$3&"-8",Plano_Acao!$L$4:$L$503,0)),"") | G103: =IFERROR(INDEX(Plano_Acao!$H$4:$H$503,MATCH($C$3&"-8",Plano_Acao!$L$4:$L$503,0)),"") | H103: =IFERROR(INDEX(Plano_Acao!$I$4:$I$503,MATCH($C$3&"-8",Plano_Acao!$L$4:$L$503,0)),"") | I103: =IFERROR(INDEX(Plano_Acao!$K$4:$K$503,MATCH($C$3&"-8",Plano_Acao!$L$4:$L$503,0)),"")

Sheet Config
A1: Configurações, metas e listas
A2: Células amarelas: preencher. As listas alimentam os menus (validação) das abas de coleta.
A4: Equipe
A5: Fisio 1 | B5: Ariosto
A6: Fisio 2 | B6: Tássia
A8: Metas
A9: Indicador | B9: Meta semanal | C9: Meta mensal | E9: Tipo de contrato | F9: Condição de pagamento | G9: Forma de pagamento | H9: Status de pagamento | I9: Canal de ingresso | J9: Categoria financeira | K9: Tipo de custo | L9: Status da ação | M9: Resultado geral | N9: Sim/Não | O9: Fisioterapeuta
A10: Leads recebidos | B10: 40 | C10: 170 | E10: Avaliação | F10: À vista | G10: Pix | H10: Pago | I10: Instagram | J10: Receita | K10: Fixo | L10: A fazer | M10: Melhor | N10: Sim | O10: =$B$5 -> Ariosto
A11: Novos pacientes | B11: 8 | C11: 32 | E11: Protocolo | F11: Parcelado | G11: Dinheiro | H11: Pendente | I11: Google | J11: Gasto | K11: Variável | L11: Em andamento | M11: Igual | N11: Não | O11: =$B$6 -> Tássia
A12: Avaliações realizadas | B12: 12 | C12: 50 | G12: Cartão de débito | H12: Atrasado | I12: WhatsApp direto | J12: Imposto | L12: Concluída | M12: Pior
A13: Contratos fechados (tratamentos) | B13: 8 | C13: 32 | G13: Cartão de crédito | H13: Cancelado | I13: Indicação | J13: Marketing | L13: Cancelada
A14: Atendimentos realizados | B14: 120 | C14: 500 | G14: Boleto | I14: Facebook
A15: Taxa de ocupação da agenda | B15: 0.85 | C15: 0.85 | G15: Transferência | I15: Site
A16: Receita | B16: 30000 | C16: 120000 | G16: Convênio | I16: Convênio/Parceria
A17: Gastos | B17: 18000 | C17: 72000 | I17: Passante/Fachada
A18: Investimento em marketing | B18: 2500 | C18: 10000 | I18: Outro
A19: Conversão avaliação → contrato | B19: 0.6 | C19: 0.6
A20: Taxa máx. de cancelamento de avaliações | B20: 0.15 | C20: 0.15
A21: Metas são valores de referência informados pelo usuário; ajuste conforme o planejamento da clínica.

Sheet Calendario
A1: Calendário de semanas
A2: Semanas ISO (segunda a domingo). O mês da semana é o mês da data de início.
A3: id_semana | B3: Início | C3: Fim | D3: Mês
A4: 2026-S02 | B4: 46027 | C4: 46033 | D4: 2026-01
A5: 2026-S03 | B5: 46034 | C5: 46040 | D5: 2026-01
A6: 2026-S04 | B6: 46041 | C6: 46047 | D6: 2026-01
A7: 2026-S05 | B7: 46048 | C7: 46054 | D7: 2026-01
A8: 2026-S06 | B8: 46055 | C8: 46061 | D8: 2026-02
A9: 2026-S07 | B9: 46062 | C9: 46068 | D9: 2026-02
A10: 2026-S08 | B10: 46069 | C10: 46075 | D10: 2026-02
A11: 2026-S09 | B11: 46076 | C11: 46082 | D11: 2026-02
A12: 2026-S10 | B12: 46083 | C12: 46089 | D12: 2026-03
A13: 2026-S11 | B13: 46090 | C13: 46096 | D13: 2026-03
A14: 2026-S12 | B14: 46097 | C14: 46103 | D14: 2026-03
A15: 2026-S13 | B15: 46104 | C15: 46110 | D15: 2026-03
... A107: 2027-S52 | B107: 46748 | C107: 46754 | D107: 2027-12

Sheet Base_Semanal
A1: Base de dados semanal (coleta)
A2: Preencha as colunas amarelas; uma linha por semana. As três primeiras colunas de datas são automáticas.
A3: id_semana | B3: Início | C3: Fim | D3: Mês | E3: Leads recebidos | F3: Aval. agendadas | G3: Aval. canceladas | H3: Aval. realizadas Fisio 1 | I3: Aval. realizadas Fisio 2 | J3: Contratos fechados Fisio 1 | K3: Contratos fechados Fisio 2 | L3: Atendimentos Fisio 1 | M3: Atendimentos Fisio 2 | N3: Cancelamentos de atendimentos | O3: Novos pacientes | P3: Horários disponíveis manhã | Q3: Horários ocupados manhã | R3: Horários disponíveis tarde | S3: Horários ocupados tarde | T3: Tempo médio atend. Fisio 1 (min) | U3: Desvio padrão Fisio 1 (min) | V3: Tempo médio atend. Fisio 2 (min) | W3: Desvio padrão Fisio 2 (min) | X3: Observações
A4: 2026-S02 | B4: =IFERROR(INDEX(Calendario!$B$4:$B$107,MATCH($A4,Calendario!$A$4:$A$107,0)),"") -> 46027 | C4: =IFERROR(INDEX(Calendario!$C$4:$C$107,MATCH($A4,Calendario!$A$4:$A$107,0)),"") -> 46033 | D4: =IFERROR(INDEX(Calendario!$D$4:$D$107,MATCH($A4,Calendario!$A$4:$A$107,0)),"") -> 2026-01
A5: 2026-S03 | B5: =IFERROR(INDEX(Calendario!$B$4:$B$107,MATCH($A5,Calendario!$A$4:$A$107,0)),"") -> 46034 | C5: =IFERROR(INDEX(Calendario!$C$4:$C$107,MATCH($A5,Calendario!$A$4:$A$107,0)),"") -> 46040 | D5: =IFERROR(INDEX(Calendario!$D$4:$D$107,MATCH($A5,Calendario!$A$4:$A$107,0)),"") -> 2026-01
A6: 2026-S04 | B6: =IFERROR(INDEX(Calendario!$B$4:$B$107,MATCH($A6,Calendario!$A$4:$A$107,0)),"") -> 46041 | C6: =IFERROR(INDEX(Calendario!$C$4:$C$107,MATCH($A6,Calendario!$A$4:$A$107,0)),"") -> 46047 | D6: =IFERROR(INDEX(Calendario!$D$4:$D$107,MATCH($A6,Calendario!$A$4:$A$107,0)),"") -> 2026-01
A7: 2026-S05 | B7: =IFERROR(INDEX(Calendario!$B$4:$B$107,MATCH($A7,Calendario!$A$4:$A$107,0)),"") -> 46048 | C7: =IFERROR(INDEX(Calendario!$C$4:$C$107,MATCH($A7,Calendario!$A$4:$A$107,0)),"") -> 46054 | D7: =IFERROR(INDEX(Calendario!$D$4:$D$107,MATCH($A7,Calendario!$A$4:$A$107,0)),"") -> 2026-01
A8: 2026-S06 | B8: =IFERROR(INDEX(Calendario!$B$4:$B$107,MATCH($A8,Calendario!$A$4:$A$107,0)),"") -> 46055 | C8: =IFERROR(INDEX(Calendario!$C$4:$C$107,MATCH($A8,Calendario!$A$4:$A$107,0)),"") -> 46061 | D8: =IFERROR(INDEX(Calendario!$D$4:$D$107,MATCH($A8,Calendario!$A$4:$A$107,0)),"") -> 2026-02
A9: 2026-S07 | B9: =IFERROR(INDEX(Calendario!$B$4:$B$107,MATCH($A9,Calendario!$A$4:$A$107,0)),"") -> 46062 | C9: =IFERROR(INDEX(Calendario!$C$4:$C$107,MATCH($A9,Calendario!$A$4:$A$107,0)),"") -> 46068 | D9: =IFERROR(INDEX(Calendario!$D$4:$D$107,MATCH($A9,Calendario!$A$4:$A$107,0)),"") -> 2026-02
A10: 2026-S08 | B10: =IFERROR(INDEX(Calendario!$B$4:$B$107,MATCH($A10,Calendario!$A$4:$A$107,0)),"") -> 46069 | C10: =IFERROR(INDEX(Calendario!$C$4:$C$107,MATCH($A10,Calendario!$A$4:$A$107,0)),"") -> 46075 | D10: =IFERROR(INDEX(Calendario!$D$4:$D$107,MATCH($A10,Calendario!$A$4:$A$107,0)),"") -> 2026-02
A11: 2026-S09 | B11: =IFERROR(INDEX(Calendario!$B$4:$B$107,MATCH($A11,Calendario!$A$4:$A$107,0)),"") -> 46076 | C11: =IFERROR(INDEX(Calendario!$C$4:$C$107,MATCH($A11,Calendario!$A$4:$A$107,0)),"") -> 46082 | D11: =IFERROR(INDEX(Calendario!$D$4:$D$107,MATCH($A11,Calendario!$A$4:$A$107,0)),"") -> 2026-02
A12: 2026-S10 | B12: =IFERROR(INDEX(Calendario!$B$4:$B$107,MATCH($A12,Calendario!$A$4:$A$107,0)),"") -> 46083 | C12: =IFERROR(INDEX(Calendario!$C$4:$C$107,MATCH($A12,Calendario!$A$4:$A$107,0)),"") -> 46089 | D12: =IFERROR(INDEX(Calendario!$D$4:$D$107,MATCH($A12,Calendario!$A$4:$A$107,0)),"") -> 2026-03
A13: 2026-S11 | B13: =IFERROR(INDEX(Calendario!$B$4:$B$107,MATCH($A13,Calendario!$A$4:$A$107,0)),"") -> 46090 | C13: =IFERROR(INDEX(Calendario!$C$4:$C$107,MATCH($A13,Calendario!$A$4:$A$107,0)),"") -> 46096 | D13: =IFERROR(INDEX(Calendario!$D$4:$D$107,MATCH($A13,Calendario!$A$4:$A$107,0)),"") -> 2026-03
A14: 2026-S12 | B14: =IFERROR(INDEX(Calendario!$B$4:$B$107,MATCH($A14,Calendario!$A$4:$A$107,0)),"") -> 46097 | C14: =IFERROR(INDEX(Calendario!$C$4:$C$107,MATCH($A14,Calendario!$A$4:$A$107,0)),"") -> 46103 | D14: =IFERROR(INDEX(Calendario!$D$4:$D$107,MATCH($A14,Calendario!$A$4:$A$107,0)),"") -> 2026-03
A15: 2026-S13 | B15: =IFERROR(INDEX(Calendario!$B$4:$B$107,MATCH($A15,Calendario!$A$4:$A$107,0)),"") -> 46104 | C15: =IFERROR(INDEX(Calendario!$C$4:$C$107,MATCH($A15,Calendario!$A$4:$A$107,0)),"") -> 46110 | D15: =IFERROR(INDEX(Calendario!$D$4:$D$107,MATCH($A15,Calendario!$A$4:$A$107,0)),"") -> 2026-03
... A40: 2026-S38 | B40: =IFERROR(INDEX(Calendario!$B$4:$B$107,MATCH($A40,Calendario!$A$4:$A$107,0)),"") -> 46279 | C40: =IFERROR(INDEX(Calendario!$C$4:$C$107,MATCH($A40,Calendario!$A$4:$A$107,0)),"") -> 46285 | D40: =IFERROR(INDEX(Calendario!$D$4:$D$107,MATCH($A40,Calendario!$A$4:$A$107,0)),"") -> 2026-09
A41: 2026-S39 | B41: =IFERROR(INDEX(Calendario!$B$4:$B$107,MATCH($A41,Calendario!$A$4:$A$107,0)),"") -> 46286 | C41: =IFERROR(INDEX(Calendario!$C$4:$C$107,MATCH($A41,Calendario!$A$4:$A$107,0)),"") -> 46292 | D41: =IFERROR(INDEX(Calendario!$D$4:$D$107,MATCH($A41,Calendario!$A$4:$A$107,0)),"") -> 2026-09 | E41: 38 | F41: 14 | G41: 2 | H41: 6 | I41: 5 | J41: 4 | K41: 3 | L41: 58 | M41: 52 | N41: 7 | O41: 6 | P41: 60 | Q41: 54 | R41: 60 | S41: 50 | T41: 42.5 | U41: 6.1 | V41: 39.8 | W41: 5.4 | X41: Exemplo — substitua pelos dados reais
A42: 2026-S40 | B42: =IFERROR(INDEX(Calendario!$B$4:$B$107,MATCH($A42,Calendario!$A$4:$A$107,0)),"") -> 46293 | C42: =IFERROR(INDEX(Calendario!$C$4:$C$107,MATCH($A42,Calendario!$A$4:$A$107,0)),"") -> 46299 | D42: =IFERROR(INDEX(Calendario!$D$4:$D$107,MATCH($A42,Calendario!$A$4:$A$107,0)),"") -> 2026-09 | E42: 45 | F42: 16 | G42: 1 | H42: 8 | I42: 6 | J42: 6 | K42: 4 | L42: 63 | M42: 57 | N42: 5 | O42: 9 | P42: 60 | Q42: 57 | R42: 60 | S42: 55 | T42: 41.2 | U42: 5.8 | V42: 40.5 | W42: 4.9 | X42: Exemplo — substitua pelos dados reais
A43: 2026-S41 | B43: =IFERROR(INDEX(Calendario!$B$4:$B$107,MATCH($A43,Calendario!$A$4:$A$107,0)),"") -> 46300 | C43: =IFERROR(INDEX(Calendario!$C$4:$C$107,MATCH($A43,Calendario!$A$4:$A$107,0)),"") -> 46306 | D43: =IFERROR(INDEX(Calendario!$D$4:$D$107,MATCH($A43,Calendario!$A$4:$A$107,0)),"") -> 2026-10 | P43: 60 | Q43: 44 | R43: 60 | S43: 38 | X43: Exemplo — agenda já ocupada para a próxima semana
A44: 2026-S42 | B44: =IFERROR(INDEX(Calendario!$B$4:$B$107,MATCH($A44,Calendario!$A$4:$A$107,0)),"") -> 46307 | C44: =IFERROR(INDEX(Calendario!$C$4:$C$107,MATCH($A44,Calendario!$A$4:$A$107,0)),"") -> 46313 | D44: =IFERROR(INDEX(Calendario!$D$4:$D$107,MATCH($A44,Calendario!$A$4:$A$107,0)),"") -> 2026-10
A45: 2026-S43 | B45: =IFERROR(INDEX(Calendario!$B$4:$B$107,MATCH($A45,Calendario!$A$4:$A$107,0)),"") -> 46314 | C45: =IFERROR(INDEX(Calendario!$C$4:$C$107,MATCH($A45,Calendario!$A$4:$A$107,0)),"") -> 46320 | D45: =IFERROR(INDEX(Calendario!$D$4:$D$107,MATCH($A45,Calendario!$A$4:$A$107,0)),"") -> 2026-10
A46: 2026-S44 | B46: =IFERROR(INDEX(Calendario!$B$4:$B$107,MATCH($A46,Calendario!$A$4:$A$107,0)),"") -> 46321 | C46: =IFERROR(INDEX(Calendario!$C$4:$C$107,MATCH($A46,Calendario!$A$4:$A$107,0)),"") -> 46327 | D46: =IFERROR(INDEX(Calendario!$D$4:$D$107,MATCH($A46,Calendario!$A$4:$A$107,0)),"") -> 2026-10
A47: 2026-S45 | B47: =IFERROR(INDEX(Calendario!$B$4:$B$107,MATCH($A47,Calendario!$A$4:$A$107,0)),"") -> 46328 | C47: =IFERROR(INDEX(Calendario!$C$4:$C$107,MATCH($A47,Calendario!$A$4:$A$107,0)),"") -> 46334 | D47: =IFERROR(INDEX(Calendario!$D$4:$D$107,MATCH($A47,Calendario!$A$4:$A$107,0)),"") -> 2026-11
A48: 2026-S46 | B48: =IFERROR(INDEX(Calendario!$B$4:$B$107,MATCH($A48,Calendario!$A$4:$A$107,0)),"") -> 46335 | C48: =IFERROR(INDEX(Calendario!$C$4:$C$107,MATCH($A48,Calendario!$A$4:$A$107,0)),"") -> 46341 | D48: =IFERROR(INDEX(Calendario!$D$4:$D$107,MATCH($A48,Calendario!$A$4:$A$107,0)),"") -> 2026-11
A49: 2026-S47 | B49: =IFERROR(INDEX(Calendario!$B$4:$B$107,MATCH($A49,Calendario!$A$4:$A$107,0)),"") -> 46342 | C49: =IFERROR(INDEX(Calendario!$C$4:$C$107,MATCH($A49,Calendario!$A$4:$A$107,0)),"") -> 46348 | D49: =IFERROR(INDEX(Calendario!$D$4:$D$107,MATCH($A49,Calendario!$A$4:$A$107,0)),"") -> 2026-11
A50: 2026-S48 | B50: =IFERROR(INDEX(Calendario!$B$4:$B$107,MATCH($A50,Calendario!$A$4:$A$107,0)),"") -> 46349 | C50: =IFERROR(INDEX(Calendario!$C$4:$C$107,MATCH($A50,Calendario!$A$4:$A$107,0)),"") -> 46355 | D50: =IFERROR(INDEX(Calendario!$D$4:$D$107,MATCH($A50,Calendario!$A$4:$A$107,0)),"") -> 2026-11
A51: 2026-S49 | B51: =IFERROR(INDEX(Calendario!$B$4:$B$107,MATCH($A51,Calendario!$A$4:$A$107,0)),"") -> 46356 | C51: =IFERROR(INDEX(Calendario!$C$4:$C$107,MATCH($A51,Calendario!$A$4:$A$107,0)),"") -> 46362 | D51: =IFERROR(INDEX(Calendario!$D$4:$D$107,MATCH($A51,Calendario!$A$4:$A$107,0)),"") -> 2026-11
A52: 2026-S50 | B52: =IFERROR(INDEX(Calendario!$B$4:$B$107,MATCH($A52,Calendario!$A$4:$A$107,0)),"") -> 46363 | C52: =IFERROR(INDEX(Calendario!$C$4:$C$107,MATCH($A52,Calendario!$A$4:$A$107,0)),"") -> 46369 | D52: =IFERROR(INDEX(Calendario!$D$4:$D$107,MATCH($A52,Calendario!$A$4:$A$107,0)),"") -> 2026-12
A53: 2026-S51 | B53: =IFERROR(INDEX(Calendario!$B$4:$B$107,MATCH($A53,Calendario!$A$4:$A$107,0)),"") -> 46370 | C53: =IFERROR(INDEX(Calendario!$C$4:$C$107,MATCH($A53,Calendario!$A$4:$A$107,0)),"") -> 46376 | D53: =IFERROR(INDEX(Calendario!$D$4:$D$107,MATCH($A53,Calendario!$A$4:$A$107,0)),"") -> 2026-12
A54: 2026-S52 | B54: =IFERROR(INDEX(Calendario!$B$4:$B$107,MATCH($A54,Calendario!$A$4:$A$107,0)),"") -> 46377 | C54: =IFERROR(INDEX(Calendario!$C$4:$C$107,MATCH($A54,Calendario!$A$4:$A$107,0)),"") -> 46383 | D54: =IFERROR(INDEX(Calendario!$D$4:$D$107,MATCH($A54,Calendario!$A$4:$A$107,0)),"") -> 2026-12
A55: 2026-S53 | B55: =IFERROR(INDEX(Calendario!$B$4:$B$107,MATCH($A55,Calendario!$A$4:$A$107,0)),"") -> 46384 | C55: =IFERROR(INDEX(Calendario!$C$4:$C$107,MATCH($A55,Calendario!$A$4:$A$107,0)),"") -> 46390 | D55: =IFERROR(INDEX(Calendario!$D$4:$D$107,MATCH($A55,Calendario!$A$4:$A$107,0)),"") -> 2026-12
... A107: 2027-S52 | B107: =IFERROR(INDEX(Calendario!$B$4:$B$107,MATCH($A107,Calendario!$A$4:$A$107,0)),"") -> 46748 | C107: =IFERROR(INDEX(Calendario!$C$4:$C$107,MATCH($A107,Calendario!$A$4:$A$107,0)),"") -> 46754 | D107: =IFERROR(INDEX(Calendario!$D$4:$D$107,MATCH($A107,Calendario!$A$4:$A$107,0)),"") -> 2027-12

Sheet Contratos
A1: Avaliações e protocolos contratados
A2: Uma linha por contrato fechado. Semana e mês são calculados pela data.
A3: Data | B3: id_semana | C3: Mês | D3: Paciente | E3: Tipo | F3: Fisioterapeuta | G3: Protocolo / descrição | H3: Nº sessões | I3: Valor (R$) | J3: Condição de pagamento | K3: Forma de pagamento | L3: Parcelas | M3: Status pagamento | N3: Canal de ingresso | O3: Observações
A4: 46287 | B4: =IF(A4="","",IFERROR(INDEX(Calendario!$A$4:$A$107,MATCH(A4,Calendario!$B$4:$B$107,1)),"")) -> 2026-S39 | C4: =IF(A4="","",YEAR(A4)&"-"&TEXT(MONTH(A4),"00")) -> 2026-09 | D4: Maria S. (exemplo) | E4: Avaliação | F4: Ariosto | G4: Avaliação inicial coluna | H4: 1 | I4: 150 | J4: À vista | K4: Pix | L4: 1 | M4: Pago | N4: Instagram | O4: Exemplo — substitua pelos dados reais
A5: 46288 | B5: =IF(A5="","",IFERROR(INDEX(Calendario!$A$4:$A$107,MATCH(A5,Calendario!$B$4:$B$107,1)),"")) -> 2026-S39 | C5: =IF(A5="","",YEAR(A5)&"-"&TEXT(MONTH(A5),"00")) -> 2026-09 | D5: João P. (exemplo) | E5: Protocolo | F5: Tássia | G5: Protocolo hérnia lombar — 20 sessões | H5: 20 | I5: 3800 | J5: Parcelado | K5: Cartão de crédito | L5: 6 | M5: Pago | N5: Google | O5: Exemplo — substitua pelos dados reais
A6: 46290 | B6: =IF(A6="","",IFERROR(INDEX(Calendario!$A$4:$A$107,MATCH(A6,Calendario!$B$4:$B$107,1)),"")) -> 2026-S39 | C6: =IF(A6="","",YEAR(A6)&"-"&TEXT(MONTH(A6),"00")) -> 2026-09 | D6: Carla M. (exemplo) | E6: Protocolo | F6: Ariosto | G6: Protocolo cervical — 12 sessões | H6: 12 | I6: 2400 | J6: À vista | K6: Pix | L6: 1 | M6: Pago | N6: Indicação | O6: Exemplo — substitua pelos dados reais
A7: 46294 | B7: =IF(A7="","",IFERROR(INDEX(Calendario!$A$4:$A$107,MATCH(A7,Calendario!$B$4:$B$107,1)),"")) -> 2026-S40 | C7: =IF(A7="","",YEAR(A7)&"-"&TEXT(MONTH(A7),"00")) -> 2026-09 | D7: Pedro L. (exemplo) | E7: Avaliação | F7: Tássia | G7: Avaliação inicial | H7: 1 | I7: 150 | J7: À vista | K7: Dinheiro | L7: 1 | M7: Pago | N7: WhatsApp direto | O7: Exemplo — substitua pelos dados reais
A8: 46295 | B8: =IF(A8="","",IFERROR(INDEX(Calendario!$A$4:$A$107,MATCH(A8,Calendario!$B$4:$B$107,1)),"")) -> 2026-S40 | C8: =IF(A8="","",YEAR(A8)&"-"&TEXT(MONTH(A8),"00")) -> 2026-09 | D8: Ana R. (exemplo) | E8: Protocolo | F8: Ariosto | G8: Protocolo hérnia lombar — 20 sessões | H8: 20 | I8: 3800 | J8: Parcelado | K8: Boleto | L8: 4 | M8: Pendente | N8: Instagram | O8: Exemplo — substitua pelos dados reais
A9: 46296 | B9: =IF(A9="","",IFERROR(INDEX(Calendario!$A$4:$A$107,MATCH(A9,Calendario!$B$4:$B$107,1)),"")) -> 2026-S40 | C9: =IF(A9="","",YEAR(A9)&"-"&TEXT(MONTH(A9),"00")) -> 2026-10 | D9: Lucas F. (exemplo) | E9: Protocolo | F9: Tássia | G9: Protocolo joelho — 16 sessões | H9: 16 | I9: 3000 | J9: Parcelado | K9: Cartão de crédito | L9: 3 | M9: Pago | N9: Indicação | O9: Exemplo — substitua pelos dados reais
A10: 46297 | B10: =IF(A10="","",IFERROR(INDEX(Calendario!$A$4:$A$107,MATCH(A10,Calendario!$B$4:$B$107,1)),"")) -> 2026-S40 | C10: =IF(A10="","",YEAR(A10)&"-"&TEXT(MONTH(A10),"00")) -> 2026-10 | D10: Beatriz C. (exemplo) | E10: Avaliação | F10: Ariosto | G10: Avaliação inicial | H10: 1 | I10: 150 | J10: À vista | K10: Pix | L10: 1 | M10: Pago | N10: Google | O10: Exemplo — substitua pelos dados reais
B11: =IF(A11="","",IFERROR(INDEX(Calendario!$A$4:$A$107,MATCH(A11,Calendario!$B$4:$B$107,1)),"")) | C11: =IF(A11="","",YEAR(A11)&"-"&TEXT(MONTH(A11),"00"))
B12: =IF(A12="","",IFERROR(INDEX(Calendario!$A$4:$A$107,MATCH(A12,Calendario!$B$4:$B$107,1)),"")) | C12: =IF(A12="","",YEAR(A12)&"-"&TEXT(MONTH(A12),"00"))
B13: =IF(A13="","",IFERROR(INDEX(Calendario!$A$4:$A$107,MATCH(A13,Calendario!$B$4:$B$107,1)),"")) | C13: =IF(A13="","",YEAR(A13)&"-"&TEXT(MONTH(A13),"00"))
B14: =IF(A14="","",IFERROR(INDEX(Calendario!$A$4:$A$107,MATCH(A14,Calendario!$B$4:$B$107,1)),"")) | C14: =IF(A14="","",YEAR(A14)&"-"&TEXT(MONTH(A14),"00"))
B15: =IF(A15="","",IFERROR(INDEX(Calendario!$A$4:$A$107,MATCH(A15,Calendario!$B$4:$B$107,1)),"")) | C15: =IF(A15="","",YEAR(A15)&"-"&TEXT(MONTH(A15),"00"))
B16: =IF(A16="","",IFERROR(INDEX(Calendario!$A$4:$A$107,MATCH(A16,Calendario!$B$4:$B$107,1)),"")) | C16: =IF(A16="","",YEAR(A16)&"-"&TEXT(MONTH(A16),"00"))
B17: =IF(A17="","",IFERROR(INDEX(Calendario!$A$4:$A$107,MATCH(A17,Calendario!$B$4:$B$107,1)),"")) | C17: =IF(A17="","",YEAR(A17)&"-"&TEXT(MONTH(A17),"00"))
B18: =IF(A18="","",IFERROR(INDEX(Calendario!$A$4:$A$107,MATCH(A18,Calendario!$B$4:$B$107,1)),"")) | C18: =IF(A18="","",YEAR(A18)&"-"&TEXT(MONTH(A18),"00"))
B19: =IF(A19="","",IFERROR(INDEX(Calendario!$A$4:$A$107,MATCH(A19,Calendario!$B$4:$B$107,1)),"")) | C19: =IF(A19="","",YEAR(A19)&"-"&TEXT(MONTH(A19),"00"))
B20: =IF(A20="","",IFERROR(INDEX(Calendario!$A$4:$A$107,MATCH(A20,Calendario!$B$4:$B$107,1)),"")) | C20: =IF(A20="","",YEAR(A20)&"-"&TEXT(MONTH(A20),"00"))
B21: =IF(A21="","",IFERROR(INDEX(Calendario!$A$4:$A$107,MATCH(A21,Calendario!$B$4:$B$107,1)),"")) | C21: =IF(A21="","",YEAR(A21)&"-"&TEXT(MONTH(A21),"00"))
B22: =IF(A22="","",IFERROR(INDEX(Calendario!$A$4:$A$107,MATCH(A22,Calendario!$B$4:$B$107,1)),"")) | C22: =IF(A22="","",YEAR(A22)&"-"&TEXT(MONTH(A22),"00"))
... B503: =IF(A503="","",IFERROR(INDEX(Calendario!$A$4:$A$107,MATCH(A503,Calendario!$B$4:$B$107,1)),"")) | C503: =IF(A503="","",YEAR(A503)&"-"&TEXT(MONTH(A503),"00"))

Sheet Financeiro
A1: Financeiro (lançamentos)
A2: Uma linha por receita, gasto, imposto ou investimento em marketing. Receitas com status Pendente = pendências; Atrasado = inadimplência.
A3: Data | B3: id_semana | C3: Mês | D3: Categoria | E3: Tipo de custo | F3: Descrição | G3: Valor (R$) | H3: Status | I3: Vencimento | J3: Paciente / fornecedor | K3: Observações
A4: 46287 | B4: =IF(A4="","",IFERROR(INDEX(Calendario!$A$4:$A$107,MATCH(A4,Calendario!$B$4:$B$107,1)),"")) -> 2026-S39 | C4: =IF(A4="","",YEAR(A4)&"-"&TEXT(MONTH(A4),"00")) -> 2026-09 | D4: Receita | F4: Avaliação — Maria S. | G4: 150 | H4: Pago | I4: 46287 | J4: Maria S. | K4: Exemplo — substitua pelos dados reais
A5: 46288 | B5: =IF(A5="","",IFERROR(INDEX(Calendario!$A$4:$A$107,MATCH(A5,Calendario!$B$4:$B$107,1)),"")) -> 2026-S39 | C5: =IF(A5="","",YEAR(A5)&"-"&TEXT(MONTH(A5),"00")) -> 2026-09 | D5: Receita | F5: Protocolo — João P. (1/6) | G5: 633.33 | H5: Pago | I5: 46288 | J5: João P. | K5: Exemplo — substitua pelos dados reais
A6: 46290 | B6: =IF(A6="","",IFERROR(INDEX(Calendario!$A$4:$A$107,MATCH(A6,Calendario!$B$4:$B$107,1)),"")) -> 2026-S39 | C6: =IF(A6="","",YEAR(A6)&"-"&TEXT(MONTH(A6),"00")) -> 2026-09 | D6: Receita | F6: Protocolo — Carla M. | G6: 2400 | H6: Pago | I6: 46290 | J6: Carla M. | K6: Exemplo — substitua pelos dados reais
A7: 46290 | B7: =IF(A7="","",IFERROR(INDEX(Calendario!$A$4:$A$107,MATCH(A7,Calendario!$B$4:$B$107,1)),"")) -> 2026-S39 | C7: =IF(A7="","",YEAR(A7)&"-"&TEXT(MONTH(A7),"00")) -> 2026-09 | D7: Gasto | E7: Fixo | F7: Folha de pagamento — recepção | G7: 2800 | H7: Pago | I7: 46290 | J7: Equipe | K7: Exemplo — substitua pelos dados reais
A8: 46291 | B8: =IF(A8="","",IFERROR(INDEX(Calendario!$A$4:$A$107,MATCH(A8,Calendario!$B$4:$B$107,1)),"")) -> 2026-S39 | C8: =IF(A8="","",YEAR(A8)&"-"&TEXT(MONTH(A8),"00")) -> 2026-09 | D8: Marketing | F8: Impulsionamento Instagram | G8: 600 | H8: Pago | I8: 46291 | J8: Meta Ads | K8: Exemplo — substitua pelos dados reais
A9: 46294 | B9: =IF(A9="","",IFERROR(INDEX(Calendario!$A$4:$A$107,MATCH(A9,Calendario!$B$4:$B$107,1)),"")) -> 2026-S40 | C9: =IF(A9="","",YEAR(A9)&"-"&TEXT(MONTH(A9),"00")) -> 2026-09 | D9: Receita | F9: Avaliação — Pedro L. | G9: 150 | H9: Pago | I9: 46294 | J9: Pedro L. | K9: Exemplo — substitua pelos dados reais
A10: 46295 | B10: =IF(A10="","",IFERROR(INDEX(Calendario!$A$4:$A$107,MATCH(A10,Calendario!$B$4:$B$107,1)),"")) -> 2026-S40 | C10: =IF(A10="","",YEAR(A10)&"-"&TEXT(MONTH(A10),"00")) -> 2026-09 | D10: Receita | F10: Protocolo — Ana R. (1/4) | G10: 950 | H10: Pendente | I10: 46305 | J10: Ana R. | K10: Exemplo — substitua pelos dados reais
A11: 46296 | B11: =IF(A11="","",IFERROR(INDEX(Calendario!$A$4:$A$107,MATCH(A11,Calendario!$B$4:$B$107,1)),"")) -> 2026-S40 | C11: =IF(A11="","",YEAR(A11)&"-"&TEXT(MONTH(A11),"00")) -> 2026-10 | D11: Receita | F11: Protocolo — Lucas F. (1/3) | G11: 1000 | H11: Pago | I11: 46296 | J11: Lucas F. | K11: Exemplo — substitua pelos dados reais
A12: 46296 | B12: =IF(A12="","",IFERROR(INDEX(Calendario!$A$4:$A$107,MATCH(A12,Calendario!$B$4:$B$107,1)),"")) -> 2026-S40 | C12: =IF(A12="","",YEAR(A12)&"-"&TEXT(MONTH(A12),"00")) -> 2026-10 | D12: Gasto | E12: Fixo | F12: Aluguel | G12: 4500 | H12: Pago | I12: 46296 | J12: Imobiliária | K12: Exemplo — substitua pelos dados reais
A13: 46296 | B13: =IF(A13="","",IFERROR(INDEX(Calendario!$A$4:$A$107,MATCH(A13,Calendario!$B$4:$B$107,1)),"")) -> 2026-S40 | C13: =IF(A13="","",YEAR(A13)&"-"&TEXT(MONTH(A13),"00")) -> 2026-10 | D13: Gasto | E13: Variável | F13: Material de consumo (bandagens, eletrodos) | G13: 380 | H13: Pago | I13: 46296 | J13: Fornecedor | K13: Exemplo — substitua pelos dados reais
A14: 46297 | B14: =IF(A14="","",IFERROR(INDEX(Calendario!$A$4:$A$107,MATCH(A14,Calendario!$B$4:$B$107,1)),"")) -> 2026-S40 | C14: =IF(A14="","",YEAR(A14)&"-"&TEXT(MONTH(A14),"00")) -> 2026-10 | D14: Imposto | F14: Simples Nacional — DAS | G14: 1850 | H14: Pago | I14: 46315 | J14: Receita Federal | K14: Exemplo — substitua pelos dados reais
A15: 46297 | B15: =IF(A15="","",IFERROR(INDEX(Calendario!$A$4:$A$107,MATCH(A15,Calendario!$B$4:$B$107,1)),"")) -> 2026-S40 | C15: =IF(A15="","",YEAR(A15)&"-"&TEXT(MONTH(A15),"00")) -> 2026-10 | D15: Marketing | F15: Google Ads | G15: 700 | H15: Pago | I15: 46297 | J15: Google | K15: Exemplo — substitua pelos dados reais
A16: 46297 | B16: =IF(A16="","",IFERROR(INDEX(Calendario!$A$4:$A$107,MATCH(A16,Calendario!$B$4:$B$107,1)),"")) -> 2026-S40 | C16: =IF(A16="","",YEAR(A16)&"-"&TEXT(MONTH(A16),"00")) -> 2026-10 | D16: Receita | F16: Protocolo — Roberto A. (2/5) | G16: 760 | H16: Atrasado | I16: 46280 | J16: Roberto A. | K16: Exemplo — substitua pelos dados reais
B17: =IF(A17="","",IFERROR(INDEX(Calendario!$A$4:$A$107,MATCH(A17,Calendario!$B$4:$B$107,1)),"")) | C17: =IF(A17="","",YEAR(A17)&"-"&TEXT(MONTH(A17),"00"))
B18: =IF(A18="","",IFERROR(INDEX(Calendario!$A$4:$A$107,MATCH(A18,Calendario!$B$4:$B$107,1)),"")) | C18: =IF(A18="","",YEAR(A18)&"-"&TEXT(MONTH(A18),"00"))
B19: =IF(A19="","",IFERROR(INDEX(Calendario!$A$4:$A$107,MATCH(A19,Calendario!$B$4:$B$107,1)),"")) | C19: =IF(A19="","",YEAR(A19)&"-"&TEXT(MONTH(A19),"00"))
B20: =IF(A20="","",IFERROR(INDEX(Calendario!$A$4:$A$107,MATCH(A20,Calendario!$B$4:$B$107,1)),"")) | C20: =IF(A20="","",YEAR(A20)&"-"&TEXT(MONTH(A20),"00"))
B21: =IF(A21="","",IFERROR(INDEX(Calendario!$A$4:$A$107,MATCH(A21,Calendario!$B$4:$B$107,1)),"")) | C21: =IF(A21="","",YEAR(A21)&"-"&TEXT(MONTH(A21),"00"))
B22: =IF(A22="","",IFERROR(INDEX(Calendario!$A$4:$A$107,MATCH(A22,Calendario!$B$4:$B$107,1)),"")) | C22: =IF(A22="","",YEAR(A22)&"-"&TEXT(MONTH(A22),"00"))
B23: =IF(A23="","",IFERROR(INDEX(Calendario!$A$4:$A$107,MATCH(A23,Calendario!$B$4:$B$107,1)),"")) | C23: =IF(A23="","",YEAR(A23)&"-"&TEXT(MONTH(A23),"00"))
B24: =IF(A24="","",IFERROR(INDEX(Calendario!$A$4:$A$107,MATCH(A24,Calendario!$B$4:$B$107,1)),"")) | C24: =IF(A24="","",YEAR(A24)&"-"&TEXT(MONTH(A24),"00"))
B25: =IF(A25="","",IFERROR(INDEX(Calendario!$A$4:$A$107,MATCH(A25,Calendario!$B$4:$B$107,1)),"")) | C25: =IF(A25="","",YEAR(A25)&"-"&TEXT(MONTH(A25),"00"))
B26: =IF(A26="","",IFERROR(INDEX(Calendario!$A$4:$A$107,MATCH(A26,Calendario!$B$4:$B$107,1)),"")) | C26: =IF(A26="","",YEAR(A26)&"-"&TEXT(MONTH(A26),"00"))
B27: =IF(A27="","",IFERROR(INDEX(Calendario!$A$4:$A$107,MATCH(A27,Calendario!$B$4:$B$107,1)),"")) | C27: =IF(A27="","",YEAR(A27)&"-"&TEXT(MONTH(A27),"00"))
B28: =IF(A28="","",IFERROR(INDEX(Calendario!$A$4:$A$107,MATCH(A28,Calendario!$B$4:$B$107,1)),"")) | C28: =IF(A28="","",YEAR(A28)&"-"&TEXT(MONTH(A28),"00"))
... B503: =IF(A503="","",IFERROR(INDEX(Calendario!$A$4:$A$107,MATCH(A503,Calendario!$B$4:$B$107,1)),"")) | C503: =IF(A503="","",YEAR(A503)&"-"&TEXT(MONTH(A503),"00"))

Sheet Leads_Canal
A1: Leads por canal de ingresso
A2: Uma linha por semana e canal. A soma deve bater com 'Leads recebidos' da Base_Semanal (há checagem no Resumo_Semanal).
A3: id_semana | B3: Canal | C3: Quantidade | D3: Observações
A4: 2026-S39 | B4: Instagram | C4: 16 | D4: Exemplo
A5: 2026-S39 | B5: Google | C5: 10 | D5: Exemplo
A6: 2026-S39 | B6: Indicação | C6: 7 | D6: Exemplo
A7: 2026-S39 | B7: WhatsApp direto | C7: 5 | D7: Exemplo
A8: 2026-S40 | B8: Instagram | C8: 20 | D8: Exemplo
A9: 2026-S40 | B9: Google | C9: 12 | D9: Exemplo
A10: 2026-S40 | B10: Indicação | C10: 8 | D10: Exemplo
A11: 2026-S40 | B11: WhatsApp direto | C11: 5 | D11: Exemplo

Sheet Reuniao_Semanal
A1: Registro qualitativo da reunião semanal
A2: Uma linha por semana. Os textos aparecem automaticamente no Painel_Semanal.
A3: id_semana | B3: Resultado geral (registrado) | C3: Pontos positivos | D3: Pontos a melhorar | E3: Pacientes críticos / risco de desistência | F3: Pontos pertinentes | G3: Problemas no atendimento | H3: Algo prejudicando a experiência? | I3: Descrição do que prejudica | J3: Demandas da recepção e equipe | K3: Pontos relevantes (próxima semana) | L3: Outros pontos | M3: Metas da semana | N3: Soluções para os problemas identificados
A4: 2026-S40 | B4: Melhor | C4: Receita acima da meta; 4 protocolos fechados por indicação | D4: Taxa de ocupação da tarde abaixo de 90%; 5 cancelamentos de atendimento | E4: Roberto A. — 2 faltas seguidas e parcela em atraso; Ana R. — reclamou de espera | F4: Pacientes elogiaram o novo protocolo de alongamento | G4: Espera de 15 min na recepção em dois dias (acúmulo às 8h) | H4: Sim | I4: Atraso na abertura da recepção às 7h50 | J4: Recepção pede roteiro de confirmação de consulta por WhatsApp | K4: Agenda da manhã já com 73% ocupada; reforçar captação para a tarde | L4: Manutenção do ar-condicionado da sala 2 agendada para quinta | M4: Receita R$ 32.000; 10 avaliações; ocupação total ≥ 85% | N4: Confirmação de consulta 24h antes por WhatsApp; escala da recepção a partir de 7h40
A5: 2026-S39 | B5: Igual | C5: Exemplo — substitua pelos dados reais

Sheet Plano_Acao
A1: Plano de ação 5W2H
A2: Uma linha por ação. As 8 primeiras ações de cada semana aparecem no Painel_Semanal.
A3: id_semana | B3: Ordem | C3: Problema / meta | D3: O quê (What) | E3: Por quê (Why) | F3: Onde (Where) | G3: Quando (When) | H3: Quem (Who) | I3: Como (How) | J3: Quanto (How much) | K3: Status | L3: chave
A4: 2026-S40 | B4: =IF(A4="","",COUNTIF($A$4:A4,A4)) -> 1 | C4: Espera na recepção às 8h | D4: Antecipar abertura da recepção | E4: Reduzir espera e reclamações | F4: Recepção | G4: 46301 | H4: Recepção | I4: Escala iniciando às 7h40; check-in antecipado | J4: 0 | K4: Em andamento | L4: =IF(A4="","",A4&"-"&B4) -> 2026-S40-1
A5: 2026-S40 | B5: =IF(A5="","",COUNTIF($A$4:A5,A5)) -> 2 | C5: Cancelamentos de atendimento | D5: Confirmar consultas 24h antes por WhatsApp | E5: Reduzir faltas e liberar horários | F5: Recepção | G5: 46304 | H5: Recepção | I5: Modelo de mensagem + lista diária de confirmação | J5: 0 | K5: A fazer | L5: =IF(A5="","",A5&"-"&B5) -> 2026-S40-2
A6: 2026-S40 | B6: =IF(A6="","",COUNTIF($A$4:A6,A6)) -> 3 | C6: Ocupação da tarde < 90% | D6: Campanha de captação para horários da tarde | E6: Elevar taxa de ocupação | F6: Marketing | G6: 46311 | H6: Ariosto | I6: Anúncio segmentado + oferta de avaliação à tarde | J6: 400 | K6: A fazer | L6: =IF(A6="","",A6&"-"&B6) -> 2026-S40-3
B7: =IF(A7="","",COUNTIF($A$4:A7,A7)) | L7: =IF(A7="","",A7&"-"&B7)
B8: =IF(A8="","",COUNTIF($A$4:A8,A8)) | L8: =IF(A8="","",A8&"-"&B8)
B9: =IF(A9="","",COUNTIF($A$4:A9,A9)) | L9: =IF(A9="","",A9&"-"&B9)
B10: =IF(A10="","",COUNTIF($A$4:A10,A10)) | L10: =IF(A10="","",A10&"-"&B10)
B11: =IF(A11="","",COUNTIF($A$4:A11,A11)) | L11: =IF(A11="","",A11&"-"&B11)
B12: =IF(A12="","",COUNTIF($A$4:A12,A12)) | L12: =IF(A12="","",A12&"-"&B12)
B13: =IF(A13="","",COUNTIF($A$4:A13,A13)) | L13: =IF(A13="","",A13&"-"&B13)
B14: =IF(A14="","",COUNTIF($A$4:A14,A14)) | L14: =IF(A14="","",A14&"-"&B14)
B15: =IF(A15="","",COUNTIF($A$4:A15,A15)) | L15: =IF(A15="","",A15&"-"&B15)
B16: =IF(A16="","",COUNTIF($A$4:A16,A16)) | L16: =IF(A16="","",A16&"-"&B16)
B17: =IF(A17="","",COUNTIF($A$4:A17,A17)) | L17: =IF(A17="","",A17&"-"&B17)
B18: =IF(A18="","",COUNTIF($A$4:A18,A18)) | L18: =IF(A18="","",A18&"-"&B18)
... B503: =IF(A503="","",COUNTIF($A$4:A503,A503)) | L503: =IF(A503="","",A503&"-"&B503)

Sheet Resumo_Semanal
A1: Resumo semanal (calculado)
A2: Não edite: tudo é calculado a partir das abas de coleta. Base do Painel_Semanal.
A3: id_semana | B3: Início | C3: Fim | D3: Mês | E3: Leads recebidos | F3: Aval. agendadas | G3: Aval. canceladas | H3: Aval. realizadas F1 | I3: Aval. realizadas F2 | J3: Aval. realizadas total | K3: Taxa canc. avaliações | L3: Contratos F1 | M3: Contratos F2 | N3: Contratos total | O3: Conversão aval→contrato | P3: Atend. F1 | Q3: Atend. F2 | R3: Atend. total | S3: Cancelamentos atend. | T3: Novos pacientes | U3: Ocupação manhã | V3: Ocupação tarde | W3: Ocupação total | X3: Tempo médio F1 | Y3: Desvio F1 | Z3: Tempo médio F2 | AA3: Desvio F2 | AB3: Aval. contratadas (qtd) | AC3: Valor avaliações | AD3: Protocolos contratados (qtd) | AE3: Valor protocolos | AF3: Valor total contratado | AG3: Contratos à vista (qtd) | AH3: Contratos parcelados (qtd) | AI3: Receitas | AJ3: Gastos | AK3: Impostos | AL3: Marketing | AM3: Resultado | AN3: Receita vs meta | AO3: Gastos vs meta | AP3: CAC (marketing / novos pac.) | AQ3: Receita acum. mês | AR3: Gastos acum. mês | AS3: Leads por canal (soma) | AT3: Checagem leads | AU3: Checagem contratos
A4: =Base_Semanal!A4 -> 2026-S02 | B4: =Base_Semanal!B4 -> 46027 | C4: =Base_Semanal!C4 -> 46033 | D4: =Base_Semanal!D4 -> 2026-01 | E4: =Base_Semanal!E4 -> 0 | F4: =Base_Semanal!F4 -> 0 | G4: =Base_Semanal!G4 -> 0 | H4: =Base_Semanal!H4 -> 0 | I4: =Base_Semanal!I4 -> 0 | J4: =H4+I4 -> 0 | K4: =IF(F4=0,"",G4/F4) | L4: =Base_Semanal!J4 -> 0 | M4: =Base_Semanal!K4 -> 0 | N4: =L4+M4 -> 0 | O4: =IF(J4=0,"",N4/J4) | P4: =Base_Semanal!L4 -> 0 | Q4: =Base_Semanal!M4 -> 0 | R4: =P4+Q4 -> 0 | S4: =Base_Semanal!N4 -> 0 | T4: =Base_Semanal!O4 -> 0 | U4: =IF(Base_Semanal!P4=0,"",Base_Semanal!Q4/Base_Semanal!P4) | V4: =IF(Base_Semanal!R4=0,"",Base_Semanal!S4/Base_Semanal!R4) | W4: =IF(Base_Semanal!P4+Base_Semanal!R4=0,"",(Base_Semanal!Q4+Base_Semanal!S4)/(Base_Semanal!P4+Base_Semanal!R4)) | X4: =Base_Semanal!T4 -> 0 | Y4: =Base_Semanal!U4 -> 0 | Z4: =Base_Semanal!V4 -> 0 | AA4: =Base_Semanal!W4 -> 0 | AB4: =COUNTIFS(Contratos!$B$4:$B$503,$A4,Contratos!$E$4:$E$503,"Avaliação") -> 0 | AC4: =SUMIFS(Contratos!$I$4:$I$503,Contratos!$B$4:$B$503,$A4,Contratos!$E$4:$E$503,"Avaliação") -> 0 | AD4: =COUNTIFS(Contratos!$B$4:$B$503,$A4,Contratos!$E$4:$E$503,"Protocolo") -> 0 | AE4: =SUMIFS(Contratos!$I$4:$I$503,Contratos!$B$4:$B$503,$A4,Contratos!$E$4:$E$503,"Protocolo") -> 0 | AF4: =AC4+AE4 -> 0 | AG4: =COUNTIFS(Contratos!$B$4:$B$503,$A4,Contratos!$J$4:$J$503,"À vista") -> 0 | AH4: =COUNTIFS(Contratos!$B$4:$B$503,$A4,Contratos!$J$4:$J$503,"Parcelado") -> 0 | AI4: =SUMIFS(Financeiro!$G$4:$G$503,Financeiro!$B$4:$B$503,$A4,Financeiro!$D$4:$D$503,"Receita",Financeiro!$H$4:$H$503,"<>Cancelado") -> 0 | AJ4: =SUMIFS(Financeiro!$G$4:$G$503,Financeiro!$B$4:$B$503,$A4,Financeiro!$D$4:$D$503,"Gasto",Financeiro!$H$4:$H$503,"<>Cancelado") -> 0 | AK4: =SUMIFS(Financeiro!$G$4:$G$503,Financeiro!$B$4:$B$503,$A4,Financeiro!$D$4:$D$503,"Imposto",Financeiro!$H$4:$H$503,"<>Cancelado") -> 0 | AL4: =SUMIFS(Financeiro!$G$4:$G$503,Financeiro!$B$4:$B$503,$A4,Financeiro!$D$4:$D$503,"Marketing",Financeiro!$H$4:$H$503,"<>Cancelado") -> 0 | AM4: =AI4-AJ4-AK4-AL4 -> 0 | AN4: =IF(Config!$B$16=0,"",AI4/Config!$B$16) -> 0 | AO4: =IF(Config!$B$17=0,"",AJ4/Config!$B$17) -> 0 | AP4: =IF(T4=0,"",AL4/T4) | AQ4: =SUMIFS($AI$4:$AI$107,$D$4:$D$107,$D4,$B$4:$B$107,"<="&$B4) -> 0 | AR4: =SUMIFS($AJ$4:$AJ$107,$D$4:$D$107,$D4,$B$4:$B$107,"<="&$B4) -> 0 | AS4: =SUMIFS(Leads_Canal!$C$4:$C$503,Leads_Canal!$A$4:$A$503,$A4) -> 0 | AT4: =IF(E4=0,"",IF(E4=AR4,"OK","Divergente")) | AU4: =IF(N4=0,"",IF(N4=AD4,"OK","Divergente"))
A5: =Base_Semanal!A5 -> 2026-S03 | B5: =Base_Semanal!B5 -> 46034 | C5: =Base_Semanal!C5 -> 46040 | D5: =Base_Semanal!D5 -> 2026-01 | E5: =Base_Semanal!E5 -> 0 | F5: =Base_Semanal!F5 -> 0 | G5: =Base_Semanal!G5 -> 0 | H5: =Base_Semanal!H5 -> 0 | I5: =Base_Semanal!I5 -> 0 | J5: =H5+I5 -> 0 | K5: =IF(F5=0,"",G5/F5) | L5: =Base_Semanal!J5 -> 0 | M5: =Base_Semanal!K5 -> 0 | N5: =L5+M5 -> 0 | O5: =IF(J5=0,"",N5/J5) | P5: =Base_Semanal!L5 -> 0 | Q5: =Base_Semanal!M5 -> 0 | R5: =P5+Q5 -> 0 | S5: =Base_Semanal!N5 -> 0 | T5: =Base_Semanal!O5 -> 0 | U5: =IF(Base_Semanal!P5=0,"",Base_Semanal!Q5/Base_Semanal!P5) | V5: =IF(Base_Semanal!R5=0,"",Base_Semanal!S5/Base_Semanal!R5) | W5: =IF(Base_Semanal!P5+Base_Semanal!R5=0,"",(Base_Semanal!Q5+Base_Semanal!S5)/(Base_Semanal!P5+Base_Semanal!R5)) | X5: =Base_Semanal!T5 -> 0 | Y5: =Base_Semanal!U5 -> 0 | Z5: =Base_Semanal!V5 -> 0 | AA5: =Base_Semanal!W5 -> 0 | AB5: =COUNTIFS(Contratos!$B$4:$B$503,$A5,Contratos!$E$4:$E$503,"Avaliação") -> 0 | AC5: =SUMIFS(Contratos!$I$4:$I$503,Contratos!$B$4:$B$503,$A5,Contratos!$E$4:$E$503,"Avaliação") -> 0 | AD5: =COUNTIFS(Contratos!$B$4:$B$503,$A5,Contratos!$E$4:$E$503,"Protocolo") -> 0 | AE5: =SUMIFS(Contratos!$I$4:$I$503,Contratos!$B$4:$B$503,$A5,Contratos!$E$4:$E$503,"Protocolo") -> 0 | AF5: =AC5+AE5 -> 0 | AG5: =COUNTIFS(Contratos!$B$4:$B$503,$A5,Contratos!$J$4:$J$503,"À vista") -> 0 | AH5: =COUNTIFS(Contratos!$B$4:$B$503,$A5,Contratos!$J$4:$J$503,"Parcelado") -> 0 | AI5: =SUMIFS(Financeiro!$G$4:$G$503,Financeiro!$B$4:$B$503,$A5,Financeiro!$D$4:$D$503,"Receita",Financeiro!$H$4:$H$503,"<>Cancelado") -> 0 | AJ5: =SUMIFS(Financeiro!$G$4:$G$503,Financeiro!$B$4:$B$503,$A5,Financeiro!$D$4:$D$503,"Gasto",Financeiro!$H$4:$H$503,"<>Cancelado") -> 0 | AK5: =SUMIFS(Financeiro!$G$4:$G$503,Financeiro!$B$4:$B$503,$A5,Financeiro!$D$4:$D$503,"Imposto",Financeiro!$H$4:$H$503,"<>Cancelado") -> 0 | AL5: =SUMIFS(Financeiro!$G$4:$G$503,Financeiro!$B$4:$B$503,$A5,Financeiro!$D$4:$D$503,"Marketing",Financeiro!$H$4:$H$503,"<>Cancelado") -> 0 | AM5: =AI5-AJ5-AK5-AL5 -> 0 | AN5: =IF(Config!$B$16=0,"",AI5/Config!$B$16) -> 0 | AO5: =IF(Config!$B$17=0,"",AJ5/Config!$B$17) -> 0 | AP5: =IF(T5=0,"",AL5/T5) | AQ5: =SUMIFS($AI$4:$AI$107,$D$4:$D$107,$D5,$B$4:$B$107,"<="&$B5) -> 0 | AR5: =SUMIFS($AJ$4:$AJ$107,$D$4:$D$107,$D5,$B$4:$B$107,"<="&$B5) -> 0 | AS5: =SUMIFS(Leads_Canal!$C$4:$C$503,Leads_Canal!$A$4:$A$503,$A5) -> 0 | AT5: =IF(E5=0,"",IF(E5=AR5,"OK","Divergente")) | AU5: =IF(N5=0,"",IF(N5=AD5,"OK","Divergente"))
A6: =Base_Semanal!A6 -> 2026-S04 | B6: =Base_Semanal!B6 -> 46041 | C6: =Base_Semanal!C6 -> 46047 | D6: =Base_Semanal!D6 -> 2026-01 | E6: =Base_Semanal!E6 -> 0 | F6: =Base_Semanal!F6 -> 0 | G6: =Base_Semanal!G6 -> 0 | H6: =Base_Semanal!H6 -> 0 | I6: =Base_Semanal!I6 -> 0 | J6: =H6+I6 -> 0 | K6: =IF(F6=0,"",G6/F6) | L6: =Base_Semanal!J6 -> 0 | M6: =Base_Semanal!K6 -> 0 | N6: =L6+M6 -> 0 | O6: =IF(J6=0,"",N6/J6) | P6: =Base_Semanal!L6 -> 0 | Q6: =Base_Semanal!M6 -> 0 | R6: =P6+Q6 -> 0 | S6: =Base_Semanal!N6 -> 0 | T6: =Base_Semanal!O6 -> 0 | U6: =IF(Base_Semanal!P6=0,"",Base_Semanal!Q6/Base_Semanal!P6) | V6: =IF(Base_Semanal!R6=0,"",Base_Semanal!S6/Base_Semanal!R6) | W6: =IF(Base_Semanal!P6+Base_Semanal!R6=0,"",(Base_Semanal!Q6+Base_Semanal!S6)/(Base_Semanal!P6+Base_Semanal!R6)) | X6: =Base_Semanal!T6 -> 0 | Y6: =Base_Semanal!U6 -> 0 | Z6: =Base_Semanal!V6 -> 0 | AA6: =Base_Semanal!W6 -> 0 | AB6: =COUNTIFS(Contratos!$B$4:$B$503,$A6,Contratos!$E$4:$E$503,"Avaliação") -> 0 | AC6: =SUMIFS(Contratos!$I$4:$I$503,Contratos!$B$4:$B$503,$A6,Contratos!$E$4:$E$503,"Avaliação") -> 0 | AD6: =COUNTIFS(Contratos!$B$4:$B$503,$A6,Contratos!$E$4:$E$503,"Protocolo") -> 0 | AE6: =SUMIFS(Contratos!$I$4:$I$503,Contratos!$B$4:$B$503,$A6,Contratos!$E$4:$E$503,"Protocolo") -> 0 | AF6: =AC6+AE6 -> 0 | AG6: =COUNTIFS(Contratos!$B$4:$B$503,$A6,Contratos!$J$4:$J$503,"À vista") -> 0 | AH6: =COUNTIFS(Contratos!$B$4:$B$503,$A6,Contratos!$J$4:$J$503,"Parcelado") -> 0 | AI6: =SUMIFS(Financeiro!$G$4:$G$503,Financeiro!$B$4:$B$503,$A6,Financeiro!$D$4:$D$503,"Receita",Financeiro!$H$4:$H$503,"<>Cancelado") -> 0 | AJ6: =SUMIFS(Financeiro!$G$4:$G$503,Financeiro!$B$4:$B$503,$A6,Financeiro!$D$4:$D$503,"Gasto",Financeiro!$H$4:$H$503,"<>Cancelado") -> 0 | AK6: =SUMIFS(Financeiro!$G$4:$G$503,Financeiro!$B$4:$B$503,$A6,Financeiro!$D$4:$D$503,"Imposto",Financeiro!$H$4:$H$503,"<>Cancelado") -> 0 | AL6: =SUMIFS(Financeiro!$G$4:$G$503,Financeiro!$B$4:$B$503,$A6,Financeiro!$D$4:$D$503,"Marketing",Financeiro!$H$4:$H$503,"<>Cancelado") -> 0 | AM6: =AI6-AJ6-AK6-AL6 -> 0 | AN6: =IF(Config!$B$16=0,"",AI6/Config!$B$16) -> 0 | AO6: =IF(Config!$B$17=0,"",AJ6/Config!$B$17) -> 0 | AP6: =IF(T6=0,"",AL6/T6) | AQ6: =SUMIFS($AI$4:$AI$107,$D$4:$D$107,$D6,$B$4:$B$107,"<="&$B6) -> 0 | AR6: =SUMIFS($AJ$4:$AJ$107,$D$4:$D$107,$D6,$B$4:$B$107,"<="&$B6) -> 0 | AS6: =SUMIFS(Leads_Canal!$C$4:$C$503,Leads_Canal!$A$4:$A$503,$A6) -> 0 | AT6: =IF(E6=0,"",IF(E6=AR6,"OK","Divergente")) | AU6: =IF(N6=0,"",IF(N6=AD6,"OK","Divergente"))
A7: =Base_Semanal!A7 -> 2026-S05 | B7: =Base_Semanal!B7 -> 46048 | C7: =Base_Semanal!C7 -> 46054 | D7: =Base_Semanal!D7 -> 2026-01 | E7: =Base_Semanal!E7 -> 0 | F7: =Base_Semanal!F7 -> 0 | G7: =Base_Semanal!G7 -> 0 | H7: =Base_Semanal!H7 -> 0 | I7: =Base_Semanal!I7 -> 0 | J7: =H7+I7 -> 0 | K7: =IF(F7=0,"",G7/F7) | L7: =Base_Semanal!J7 -> 0 | M7: =Base_Semanal!K7 -> 0 | N7: =L7+M7 -> 0 | O7: =IF(J7=0,"",N7/J7) | P7: =Base_Semanal!L7 -> 0 | Q7: =Base_Semanal!M7 -> 0 | R7: =P7+Q7 -> 0 | S7: =Base_Semanal!N7 -> 0 | T7: =Base_Semanal!O7 -> 0 | U7: =IF(Base_Semanal!P7=0,"",Base_Semanal!Q7/Base_Semanal!P7) | V7: =IF(Base_Semanal!R7=0,"",Base_Semanal!S7/Base_Semanal!R7) | W7: =IF(Base_Semanal!P7+Base_Semanal!R7=0,"",(Base_Semanal!Q7+Base_Semanal!S7)/(Base_Semanal!P7+Base_Semanal!R7)) | X7: =Base_Semanal!T7 -> 0 | Y7: =Base_Semanal!U7 -> 0 | Z7: =Base_Semanal!V7 -> 0 | AA7: =Base_Semanal!W7 -> 0 | AB7: =COUNTIFS(Contratos!$B$4:$B$503,$A7,Contratos!$E$4:$E$503,"Avaliação") -> 0 | AC7: =SUMIFS(Contratos!$I$4:$I$503,Contratos!$B$4:$B$503,$A7,Contratos!$E$4:$E$503,"Avaliação") -> 0 | AD7: =COUNTIFS(Contratos!$B$4:$B$503,$A7,Contratos!$E$4:$E$503,"Protocolo") -> 0 | AE7: =SUMIFS(Contratos!$I$4:$I$503,Contratos!$B$4:$B$503,$A7,Contratos!$E$4:$E$503,"Protocolo") -> 0 | AF7: =AC7+AE7 -> 0 | AG7: =COUNTIFS(Contratos!$B$4:$B$503,$A7,Contratos!$J$4:$J$503,"À vista") -> 0 | AH7: =COUNTIFS(Contratos!$B$4:$B$503,$A7,Contratos!$J$4:$J$503,"Parcelado") -> 0 | AI7: =SUMIFS(Financeiro!$G$4:$G$503,Financeiro!$B$4:$B$503,$A7,Financeiro!$D$4:$D$503,"Receita",Financeiro!$H$4:$H$503,"<>Cancelado") -> 0 | AJ7: =SUMIFS(Financeiro!$G$4:$G$503,Financeiro!$B$4:$B$503,$A7,Financeiro!$D$4:$D$503,"Gasto",Financeiro!$H$4:$H$503,"<>Cancelado") -> 0 | AK7: =SUMIFS(Financeiro!$G$4:$G$503,Financeiro!$B$4:$B$503,$A7,Financeiro!$D$4:$D$503,"Imposto",Financeiro!$H$4:$H$503,"<>Cancelado") -> 0 | AL7: =SUMIFS(Financeiro!$G$4:$G$503,Financeiro!$B$4:$B$503,$A7,Financeiro!$D$4:$D$503,"Marketing",Financeiro!$H$4:$H$503,"<>Cancelado") -> 0 | AM7: =AI7-AJ7-AK7-AL7 -> 0 | AN7: =IF(Config!$B$16=0,"",AI7/Config!$B$16) -> 0 | AO7: =IF(Config!$B$17=0,"",AJ7/Config!$B$17) -> 0 | AP7: =IF(T7=0,"",AL7/T7) | AQ7: =SUMIFS($AI$4:$AI$107,$D$4:$D$107,$D7,$B$4:$B$107,"<="&$B7) -> 0 | AR7: =SUMIFS($AJ$4:$AJ$107,$D$4:$D$107,$D7,$B$4:$B$107,"<="&$B7) -> 0 | AS7: =SUMIFS(Leads_Canal!$C$4:$C$503,Leads_Canal!$A$4:$A$503,$A7) -> 0 | AT7: =IF(E7=0,"",IF(E7=AR7,"OK","Divergente")) | AU7: =IF(N7=0,"",IF(N7=AD7,"OK","Divergente"))
A8: =Base_Semanal!A8 -> 2026-S06 | B8: =Base_Semanal!B8 -> 46055 | C8: =Base_Semanal!C8 -> 46061 | D8: =Base_Semanal!D8 -> 2026-02 | E8: =Base_Semanal!E8 -> 0 | F8: =Base_Semanal!F8 -> 0 | G8: =Base_Semanal!G8 -> 0 | H8: =Base_Semanal!H8 -> 0 | I8: =Base_Semanal!I8 -> 0 | J8: =H8+I8 -> 0 | K8: =IF(F8=0,"",G8/F8) | L8: =Base_Semanal!J8 -> 0 | M8: =Base_Semanal!K8 -> 0 | N8: =L8+M8 -> 0 | O8: =IF(J8=0,"",N8/J8) | P8: =Base_Semanal!L8 -> 0 | Q8: =Base_Semanal!M8 -> 0 | R8: =P8+Q8 -> 0 | S8: =Base_Semanal!N8 -> 0 | T8: =Base_Semanal!O8 -> 0 | U8: =IF(Base_Semanal!P8=0,"",Base_Semanal!Q8/Base_Semanal!P8) | V8: =IF(Base_Semanal!R8=0,"",Base_Semanal!S8/Base_Semanal!R8) | W8: =IF(Base_Semanal!P8+Base_Semanal!R8=0,"",(Base_Semanal!Q8+Base_Semanal!S8)/(Base_Semanal!P8+Base_Semanal!R8)) | X8: =Base_Semanal!T8 -> 0 | Y8: =Base_Semanal!U8 -> 0 | Z8: =Base_Semanal!V8 -> 0 | AA8: =Base_Semanal!W8 -> 0 | AB8: =COUNTIFS(Contratos!$B$4:$B$503,$A8,Contratos!$E$4:$E$503,"Avaliação") -> 0 | AC8: =SUMIFS(Contratos!$I$4:$I$503,Contratos!$B$4:$B$503,$A8,Contratos!$E$4:$E$503,"Avaliação") -> 0 | AD8: =COUNTIFS(Contratos!$B$4:$B$503,$A8,Contratos!$E$4:$E$503,"Protocolo") -> 0 | AE8: =SUMIFS(Contratos!$I$4:$I$503,Contratos!$B$4:$B$503,$A8,Contratos!$E$4:$E$503,"Protocolo") -> 0 | AF8: =AC8+AE8 -> 0 | AG8: =COUNTIFS(Contratos!$B$4:$B$503,$A8,Contratos!$J$4:$J$503,"À vista") -> 0 | AH8: =COUNTIFS(Contratos!$B$4:$B$503,$A8,Contratos!$J$4:$J$503,"Parcelado") -> 0 | AI8: =SUMIFS(Financeiro!$G$4:$G$503,Financeiro!$B$4:$B$503,$A8,Financeiro!$D$4:$D$503,"Receita",Financeiro!$H$4:$H$503,"<>Cancelado") -> 0 | AJ8: =SUMIFS(Financeiro!$G$4:$G$503,Financeiro!$B$4:$B$503,$A8,Financeiro!$D$4:$D$503,"Gasto",Financeiro!$H$4:$H$503,"<>Cancelado") -> 0 | AK8: =SUMIFS(Financeiro!$G$4:$G$503,Financeiro!$B$4:$B$503,$A8,Financeiro!$D$4:$D$503,"Imposto",Financeiro!$H$4:$H$503,"<>Cancelado") -> 0 | AL8: =SUMIFS(Financeiro!$G$4:$G$503,Financeiro!$B$4:$B$503,$A8,Financeiro!$D$4:$D$503,"Marketing",Financeiro!$H$4:$H$503,"<>Cancelado") -> 0 | AM8: =AI8-AJ8-AK8-AL8 -> 0 | AN8: =IF(Config!$B$16=0,"",AI8/Config!$B$16) -> 0 | AO8: =IF(Config!$B$17=0,"",AJ8/Config!$B$17) -> 0 | AP8: =IF(T8=0,"",AL8/T8) | AQ8: =SUMIFS($AI$4:$AI$107,$D$4:$D$107,$D8,$B$4:$B$107,"<="&$B8) -> 0 | AR8: =SUMIFS($AJ$4:$AJ$107,$D$4:$D$107,$D8,$B$4:$B$107,"<="&$B8) -> 0 | AS8: =SUMIFS(Leads_Canal!$C$4:$C$503,Leads_Canal!$A$4:$A$503,$A8) -> 0 | AT8: =IF(E8=0,"",IF(E8=AR8,"OK","Divergente")) | AU8: =IF(N8=0,"",IF(N8=AD8,"OK","Divergente"))
A9: =Base_Semanal!A9 -> 2026-S07 | B9: =Base_Semanal!B9 -> 46062 | C9: =Base_Semanal!C9 -> 46068 | D9: =Base_Semanal!D9 -> 2026-02 | E9: =Base_Semanal!E9 -> 0 | F9: =Base_Semanal!F9 -> 0 | G9: =Base_Semanal!G9 -> 0 | H9: =Base_Semanal!H9 -> 0 | I9: =Base_Semanal!I9 -> 0 | J9: =H9+I9 -> 0 | K9: =IF(F9=0,"",G9/F9) | L9: =Base_Semanal!J9 -> 0 | M9: =Base_Semanal!K9 -> 0 | N9: =L9+M9 -> 0 | O9: =IF(J9=0,"",N9/J9) | P9: =Base_Semanal!L9 -> 0 | Q9: =Base_Semanal!M9 -> 0 | R9: =P9+Q9 -> 0 | S9: =Base_Semanal!N9 -> 0 | T9: =Base_Semanal!O9 -> 0 | U9: =IF(Base_Semanal!P9=0,"",Base_Semanal!Q9/Base_Semanal!P9) | V9: =IF(Base_Semanal!R9=0,"",Base_Semanal!S9/Base_Semanal!R9) | W9: =IF(Base_Semanal!P9+Base_Semanal!R9=0,"",(Base_Semanal!Q9+Base_Semanal!S9)/(Base_Semanal!P9+Base_Semanal!R9)) | X9: =Base_Semanal!T9 -> 0 | Y9: =Base_Semanal!U9 -> 0 | Z9: =Base_Semanal!V9 -> 0 | AA9: =Base_Semanal!W9 -> 0 | AB9: =COUNTIFS(Contratos!$B$4:$B$503,$A9,Contratos!$E$4:$E$503,"Avaliação") -> 0 | AC9: =SUMIFS(Contratos!$I$4:$I$503,Contratos!$B$4:$B$503,$A9,Contratos!$E$4:$E$503,"Avaliação") -> 0 | AD9: =COUNTIFS(Contratos!$B$4:$B$503,$A9,Contratos!$E$4:$E$503,"Protocolo") -> 0 | AE9: =SUMIFS(Contratos!$I$4:$I$503,Contratos!$B$4:$B$503,$A9,Contratos!$E$4:$E$503,"Protocolo") -> 0 | AF9: =AC9+AE9 -> 0 | AG9: =COUNTIFS(Contratos!$B$4:$B$503,$A9,Contratos!$J$4:$J$503,"À vista") -> 0 | AH9: =COUNTIFS(Contratos!$B$4:$B$503,$A9,Contratos!$J$4:$J$503,"Parcelado") -> 0 | AI9: =SUMIFS(Financeiro!$G$4:$G$503,Financeiro!$B$4:$B$503,$A9,Financeiro!$D$4:$D$503,"Receita",Financeiro!$H$4:$H$503,"<>Cancelado") -> 0 | AJ9: =SUMIFS(Financeiro!$G$4:$G$503,Financeiro!$B$4:$B$503,$A9,Financeiro!$D$4:$D$503,"Gasto",Financeiro!$H$4:$H$503,"<>Cancelado") -> 0 | AK9: =SUMIFS(Financeiro!$G$4:$G$503,Financeiro!$B$4:$B$503,$A9,Financeiro!$D$4:$D$503,"Imposto",Financeiro!$H$4:$H$503,"<>Cancelado") -> 0 | AL9: =SUMIFS(Financeiro!$G$4:$G$503,Financeiro!$B$4:$B$503,$A9,Financeiro!$D$4:$D$503,"Marketing",Financeiro!$H$4:$H$503,"<>Cancelado") -> 0 | AM9: =AI9-AJ9-AK9-AL9 -> 0 | AN9: =IF(Config!$B$16=0,"",AI9/Config!$B$16) -> 0 | AO9: =IF(Config!$B$17=0,"",AJ9/Config!$B$17) -> 0 | AP9: =IF(T9=0,"",AL9/T9) | AQ9: =SUMIFS($AI$4:$AI$107,$D$4:$D$107,$D9,$B$4:$B$107,"<="&$B9) -> 0 | AR9: =SUMIFS($AJ$4:$AJ$107,$D$4:$D$107,$D9,$B$4:$B$107,"<="&$B9) -> 0 | AS9: =SUMIFS(Leads_Canal!$C$4:$C$503,Leads_Canal!$A$4:$A$503,$A9) -> 0 | AT9: =IF(E9=0,"",IF(E9=AR9,"OK","Divergente")) | AU9: =IF(N9=0,"",IF(N9=AD9,"OK","Divergente"))
A10: =Base_Semanal!A10 -> 2026-S08 | B10: =Base_Semanal!B10 -> 46069 | C10: =Base_Semanal!C10 -> 46075 | D10: =Base_Semanal!D10 -> 2026-02 | E10: =Base_Semanal!E10 -> 0 | F10: =Base_Semanal!F10 -> 0 | G10: =Base_Semanal!G10 -> 0 | H10: =Base_Semanal!H10 -> 0 | I10: =Base_Semanal!I10 -> 0 | J10: =H10+I10 -> 0 | K10: =IF(F10=0,"",G10/F10) | L10: =Base_Semanal!J10 -> 0 | M10: =Base_Semanal!K10 -> 0 | N10: =L10+M10 -> 0 | O10: =IF(J10=0,"",N10/J10) | P10: =Base_Semanal!L10 -> 0 | Q10: =Base_Semanal!M10 -> 0 | R10: =P10+Q10 -> 0 | S10: =Base_Semanal!N10 -> 0 | T10: =Base_Semanal!O10 -> 0 | U10: =IF(Base_Semanal!P10=0,"",Base_Semanal!Q10/Base_Semanal!P10) | V10: =IF(Base_Semanal!R10=0,"",Base_Semanal!S10/Base_Semanal!R10) | W10: =IF(Base_Semanal!P10+Base_Semanal!R10=0,"",(Base_Semanal!Q10+Base_Semanal!S10)/(Base_Semanal!P10+Base_Semanal!R10)) | X10: =Base_Semanal!T10 -> 0 | Y10: =Base_Semanal!U10 -> 0 | Z10: =Base_Semanal!V10 -> 0 | AA10: =Base_Semanal!W10 -> 0 | AB10: =COUNTIFS(Contratos!$B$4:$B$503,$A10,Contratos!$E$4:$E$503,"Avaliação") -> 0 | AC10: =SUMIFS(Contratos!$I$4:$I$503,Contratos!$B$4:$B$503,$A10,Contratos!$E$4:$E$503,"Avaliação") -> 0 | AD10: =COUNTIFS(Contratos!$B$4:$B$503,$A10,Contratos!$E$4:$E$503,"Protocolo") -> 0 | AE10: =SUMIFS(Contratos!$I$4:$I$503,Contratos!$B$4:$B$503,$A10,Contratos!$E$4:$E$503,"Protocolo") -> 0 | AF10: =AC10+AE10 -> 0 | AG10: =COUNTIFS(Contratos!$B$4:$B$503,$A10,Contratos!$J$4:$J$503,"À vista") -> 0 | AH10: =COUNTIFS(Contratos!$B$4:$B$503,$A10,Contratos!$J$4:$J$503,"Parcelado") -> 0 | AI10: =SUMIFS(Financeiro!$G$4:$G$503,Financeiro!$B$4:$B$503,$A10,Financeiro!$D$4:$D$503,"Receita",Financeiro!$H$4:$H$503,"<>Cancelado") -> 0 | AJ10: =SUMIFS(Financeiro!$G$4:$G$503,Financeiro!$B$4:$B$503,$A10,Financeiro!$D$4:$D$503,"Gasto",Financeiro!$H$4:$H$503,"<>Cancelado") -> 0 | AK10: =SUMIFS(Financeiro!$G$4:$G$503,Financeiro!$B$4:$B$503,$A10,Financeiro!$D$4:$D$503,"Imposto",Financeiro!$H$4:$H$503,"<>Cancelado") -> 0 | AL10: =SUMIFS(Financeiro!$G$4:$G$503,Financeiro!$B$4:$B$503,$A10,Financeiro!$D$4:$D$503,"Marketing",Financeiro!$H$4:$H$503,"<>Cancelado") -> 0 | AM10: =AI10-AJ10-AK10-AL10 -> 0 | AN10: =IF(Config!$B$16=0,"",AI10/Config!$B$16) -> 0 | AO10: =IF(Config!$B$17=0,"",AJ10/Config!$B$17) -> 0 | AP10: =IF(T10=0,"",AL10/T10) | AQ10: =SUMIFS($AI$4:$AI$107,$D$4:$D$107,$D10,$B$4:$B$107,"<="&$B10) -> 0 | AR10: =SUMIFS($AJ$4:$AJ$107,$D$4:$D$107,$D10,$B$4:$B$107,"<="&$B10) -> 0 | AS10: =SUMIFS(Leads_Canal!$C$4:$C$503,Leads_Canal!$A$4:$A$503,$A10) -> 0 | AT10: =IF(E10=0,"",IF(E10=AR10,"OK","Divergente")) | AU10: =IF(N10=0,"",IF(N10=AD10,"OK","Divergente"))
A11: =Base_Semanal!A11 -> 2026-S09 | B11: =Base_Semanal!B11 -> 46076 | C11: =Base_Semanal!C11 -> 46082 | D11: =Base_Semanal!D11 -> 2026-02 | E11: =Base_Semanal!E11 -> 0 | F11: =Base_Semanal!F11 -> 0 | G11: =Base_Semanal!G11 -> 0 | H11: =Base_Semanal!H11 -> 0 | I11: =Base_Semanal!I11 -> 0 | J11: =H11+I11 -> 0 | K11: =IF(F11=0,"",G11/F11) | L11: =Base_Semanal!J11 -> 0 | M11: =Base_Semanal!K11 -> 0 | N11: =L11+M11 -> 0 | O11: =IF(J11=0,"",N11/J11) | P11: =Base_Semanal!L11 -> 0 | Q11: =Base_Semanal!M11 -> 0 | R11: =P11+Q11 -> 0 | S11: =Base_Semanal!N11 -> 0 | T11: =Base_Semanal!O11 -> 0 | U11: =IF(Base_Semanal!P11=0,"",Base_Semanal!Q11/Base_Semanal!P11) | V11: =IF(Base_Semanal!R11=0,"",Base_Semanal!S11/Base_Semanal!R11) | W11: =IF(Base_Semanal!P11+Base_Semanal!R11=0,"",(Base_Semanal!Q11+Base_Semanal!S11)/(Base_Semanal!P11+Base_Semanal!R11)) | X11: =Base_Semanal!T11 -> 0 | Y11: =Base_Semanal!U11 -> 0 | Z11: =Base_Semanal!V11 -> 0 | AA11: =Base_Semanal!W11 -> 0 | AB11: =COUNTIFS(Contratos!$B$4:$B$503,$A11,Contratos!$E$4:$E$503,"Avaliação") -> 0 | AC11: =SUMIFS(Contratos!$I$4:$I$503,Contratos!$B$4:$B$503,$A11,Contratos!$E$4:$E$503,"Avaliação") -> 0 | AD11: =COUNTIFS(Contratos!$B$4:$B$503,$A11,Contratos!$E$4:$E$503,"Protocolo") -> 0 | AE11: =SUMIFS(Contratos!$I$4:$I$503,Contratos!$B$4:$B$503,$A11,Contratos!$E$4:$E$503,"Protocolo") -> 0 | AF11: =AC11+AE11 -> 0 | AG11: =COUNTIFS(Contratos!$B$4:$B$503,$A11,Contratos!$J$4:$J$503,"À vista") -> 0 | AH11: =COUNTIFS(Contratos!$B$4:$B$503,$A11,Contratos!$J$4:$J$503,"Parcelado") -> 0 | AI11: =SUMIFS(Financeiro!$G$4:$G$503,Financeiro!$B$4:$B$503,$A11,Financeiro!$D$4:$D$503,"Receita",Financeiro!$H$4:$H$503,"<>Cancelado") -> 0 | AJ11: =SUMIFS(Financeiro!$G$4:$G$503,Financeiro!$B$4:$B$503,$A11,Financeiro!$D$4:$D$503,"Gasto",Financeiro!$H$4:$H$503,"<>Cancelado") -> 0 | AK11: =SUMIFS(Financeiro!$G$4:$G$503,Financeiro!$B$4:$B$503,$A11,Financeiro!$D$4:$D$503,"Imposto",Financeiro!$H$4:$H$503,"<>Cancelado") -> 0 | AL11: =SUMIFS(Financeiro!$G$4:$G$503,Financeiro!$B$4:$B$503,$A11,Financeiro!$D$4:$D$503,"Marketing",Financeiro!$H$4:$H$503,"<>Cancelado") -> 0 | AM11: =AI11-AJ11-AK11-AL11 -> 0 | AN11: =IF(Config!$B$16=0,"",AI11/Config!$B$16) -> 0 | AO11: =IF(Config!$B$17=0,"",AJ11/Config!$B$17) -> 0 | AP11: =IF(T11=0,"",AL11/T11) | AQ11: =SUMIFS($AI$4:$AI$107,$D$4:$D$107,$D11,$B$4:$B$107,"<="&$B11) -> 0 | AR11: =SUMIFS($AJ$4:$AJ$107,$D$4:$D$107,$D11,$B$4:$B$107,"<="&$B11) -> 0 | AS11: =SUMIFS(Leads_Canal!$C$4:$C$503,Leads_Canal!$A$4:$A$503,$A11) -> 0 | AT11: =IF(E11=0,"",IF(E11=AR11,"OK","Divergente")) | AU11: =IF(N11=0,"",IF(N11=AD11,"OK","Divergente"))
A12: =Base_Semanal!A12 -> 2026-S10 | B12: =Base_Semanal!B12 -> 46083 | C12: =Base_Semanal!C12 -> 46089 | D12: =Base_Semanal!D12 -> 2026-03 | E12: =Base_Semanal!E12 -> 0 | F12: =Base_Semanal!F12 -> 0 | G12: =Base_Semanal!G12 -> 0 | H12: =Base_Semanal!H12 -> 0 | I12: =Base_Semanal!I12 -> 0 | J12: =H12+I12 -> 0 | K12: =IF(F12=0,"",G12/F12) | L12: =Base_Semanal!J12 -> 0 | M12: =Base_Semanal!K12 -> 0 | N12: =L12+M12 -> 0 | O12: =IF(J12=0,"",N12/J12) | P12: =Base_Semanal!L12 -> 0 | Q12: =Base_Semanal!M12 -> 0 | R12: =P12+Q12 -> 0 | S12: =Base_Semanal!N12 -> 0 | T12: =Base_Semanal!O12 -> 0 | U12: =IF(Base_Semanal!P12=0,"",Base_Semanal!Q12/Base_Semanal!P12) | V12: =IF(Base_Semanal!R12=0,"",Base_Semanal!S12/Base_Semanal!R12) | W12: =IF(Base_Semanal!P12+Base_Semanal!R12=0,"",(Base_Semanal!Q12+Base_Semanal!S12)/(Base_Semanal!P12+Base_Semanal!R12)) | X12: =Base_Semanal!T12 -> 0 | Y12: =Base_Semanal!U12 -> 0 | Z12: =Base_Semanal!V12 -> 0 | AA12: =Base_Semanal!W12 -> 0 | AB12: =COUNTIFS(Contratos!$B$4:$B$503,$A12,Contratos!$E$4:$E$503,"Avaliação") -> 0 | AC12: =SUMIFS(Contratos!$I$4:$I$503,Contratos!$B$4:$B$503,$A12,Contratos!$E$4:$E$503,"Avaliação") -> 0 | AD12: =COUNTIFS(Contratos!$B$4:$B$503,$A12,Contratos!$E$4:$E$503,"Protocolo") -> 0 | AE12: =SUMIFS(Contratos!$I$4:$I$503,Contratos!$B$4:$B$503,$A12,Contratos!$E$4:$E$503,"Protocolo") -> 0 | AF12: =AC12+AE12 -> 0 | AG12: =COUNTIFS(Contratos!$B$4:$B$503,$A12,Contratos!$J$4:$J$503,"À vista") -> 0 | AH12: =COUNTIFS(Contratos!$B$4:$B$503,$A12,Contratos!$J$4:$J$503,"Parcelado") -> 0 | AI12: =SUMIFS(Financeiro!$G$4:$G$503,Financeiro!$B$4:$B$503,$A12,Financeiro!$D$4:$D$503,"Receita",Financeiro!$H$4:$H$503,"<>Cancelado") -> 0 | AJ12: =SUMIFS(Financeiro!$G$4:$G$503,Financeiro!$B$4:$B$503,$A12,Financeiro!$D$4:$D$503,"Gasto",Financeiro!$H$4:$H$503,"<>Cancelado") -> 0 | AK12: =SUMIFS(Financeiro!$G$4:$G$503,Financeiro!$B$4:$B$503,$A12,Financeiro!$D$4:$D$503,"Imposto",Financeiro!$H$4:$H$503,"<>Cancelado") -> 0 | AL12: =SUMIFS(Financeiro!$G$4:$G$503,Financeiro!$B$4:$B$503,$A12,Financeiro!$D$4:$D$503,"Marketing",Financeiro!$H$4:$H$503,"<>Cancelado") -> 0 | AM12: =AI12-AJ12-AK12-AL12 -> 0 | AN12: =IF(Config!$B$16=0,"",AI12/Config!$B$16) -> 0 | AO12: =IF(Config!$B$17=0,"",AJ12/Config!$B$17) -> 0 | AP12: =IF(T12=0,"",AL12/T12) | AQ12: =SUMIFS($AI$4:$AI$107,$D$4:$D$107,$D12,$B$4:$B$107,"<="&$B12) -> 0 | AR12: =SUMIFS($AJ$4:$AJ$107,$D$4:$D$107,$D12,$B$4:$B$107,"<="&$B12) -> 0 | AS12: =SUMIFS(Leads_Canal!$C$4:$C$503,Leads_Canal!$A$4:$A$503,$A12) -> 0 | AT12: =IF(E12=0,"",IF(E12=AR12,"OK","Divergente")) | AU12: =IF(N12=0,"",IF(N12=AD12,"OK","Divergente"))
A13: =Base_Semanal!A13 -> 2026-S11 | B13: =Base_Semanal!B13 -> 46090 | C13: =Base_Semanal!C13 -> 46096 | D13: =Base_Semanal!D13 -> 2026-03 | E13: =Base_Semanal!E13 -> 0 | F13: =Base_Semanal!F13 -> 0 | G13: =Base_Semanal!G13 -> 0 | H13: =Base_Semanal!H13 -> 0 | I13: =Base_Semanal!I13 -> 0 | J13: =H13+I13 -> 0 | K13: =IF(F13=0,"",G13/F13) | L13: =Base_Semanal!J13 -> 0 | M13: =Base_Semanal!K13 -> 0 | N13: =L13+M13 -> 0 | O13: =IF(J13=0,"",N13/J13) | P13: =Base_Semanal!L13 -> 0 | Q13: =Base_Semanal!M13 -> 0 | R13: =P13+Q13 -> 0 | S13: =Base_Semanal!N13 -> 0 | T13: =Base_Semanal!O13 -> 0 | U13: =IF(Base_Semanal!P13=0,"",Base_Semanal!Q13/Base_Semanal!P13) | V13: =IF(Base_Semanal!R13=0,"",Base_Semanal!S13/Base_Semanal!R13) | W13: =IF(Base_Semanal!P13+Base_Semanal!R13=0,"",(Base_Semanal!Q13+Base_Semanal!S13)/(Base_Semanal!P13+Base_Semanal!R13)) | X13: =Base_Semanal!T13 -> 0 | Y13: =Base_Semanal!U13 -> 0 | Z13: =Base_Semanal!V13 -> 0 | AA13: =Base_Semanal!W13 -> 0 | AB13: =COUNTIFS(Contratos!$B$4:$B$503,$A13,Contratos!$E$4:$E$503,"Avaliação") -> 0 | AC13: =SUMIFS(Contratos!$I$4:$I$503,Contratos!$B$4:$B$503,$A13,Contratos!$E$4:$E$503,"Avaliação") -> 0 | AD13: =COUNTIFS(Contratos!$B$4:$B$503,$A13,Contratos!$E$4:$E$503,"Protocolo") -> 0 | AE13: =SUMIFS(Contratos!$I$4:$I$503,Contratos!$B$4:$B$503,$A13,Contratos!$E$4:$E$503,"Protocolo") -> 0 | AF13: =AC13+AE13 -> 0 | AG13: =COUNTIFS(Contratos!$B$4:$B$503,$A13,Contratos!$J$4:$J$503,"À vista") -> 0 | AH13: =COUNTIFS(Contratos!$B$4:$B$503,$A13,Contratos!$J$4:$J$503,"Parcelado") -> 0 | AI13: =SUMIFS(Financeiro!$G$4:$G$503,Financeiro!$B$4:$B$503,$A13,Financeiro!$D$4:$D$503,"Receita",Financeiro!$H$4:$H$503,"<>Cancelado") -> 0 | AJ13: =SUMIFS(Financeiro!$G$4:$G$503,Financeiro!$B$4:$B$503,$A13,Financeiro!$D$4:$D$503,"Gasto",Financeiro!$H$4:$H$503,"<>Cancelado") -> 0 | AK13: =SUMIFS(Financeiro!$G$4:$G$503,Financeiro!$B$4:$B$503,$A13,Financeiro!$D$4:$D$503,"Imposto",Financeiro!$H$4:$H$503,"<>Cancelado") -> 0 | AL13: =SUMIFS(Financeiro!$G$4:$G$503,Financeiro!$B$4:$B$503,$A13,Financeiro!$D$4:$D$503,"Marketing",Financeiro!$H$4:$H$503,"<>Cancelado") -> 0 | AM13: =AI13-AJ13-AK13-AL13 -> 0 | AN13: =IF(Config!$B$16=0,"",AI13/Config!$B$16) -> 0 | AO13: =IF(Config!$B$17=0,"",AJ13/Config!$B$17) -> 0 | AP13: =IF(T13=0,"",AL13/T13) | AQ13: =SUMIFS($AI$4:$AI$107,$D$4:$D$107,$D13,$B$4:$B$107,"<="&$B13) -> 0 | AR13: =SUMIFS($AJ$4:$AJ$107,$D$4:$D$107,$D13,$B$4:$B$107,"<="&$B13) -> 0 | AS13: =SUMIFS(Leads_Canal!$C$4:$C$503,Leads_Canal!$A$4:$A$503,$A13) -> 0 | AT13: =IF(E13=0,"",IF(E13=AR13,"OK","Divergente")) | AU13: =IF(N13=0,"",IF(N13=AD13,"OK","Divergente"))
A14: =Base_Semanal!A14 -> 2026-S12 | B14: =Base_Semanal!B14 -> 46097 | C14: =Base_Semanal!C14 -> 46103 | D14: =Base_Semanal!D14 -> 2026-03 | E14: =Base_Semanal!E14 -> 0 | F14: =Base_Semanal!F14 -> 0 | G14: =Base_Semanal!G14 -> 0 | H14: =Base_Semanal!H14 -> 0 | I14: =Base_Semanal!I14 -> 0 | J14: =H14+I14 -> 0 | K14: =IF(F14=0,"",G14/F14) | L14: =Base_Semanal!J14 -> 0 | M14: =Base_Semanal!K14 -> 0 | N14: =L14+M14 -> 0 | O14: =IF(J14=0,"",N14/J14) | P14: =Base_Semanal!L14 -> 0 | Q14: =Base_Semanal!M14 -> 0 | R14: =P14+Q14 -> 0 | S14: =Base_Semanal!N14 -> 0 | T14: =Base_Semanal!O14 -> 0 | U14: =IF(Base_Semanal!P14=0,"",Base_Semanal!Q14/Base_Semanal!P14) | V14: =IF(Base_Semanal!R14=0,"",Base_Semanal!S14/Base_Semanal!R14) | W14: =IF(Base_Semanal!P14+Base_Semanal!R14=0,"",(Base_Semanal!Q14+Base_Semanal!S14)/(Base_Semanal!P14+Base_Semanal!R14)) | X14: =Base_Semanal!T14 -> 0 | Y14: =Base_Semanal!U14 -> 0 | Z14: =Base_Semanal!V14 -> 0 | AA14: =Base_Semanal!W14 -> 0 | AB14: =COUNTIFS(Contratos!$B$4:$B$503,$A14,Contratos!$E$4:$E$503,"Avaliação") -> 0 | AC14: =SUMIFS(Contratos!$I$4:$I$503,Contratos!$B$4:$B$503,$A14,Contratos!$E$4:$E$503,"Avaliação") -> 0 | AD14: =COUNTIFS(Contratos!$B$4:$B$503,$A14,Contratos!$E$4:$E$503,"Protocolo") -> 0 | AE14: =SUMIFS(Contratos!$I$4:$I$503,Contratos!$B$4:$B$503,$A14,Contratos!$E$4:$E$503,"Protocolo") -> 0 | AF14: =AC14+AE14 -> 0 | AG14: =COUNTIFS(Contratos!$B$4:$B$503,$A14,Contratos!$J$4:$J$503,"À vista") -> 0 | AH14: =COUNTIFS(Contratos!$B$4:$B$503,$A14,Contratos!$J$4:$J$503,"Parcelado") -> 0 | AI14: =SUMIFS(Financeiro!$G$4:$G$503,Financeiro!$B$4:$B$503,$A14,Financeiro!$D$4:$D$503,"Receita",Financeiro!$H$4:$H$503,"<>Cancelado") -> 0 | AJ14: =SUMIFS(Financeiro!$G$4:$G$503,Financeiro!$B$4:$B$503,$A14,Financeiro!$D$4:$D$503,"Gasto",Financeiro!$H$4:$H$503,"<>Cancelado") -> 0 | AK14: =SUMIFS(Financeiro!$G$4:$G$503,Financeiro!$B$4:$B$503,$A14,Financeiro!$D$4:$D$503,"Imposto",Financeiro!$H$4:$H$503,"<>Cancelado") -> 0 | AL14: =SUMIFS(Financeiro!$G$4:$G$503,Financeiro!$B$4:$B$503,$A14,Financeiro!$D$4:$D$503,"Marketing",Financeiro!$H$4:$H$503,"<>Cancelado") -> 0 | AM14: =AI14-AJ14-AK14-AL14 -> 0 | AN14: =IF(Config!$B$16=0,"",AI14/Config!$B$16) -> 0 | AO14: =IF(Config!$B$17=0,"",AJ14/Config!$B$17) -> 0 | AP14: =IF(T14=0,"",AL14/T14) | AQ14: =SUMIFS($AI$4:$AI$107,$D$4:$D$107,$D14,$B$4:$B$107,"<="&$B14) -> 0 | AR14: =SUMIFS($AJ$4:$AJ$107,$D$4:$D$107,$D14,$B$4:$B$107,"<="&$B14) -> 0 | AS14: =SUMIFS(Leads_Canal!$C$4:$C$503,Leads_Canal!$A$4:$A$503,$A14) -> 0 | AT14: =IF(E14=0,"",IF(E14=AR14,"OK","Divergente")) | AU14: =IF(N14=0,"",IF(N14=AD14,"OK","Divergente"))
A15: =Base_Semanal!A15 -> 2026-S13 | B15: =Base_Semanal!B15 -> 46104 | C15: =Base_Semanal!C15 -> 46110 | D15: =Base_Semanal!D15 -> 2026-03 | E15: =Base_Semanal!E15 -> 0 | F15: =Base_Semanal!F15 -> 0 | G15: =Base_Semanal!G15 -> 0 | H15: =Base_Semanal!H15 -> 0 | I15: =Base_Semanal!I15 -> 0 | J15: =H15+I15 -> 0 | K15: =IF(F15=0,"",G15/F15) | L15: =Base_Semanal!J15 -> 0 | M15: =Base_Semanal!K15 -> 0 | N15: =L15+M15 -> 0 | O15: =IF(J15=0,"",N15/J15) | P15: =Base_Semanal!L15 -> 0 | Q15: =Base_Semanal!M15 -> 0 | R15: =P15+Q15 -> 0 | S15: =Base_Semanal!N15 -> 0 | T15: =Base_Semanal!O15 -> 0 | U15: =IF(Base_Semanal!P15=0,"",Base_Semanal!Q15/Base_Semanal!P15) | V15: =IF(Base_Semanal!R15=0,"",Base_Semanal!S15/Base_Semanal!R15) | W15: =IF(Base_Semanal!P15+Base_Semanal!R15=0,"",(Base_Semanal!Q15+Base_Semanal!S15)/(Base_Semanal!P15+Base_Semanal!R15)) | X15: =Base_Semanal!T15 -> 0 | Y15: =Base_Semanal!U15 -> 0 | Z15: =Base_Semanal!V15 -> 0 | AA15: =Base_Semanal!W15 -> 0 | AB15: =COUNTIFS(Contratos!$B$4:$B$503,$A15,Contratos!$E$4:$E$503,"Avaliação") -> 0 | AC15: =SUMIFS(Contratos!$I$4:$I$503,Contratos!$B$4:$B$503,$A15,Contratos!$E$4:$E$503,"Avaliação") -> 0 | AD15: =COUNTIFS(Contratos!$B$4:$B$503,$A15,Contratos!$E$4:$E$503,"Protocolo") -> 0 | AE15: =SUMIFS(Contratos!$I$4:$I$503,Contratos!$B$4:$B$503,$A15,Contratos!$E$4:$E$503,"Protocolo") -> 0 | AF15: =AC15+AE15 -> 0 | AG15: =COUNTIFS(Contratos!$B$4:$B$503,$A15,Contratos!$J$4:$J$503,"À vista") -> 0 | AH15: =COUNTIFS(Contratos!$B$4:$B$503,$A15,Contratos!$J$4:$J$503,"Parcelado") -> 0 | AI15: =SUMIFS(Financeiro!$G$4:$G$503,Financeiro!$B$4:$B$503,$A15,Financeiro!$D$4:$D$503,"Receita",Financeiro!$H$4:$H$503,"<>Cancelado") -> 0 | AJ15: =SUMIFS(Financeiro!$G$4:$G$503,Financeiro!$B$4:$B$503,$A15,Financeiro!$D$4:$D$503,"Gasto",Financeiro!$H$4:$H$503,"<>Cancelado") -> 0 | AK15: =SUMIFS(Financeiro!$G$4:$G$503,Financeiro!$B$4:$B$503,$A15,Financeiro!$D$4:$D$503,"Imposto",Financeiro!$H$4:$H$503,"<>Cancelado") -> 0 | AL15: =SUMIFS(Financeiro!$G$4:$G$503,Financeiro!$B$4:$B$503,$A15,Financeiro!$D$4:$D$503,"Marketing",Financeiro!$H$4:$H$503,"<>Cancelado") -> 0 | AM15: =AI15-AJ15-AK15-AL15 -> 0 | AN15: =IF(Config!$B$16=0,"",AI15/Config!$B$16) -> 0 | AO15: =IF(Config!$B$17=0,"",AJ15/Config!$B$17) -> 0 | AP15: =IF(T15=0,"",AL15/T15) | AQ15: =SUMIFS($AI$4:$AI$107,$D$4:$D$107,$D15,$B$4:$B$107,"<="&$B15) -> 0 | AR15: =SUMIFS($AJ$4:$AJ$107,$D$4:$D$107,$D15,$B$4:$B$107,"<="&$B15) -> 0 | AS15: =SUMIFS(Leads_Canal!$C$4:$C$503,Leads_Canal!$A$4:$A$503,$A15) -> 0 | AT15: =IF(E15=0,"",IF(E15=AR15,"OK","Divergente")) | AU15: =IF(N15=0,"",IF(N15=AD15,"OK","Divergente"))
... A107: =Base_Semanal!A107 -> 2027-S52 | B107: =Base_Semanal!B107 -> 46748 | C107: =Base_Semanal!C107 -> 46754 | D107: =Base_Semanal!D107 -> 2027-12 | E107: =Base_Semanal!E107 -> 0 | F107: =Base_Semanal!F107 -> 0 | G107: =Base_Semanal!G107 -> 0 | H107: =Base_Semanal!H107 -> 0 | I107: =Base_Semanal!I107 -> 0 | J107: =H107+I107 -> 0 | K107: =IF(F107=0,"",G107/F107) | L107: =Base_Semanal!J107 -> 0 | M107: =Base_Semanal!K107 -> 0 | N107: =L107+M107 -> 0 | O107: =IF(J107=0,"",N107/J107) | P107: =Base_Semanal!L107 -> 0 | Q107: =Base_Semanal!M107 -> 0 | R107: =P107+Q107 -> 0 | S107: =Base_Semanal!N107 -> 0 | T107: =Base_Semanal!O107 -> 0 | U107: =IF(Base_Semanal!P107=0,"",Base_Semanal!Q107/Base_Semanal!P107) | V107: =IF(Base_Semanal!R107=0,"",Base_Semanal!S107/Base_Semanal!R107) | W107: =IF(Base_Semanal!P107+Base_Semanal!R107=0,"",(Base_Semanal!Q107+Base_Semanal!S107)/(Base_Semanal!P107+Base_Semanal!R107)) | X107: =Base_Semanal!T107 -> 0 | Y107: =Base_Semanal!U107 -> 0 | Z107: =Base_Semanal!V107 -> 0 | AA107: =Base_Semanal!W107 -> 0 | AB107: =COUNTIFS(Contratos!$B$4:$B$503,$A107,Contratos!$E$4:$E$503,"Avaliação") -> 0 | AC107: =SUMIFS(Contratos!$I$4:$I$503,Contratos!$B$4:$B$503,$A107,Contratos!$E$4:$E$503,"Avaliação") -> 0 | AD107: =COUNTIFS(Contratos!$B$4:$B$503,$A107,Contratos!$E$4:$E$503,"Protocolo") -> 0 | AE107: =SUMIFS(Contratos!$I$4:$I$503,Contratos!$B$4:$B$503,$A107,Contratos!$E$4:$E$503,"Protocolo") -> 0 | AF107: =AC107+AE107 -> 0 | AG107: =COUNTIFS(Contratos!$B$4:$B$503,$A107,Contratos!$J$4:$J$503,"À vista") -> 0 | AH107: =COUNTIFS(Contratos!$B$4:$B$503,$A107,Contratos!$J$4:$J$503,"Parcelado") -> 0 | AI107: =SUMIFS(Financeiro!$G$4:$G$503,Financeiro!$B$4:$B$503,$A107,Financeiro!$D$4:$D$503,"Receita",Financeiro!$H$4:$H$503,"<>Cancelado") -> 0 | AJ107: =SUMIFS(Financeiro!$G$4:$G$503,Financeiro!$B$4:$B$503,$A107,Financeiro!$D$4:$D$503,"Gasto",Financeiro!$H$4:$H$503,"<>Cancelado") -> 0 | AK107: =SUMIFS(Financeiro!$G$4:$G$503,Financeiro!$B$4:$B$503,$A107,Financeiro!$D$4:$D$503,"Imposto",Financeiro!$H$4:$H$503,"<>Cancelado") -> 0 | AL107: =SUMIFS(Financeiro!$G$4:$G$503,Financeiro!$B$4:$B$503,$A107,Financeiro!$D$4:$D$503,"Marketing",Financeiro!$H$4:$H$503,"<>Cancelado") -> 0 | AM107: =AI107-AJ107-AK107-AL107 -> 0 | AN107: =IF(Config!$B$16=0,"",AI107/Config!$B$16) -> 0 | AO107: =IF(Config!$B$17=0,"",AJ107/Config!$B$17) -> 0 | AP107: =IF(T107=0,"",AL107/T107) | AQ107: =SUMIFS($AI$4:$AI$107,$D$4:$D$107,$D107,$B$4:$B$107,"<="&$B107) -> 0 | AR107: =SUMIFS($AJ$4:$AJ$107,$D$4:$D$107,$D107,$B$4:$B$107,"<="&$B107) -> 0 | AS107: =SUMIFS(Leads_Canal!$C$4:$C$503,Leads_Canal!$A$4:$A$503,$A107) -> 0 | AT107: =IF(E107=0,"",IF(E107=AR107,"OK","Divergente")) | AU107: =IF(N107=0,"",IF(N107=AD107,"OK","Divergente"))
A109: Semanas sem dados aparecem com zeros. 'Checagem' compara Base_Semanal com Leads_Canal e Contratos (Divergente = revisar os lançamentos).

Sheet Resumo_Mensal
A1: Resumo mensal (calculado)
A2: Semanas são atribuídas ao mês da sua data de início; contratos e lançamentos financeiros, ao mês da sua própria data.
A3: Mês | B3: Leads recebidos | C3: Aval. agendadas | D3: Aval. canceladas | E3: Aval. realizadas F1 | F3: Aval. realizadas F2 | G3: Aval. realizadas total | H3: Taxa canc. avaliações | I3: Contratos F1 | J3: Contratos F2 | K3: Contratos total | L3: Conversão aval→contrato | M3: Atend. F1 | N3: Atend. F2 | O3: Atend. total | P3: Cancelamentos atend. | Q3: Novos pacientes | R3: Ocupação manhã | S3: Ocupação tarde | T3: Ocupação total | U3: Aval. contratadas (qtd) | V3: Valor avaliações | W3: Protocolos contratados (qtd) | X3: Valor protocolos | Y3: Receitas | Z3: Gastos | AA3: Impostos | AB3: Marketing | AC3: Resultado | AD3: Receita vs meta mensal | AE3: Gastos vs meta mensal | AF3: CAC (marketing / novos pac.)
A4: 2026-01 | B4: =SUMIFS(Base_Semanal!$E$4:$E$107,Base_Semanal!$D$4:$D$107,$A4) -> 0 | C4: =SUMIFS(Base_Semanal!$F$4:$F$107,Base_Semanal!$D$4:$D$107,$A4) -> 0 | D4: =SUMIFS(Base_Semanal!$G$4:$G$107,Base_Semanal!$D$4:$D$107,$A4) -> 0 | E4: =SUMIFS(Base_Semanal!$H$4:$H$107,Base_Semanal!$D$4:$D$107,$A4) -> 0 | F4: =SUMIFS(Base_Semanal!$I$4:$I$107,Base_Semanal!$D$4:$D$107,$A4) -> 0 | G4: =E4+F4 -> 0 | H4: =IF(C4=0,"",D4/C4) | I4: =SUMIFS(Base_Semanal!$J$4:$J$107,Base_Semanal!$D$4:$D$107,$A4) -> 0 | J4: =SUMIFS(Base_Semanal!$K$4:$K$107,Base_Semanal!$D$4:$D$107,$A4) -> 0 | K4: =I4+J4 -> 0 | L4: =IF(G4=0,"",K4/G4) | M4: =SUMIFS(Base_Semanal!$L$4:$L$107,Base_Semanal!$D$4:$D$107,$A4) -> 0 | N4: =SUMIFS(Base_Semanal!$M$4:$M$107,Base_Semanal!$D$4:$D$107,$A4) -> 0 | O4: =M4+N4 -> 0 | P4: =SUMIFS(Base_Semanal!$N$4:$N$107,Base_Semanal!$D$4:$D$107,$A4) -> 0 | Q4: =SUMIFS(Base_Semanal!$O$4:$O$107,Base_Semanal!$D$4:$D$107,$A4) -> 0 | R4: =IF(SUMIFS(Base_Semanal!$P$4:$P$107,Base_Semanal!$D$4:$D$107,$A4)=0,"",SUMIFS(Base_Semanal!$Q$4:$Q$107,Base_Semanal!$D$4:$D$107,$A4)/SUMIFS(Base_Semanal!$P$4:$P$107,Base_Semanal!$D$4:$D$107,$A4)) | S4: =IF(SUMIFS(Base_Semanal!$R$4:$R$107,Base_Semanal!$D$4:$D$107,$A4)=0,"",SUMIFS(Base_Semanal!$S$4:$S$107,Base_Semanal!$D$4:$D$107,$A4)/SUMIFS(Base_Semanal!$R$4:$R$107,Base_Semanal!$D$4:$D$107,$A4)) | T4: =IF(SUMIFS(Base_Semanal!$P$4:$P$107,Base_Semanal!$D$4:$D$107,$A4)+SUMIFS(Base_Semanal!$R$4:$R$107,Base_Semanal!$D$4:$D$107,$A4)=0,"",(SUMIFS(Base_Semanal!$Q$4:$Q$107,Base_Semanal!$D$4:$D$107,$A4)+SUMIFS(Base_Semanal!$S$4:$S$107,Base_Semanal!$D$4:$D$107,$A4))/(SUMIFS(Base_Semanal!$P$4:$P$107,Base_Semanal!$D$4:$D$107,$A4)+SUMIFS(Base_Semanal!$R$4:$R$107,Base_Semanal!$D$4:$D$107,$A4))) | U4: =COUNTIFS(Contratos!$C$4:$C$503,$A4,Contratos!$E$4:$E$503,"Avaliação") -> 0 | V4: =SUMIFS(Contratos!$I$4:$I$503,Contratos!$C$4:$C$503,$A4,Contratos!$E$4:$E$503,"Avaliação") -> 0 | W4: =COUNTIFS(Contratos!$C$4:$C$503,$A4,Contratos!$E$4:$E$503,"Protocolo") -> 0 | X4: =SUMIFS(Contratos!$I$4:$I$503,Contratos!$C$4:$C$503,$A4,Contratos!$E$4:$E$503,"Protocolo") -> 0 | Y4: =SUMIFS(Financeiro!$G$4:$G$503,Financeiro!$C$4:$C$503,$A4,Financeiro!$D$4:$D$503,"Receita",Financeiro!$H$4:$H$503,"<>Cancelado") -> 0 | Z4: =SUMIFS(Financeiro!$G$4:$G$503,Financeiro!$C$4:$C$503,$A4,Financeiro!$D$4:$D$503,"Gasto",Financeiro!$H$4:$H$503,"<>Cancelado") -> 0 | AA4: =SUMIFS(Financeiro!$G$4:$G$503,Financeiro!$C$4:$C$503,$A4,Financeiro!$D$4:$D$503,"Imposto",Financeiro!$H$4:$H$503,"<>Cancelado") -> 0 | AB4: =SUMIFS(Financeiro!$G$4:$G$503,Financeiro!$C$4:$C$503,$A4,Financeiro!$D$4:$D$503,"Marketing",Financeiro!$H$4:$H$503,"<>Cancelado") -> 0 | AC4: =Y4-Z4-AA4-AB4 -> 0 | AD4: =IF(Config!$C$16=0,"",Y4/Config!$C$16) -> 0 | AE4: =IF(Config!$C$17=0,"",Z4/Config!$C$17) -> 0 | AF4: =IF(Q4=0,"",AB4/Q4)
A5: 2026-02 | B5: =SUMIFS(Base_Semanal!$E$4:$E$107,Base_Semanal!$D$4:$D$107,$A5) -> 0 | C5: =SUMIFS(Base_Semanal!$F$4:$F$107,Base_Semanal!$D$4:$D$107,$A5) -> 0 | D5: =SUMIFS(Base_Semanal!$G$4:$G$107,Base_Semanal!$D$4:$D$107,$A5) -> 0 | E5: =SUMIFS(Base_Semanal!$H$4:$H$107,Base_Semanal!$D$4:$D$107,$A5) -> 0 | F5: =SUMIFS(Base_Semanal!$I$4:$I$107,Base_Semanal!$D$4:$D$107,$A5) -> 0 | G5: =E5+F5 -> 0 | H5: =IF(C5=0,"",D5/C5) | I5: =SUMIFS(Base_Semanal!$J$4:$J$107,Base_Semanal!$D$4:$D$107,$A5) -> 0 | J5: =SUMIFS(Base_Semanal!$K$4:$K$107,Base_Semanal!$D$4:$D$107,$A5) -> 0 | K5: =I5+J5 -> 0 | L5: =IF(G5=0,"",K5/G5) | M5: =SUMIFS(Base_Semanal!$L$4:$L$107,Base_Semanal!$D$4:$D$107,$A5) -> 0 | N5: =SUMIFS(Base_Semanal!$M$4:$M$107,Base_Semanal!$D$4:$D$107,$A5) -> 0 | O5: =M5+N5 -> 0 | P5: =SUMIFS(Base_Semanal!$N$4:$N$107,Base_Semanal!$D$4:$D$107,$A5) -> 0 | Q5: =SUMIFS(Base_Semanal!$O$4:$O$107,Base_Semanal!$D$4:$D$107,$A5) -> 0 | R5: =IF(SUMIFS(Base_Semanal!$P$4:$P$107,Base_Semanal!$D$4:$D$107,$A5)=0,"",SUMIFS(Base_Semanal!$Q$4:$Q$107,Base_Semanal!$D$4:$D$107,$A5)/SUMIFS(Base_Semanal!$P$4:$P$107,Base_Semanal!$D$4:$D$107,$A5)) | S5: =IF(SUMIFS(Base_Semanal!$R$4:$R$107,Base_Semanal!$D$4:$D$107,$A5)=0,"",SUMIFS(Base_Semanal!$S$4:$S$107,Base_Semanal!$D$4:$D$107,$A5)/SUMIFS(Base_Semanal!$R$4:$R$107,Base_Semanal!$D$4:$D$107,$A5)) | T5: =IF(SUMIFS(Base_Semanal!$P$4:$P$107,Base_Semanal!$D$4:$D$107,$A5)+SUMIFS(Base_Semanal!$R$4:$R$107,Base_Semanal!$D$4:$D$107,$A5)=0,"",(SUMIFS(Base_Semanal!$Q$4:$Q$107,Base_Semanal!$D$4:$D$107,$A5)+SUMIFS(Base_Semanal!$S$4:$S$107,Base_Semanal!$D$4:$D$107,$A5))/(SUMIFS(Base_Semanal!$P$4:$P$107,Base_Semanal!$D$4:$D$107,$A5)+SUMIFS(Base_Semanal!$R$4:$R$107,Base_Semanal!$D$4:$D$107,$A5))) | U5: =COUNTIFS(Contratos!$C$4:$C$503,$A5,Contratos!$E$4:$E$503,"Avaliação") -> 0 | V5: =SUMIFS(Contratos!$I$4:$I$503,Contratos!$C$4:$C$503,$A5,Contratos!$E$4:$E$503,"Avaliação") -> 0 | W5: =COUNTIFS(Contratos!$C$4:$C$503,$A5,Contratos!$E$4:$E$503,"Protocolo") -> 0 | X5: =SUMIFS(Contratos!$I$4:$I$503,Contratos!$C$4:$C$503,$A5,Contratos!$E$4:$E$503,"Protocolo") -> 0 | Y5: =SUMIFS(Financeiro!$G$4:$G$503,Financeiro!$C$4:$C$503,$A5,Financeiro!$D$4:$D$503,"Receita",Financeiro!$H$4:$H$503,"<>Cancelado") -> 0 | Z5: =SUMIFS(Financeiro!$G$4:$G$503,Financeiro!$C$4:$C$503,$A5,Financeiro!$D$4:$D$503,"Gasto",Financeiro!$H$4:$H$503,"<>Cancelado") -> 0 | AA5: =SUMIFS(Financeiro!$G$4:$G$503,Financeiro!$C$4:$C$503,$A5,Financeiro!$D$4:$D$503,"Imposto",Financeiro!$H$4:$H$503,"<>Cancelado") -> 0 | AB5: =SUMIFS(Financeiro!$G$4:$G$503,Financeiro!$C$4:$C$503,$A5,Financeiro!$D$4:$D$503,"Marketing",Financeiro!$H$4:$H$503,"<>Cancelado") -> 0 | AC5: =Y5-Z5-AA5-AB5 -> 0 | AD5: =IF(Config!$C$16=0,"",Y5/Config!$C$16) -> 0 | AE5: =IF(Config!$C$17=0,"",Z5/Config!$C$17) -> 0 | AF5: =IF(Q5=0,"",AB5/Q5)
A6: 2026-03 | B6: =SUMIFS(Base_Semanal!$E$4:$E$107,Base_Semanal!$D$4:$D$107,$A6) -> 0 | C6: =SUMIFS(Base_Semanal!$F$4:$F$107,Base_Semanal!$D$4:$D$107,$A6) -> 0 | D6: =SUMIFS(Base_Semanal!$G$4:$G$107,Base_Semanal!$D$4:$D$107,$A6) -> 0 | E6: =SUMIFS(Base_Semanal!$H$4:$H$107,Base_Semanal!$D$4:$D$107,$A6) -> 0 | F6: =SUMIFS(Base_Semanal!$I$4:$I$107,Base_Semanal!$D$4:$D$107,$A6) -> 0 | G6: =E6+F6 -> 0 | H6: =IF(C6=0,"",D6/C6) | I6: =SUMIFS(Base_Semanal!$J$4:$J$107,Base_Semanal!$D$4:$D$107,$A6) -> 0 | J6: =SUMIFS(Base_Semanal!$K$4:$K$107,Base_Semanal!$D$4:$D$107,$A6) -> 0 | K6: =I6+J6 -> 0 | L6: =IF(G6=0,"",K6/G6) | M6: =SUMIFS(Base_Semanal!$L$4:$L$107,Base_Semanal!$D$4:$D$107,$A6) -> 0 | N6: =SUMIFS(Base_Semanal!$M$4:$M$107,Base_Semanal!$D$4:$D$107,$A6) -> 0 | O6: =M6+N6 -> 0 | P6: =SUMIFS(Base_Semanal!$N$4:$N$107,Base_Semanal!$D$4:$D$107,$A6) -> 0 | Q6: =SUMIFS(Base_Semanal!$O$4:$O$107,Base_Semanal!$D$4:$D$107,$A6) -> 0 | R6: =IF(SUMIFS(Base_Semanal!$P$4:$P$107,Base_Semanal!$D$4:$D$107,$A6)=0,"",SUMIFS(Base_Semanal!$Q$4:$Q$107,Base_Semanal!$D$4:$D$107,$A6)/SUMIFS(Base_Semanal!$P$4:$P$107,Base_Semanal!$D$4:$D$107,$A6)) | S6: =IF(SUMIFS(Base_Semanal!$R$4:$R$107,Base_Semanal!$D$4:$D$107,$A6)=0,"",SUMIFS(Base_Semanal!$S$4:$S$107,Base_Semanal!$D$4:$D$107,$A6)/SUMIFS(Base_Semanal!$R$4:$R$107,Base_Semanal!$D$4:$D$107,$A6)) | T6: =IF(SUMIFS(Base_Semanal!$P$4:$P$107,Base_Semanal!$D$4:$D$107,$A6)+SUMIFS(Base_Semanal!$R$4:$R$107,Base_Semanal!$D$4:$D$107,$A6)=0,"",(SUMIFS(Base_Semanal!$Q$4:$Q$107,Base_Semanal!$D$4:$D$107,$A6)+SUMIFS(Base_Semanal!$S$4:$S$107,Base_Semanal!$D$4:$D$107,$A6))/(SUMIFS(Base_Semanal!$P$4:$P$107,Base_Semanal!$D$4:$D$107,$A6)+SUMIFS(Base_Semanal!$R$4:$R$107,Base_Semanal!$D$4:$D$107,$A6))) | U6: =COUNTIFS(Contratos!$C$4:$C$503,$A6,Contratos!$E$4:$E$503,"Avaliação") -> 0 | V6: =SUMIFS(Contratos!$I$4:$I$503,Contratos!$C$4:$C$503,$A6,Contratos!$E$4:$E$503,"Avaliação") -> 0 | W6: =COUNTIFS(Contratos!$C$4:$C$503,$A6,Contratos!$E$4:$E$503,"Protocolo") -> 0 | X6: =SUMIFS(Contratos!$I$4:$I$503,Contratos!$C$4:$C$503,$A6,Contratos!$E$4:$E$503,"Protocolo") -> 0 | Y6: =SUMIFS(Financeiro!$G$4:$G$503,Financeiro!$C$4:$C$503,$A6,Financeiro!$D$4:$D$503,"Receita",Financeiro!$H$4:$H$503,"<>Cancelado") -> 0 | Z6: =SUMIFS(Financeiro!$G$4:$G$503,Financeiro!$C$4:$C$503,$A6,Financeiro!$D$4:$D$503,"Gasto",Financeiro!$H$4:$H$503,"<>Cancelado") -> 0 | AA6: =SUMIFS(Financeiro!$G$4:$G$503,Financeiro!$C$4:$C$503,$A6,Financeiro!$D$4:$D$503,"Imposto",Financeiro!$H$4:$H$503,"<>Cancelado") -> 0 | AB6: =SUMIFS(Financeiro!$G$4:$G$503,Financeiro!$C$4:$C$503,$A6,Financeiro!$D$4:$D$503,"Marketing",Financeiro!$H$4:$H$503,"<>Cancelado") -> 0 | AC6: =Y6-Z6-AA6-AB6 -> 0 | AD6: =IF(Config!$C$16=0,"",Y6/Config!$C$16) -> 0 | AE6: =IF(Config!$C$17=0,"",Z6/Config!$C$17) -> 0 | AF6: =IF(Q6=0,"",AB6/Q6)
A7: 2026-04 | B7: =SUMIFS(Base_Semanal!$E$4:$E$107,Base_Semanal!$D$4:$D$107,$A7) -> 0 | C7: =SUMIFS(Base_Semanal!$F$4:$F$107,Base_Semanal!$D$4:$D$107,$A7) -> 0 | D7: =SUMIFS(Base_Semanal!$G$4:$G$107,Base_Semanal!$D$4:$D$107,$A7) -> 0 | E7: =SUMIFS(Base_Semanal!$H$4:$H$107,Base_Semanal!$D$4:$D$107,$A7) -> 0 | F7: =SUMIFS(Base_Semanal!$I$4:$I$107,Base_Semanal!$D$4:$D$107,$A7) -> 0 | G7: =E7+F7 -> 0 | H7: =IF(C7=0,"",D7/C7) | I7: =SUMIFS(Base_Semanal!$J$4:$J$107,Base_Semanal!$D$4:$D$107,$A7) -> 0 | J7: =SUMIFS(Base_Semanal!$K$4:$K$107,Base_Semanal!$D$4:$D$107,$A7) -> 0 | K7: =I7+J7 -> 0 | L7: =IF(G7=0,"",K7/G7) | M7: =SUMIFS(Base_Semanal!$L$4:$L$107,Base_Semanal!$D$4:$D$107,$A7) -> 0 | N7: =SUMIFS(Base_Semanal!$M$4:$M$107,Base_Semanal!$D$4:$D$107,$A7) -> 0 | O7: =M7+N7 -> 0 | P7: =SUMIFS(Base_Semanal!$N$4:$N$107,Base_Semanal!$D$4:$D$107,$A7) -> 0 | Q7: =SUMIFS(Base_Semanal!$O$4:$O$107,Base_Semanal!$D$4:$D$107,$A7) -> 0 | R7: =IF(SUMIFS(Base_Semanal!$P$4:$P$107,Base_Semanal!$D$4:$D$107,$A7)=0,"",SUMIFS(Base_Semanal!$Q$4:$Q$107,Base_Semanal!$D$4:$D$107,$A7)/SUMIFS(Base_Semanal!$P$4:$P$107,Base_Semanal!$D$4:$D$107,$A7)) | S7: =IF(SUMIFS(Base_Semanal!$R$4:$R$107,Base_Semanal!$D$4:$D$107,$A7)=0,"",SUMIFS(Base_Semanal!$S$4:$S$107,Base_Semanal!$D$4:$D$107,$A7)/SUMIFS(Base_Semanal!$R$4:$R$107,Base_Semanal!$D$4:$D$107,$A7)) | T7: =IF(SUMIFS(Base_Semanal!$P$4:$P$107,Base_Semanal!$D$4:$D$107,$A7)+SUMIFS(Base_Semanal!$R$4:$R$107,Base_Semanal!$D$4:$D$107,$A7)=0,"",(SUMIFS(Base_Semanal!$Q$4:$Q$107,Base_Semanal!$D$4:$D$107,$A7)+SUMIFS(Base_Semanal!$S$4:$S$107,Base_Semanal!$D$4:$D$107,$A7))/(SUMIFS(Base_Semanal!$P$4:$P$107,Base_Semanal!$D$4:$D$107,$A7)+SUMIFS(Base_Semanal!$R$4:$R$107,Base_Semanal!$D$4:$D$107,$A7))) | U7: =COUNTIFS(Contratos!$C$4:$C$503,$A7,Contratos!$E$4:$E$503,"Avaliação") -> 0 | V7: =SUMIFS(Contratos!$I$4:$I$503,Contratos!$C$4:$C$503,$A7,Contratos!$E$4:$E$503,"Avaliação") -> 0 | W7: =COUNTIFS(Contratos!$C$4:$C$503,$A7,Contratos!$E$4:$E$503,"Protocolo") -> 0 | X7: =SUMIFS(Contratos!$I$4:$I$503,Contratos!$C$4:$C$503,$A7,Contratos!$E$4:$E$503,"Protocolo") -> 0 | Y7: =SUMIFS(Financeiro!$G$4:$G$503,Financeiro!$C$4:$C$503,$A7,Financeiro!$D$4:$D$503,"Receita",Financeiro!$H$4:$H$503,"<>Cancelado") -> 0 | Z7: =SUMIFS(Financeiro!$G$4:$G$503,Financeiro!$C$4:$C$503,$A7,Financeiro!$D$4:$D$503,"Gasto",Financeiro!$H$4:$H$503,"<>Cancelado") -> 0 | AA7: =SUMIFS(Financeiro!$G$4:$G$503,Financeiro!$C$4:$C$503,$A7,Financeiro!$D$4:$D$503,"Imposto",Financeiro!$H$4:$H$503,"<>Cancelado") -> 0 | AB7: =SUMIFS(Financeiro!$G$4:$G$503,Financeiro!$C$4:$C$503,$A7,Financeiro!$D$4:$D$503,"Marketing",Financeiro!$H$4:$H$503,"<>Cancelado") -> 0 | AC7: =Y7-Z7-AA7-AB7 -> 0 | AD7: =IF(Config!$C$16=0,"",Y7/Config!$C$16) -> 0 | AE7: =IF(Config!$C$17=0,"",Z7/Config!$C$17) -> 0 | AF7: =IF(Q7=0,"",AB7/Q7)
A8: 2026-05 | B8: =SUMIFS(Base_Semanal!$E$4:$E$107,Base_Semanal!$D$4:$D$107,$A8) -> 0 | C8: =SUMIFS(Base_Semanal!$F$4:$F$107,Base_Semanal!$D$4:$D$107,$A8) -> 0 | D8: =SUMIFS(Base_Semanal!$G$4:$G$107,Base_Semanal!$D$4:$D$107,$A8) -> 0 | E8: =SUMIFS(Base_Semanal!$H$4:$H$107,Base_Semanal!$D$4:$D$107,$A8) -> 0 | F8: =SUMIFS(Base_Semanal!$I$4:$I$107,Base_Semanal!$D$4:$D$107,$A8) -> 0 | G8: =E8+F8 -> 0 | H8: =IF(C8=0,"",D8/C8) | I8: =SUMIFS(Base_Semanal!$J$4:$J$107,Base_Semanal!$D$4:$D$107,$A8) -> 0 | J8: =SUMIFS(Base_Semanal!$K$4:$K$107,Base_Semanal!$D$4:$D$107,$A8) -> 0 | K8: =I8+J8 -> 0 | L8: =IF(G8=0,"",K8/G8) | M8: =SUMIFS(Base_Semanal!$L$4:$L$107,Base_Semanal!$D$4:$D$107,$A8) -> 0 | N8: =SUMIFS(Base_Semanal!$M$4:$M$107,Base_Semanal!$D$4:$D$107,$A8) -> 0 | O8: =M8+N8 -> 0 | P8: =SUMIFS(Base_Semanal!$N$4:$N$107,Base_Semanal!$D$4:$D$107,$A8) -> 0 | Q8: =SUMIFS(Base_Semanal!$O$4:$O$107,Base_Semanal!$D$4:$D$107,$A8) -> 0 | R8: =IF(SUMIFS(Base_Semanal!$P$4:$P$107,Base_Semanal!$D$4:$D$107,$A8)=0,"",SUMIFS(Base_Semanal!$Q$4:$Q$107,Base_Semanal!$D$4:$D$107,$A8)/SUMIFS(Base_Semanal!$P$4:$P$107,Base_Semanal!$D$4:$D$107,$A8)) | S8: =IF(SUMIFS(Base_Semanal!$R$4:$R$107,Base_Semanal!$D$4:$D$107,$A8)=0,"",SUMIFS(Base_Semanal!$S$4:$S$107,Base_Semanal!$D$4:$D$107,$A8)/SUMIFS(Base_Semanal!$R$4:$R$107,Base_Semanal!$D$4:$D$107,$A8)) | T8: =IF(SUMIFS(Base_Semanal!$P$4:$P$107,Base_Semanal!$D$4:$D$107,$A8)+SUMIFS(Base_Semanal!$R$4:$R$107,Base_Semanal!$D$4:$D$107,$A8)=0,"",(SUMIFS(Base_Semanal!$Q$4:$Q$107,Base_Semanal!$D$4:$D$107,$A8)+SUMIFS(Base_Semanal!$S$4:$S$107,Base_Semanal!$D$4:$D$107,$A8))/(SUMIFS(Base_Semanal!$P$4:$P$107,Base_Semanal!$D$4:$D$107,$A8)+SUMIFS(Base_Semanal!$R$4:$R$107,Base_Semanal!$D$4:$D$107,$A8))) | U8: =COUNTIFS(Contratos!$C$4:$C$503,$A8,Contratos!$E$4:$E$503,"Avaliação") -> 0 | V8: =SUMIFS(Contratos!$I$4:$I$503,Contratos!$C$4:$C$503,$A8,Contratos!$E$4:$E$503,"Avaliação") -> 0 | W8: =COUNTIFS(Contratos!$C$4:$C$503,$A8,Contratos!$E$4:$E$503,"Protocolo") -> 0 | X8: =SUMIFS(Contratos!$I$4:$I$503,Contratos!$C$4:$C$503,$A8,Contratos!$E$4:$E$503,"Protocolo") -> 0 | Y8: =SUMIFS(Financeiro!$G$4:$G$503,Financeiro!$C$4:$C$503,$A8,Financeiro!$D$4:$D$503,"Receita",Financeiro!$H$4:$H$503,"<>Cancelado") -> 0 | Z8: =SUMIFS(Financeiro!$G$4:$G$503,Financeiro!$C$4:$C$503,$A8,Financeiro!$D$4:$D$503,"Gasto",Financeiro!$H$4:$H$503,"<>Cancelado") -> 0 | AA8: =SUMIFS(Financeiro!$G$4:$G$503,Financeiro!$C$4:$C$503,$A8,Financeiro!$D$4:$D$503,"Imposto",Financeiro!$H$4:$H$503,"<>Cancelado") -> 0 | AB8: =SUMIFS(Financeiro!$G$4:$G$503,Financeiro!$C$4:$C$503,$A8,Financeiro!$D$4:$D$503,"Marketing",Financeiro!$H$4:$H$503,"<>Cancelado") -> 0 | AC8: =Y8-Z8-AA8-AB8 -> 0 | AD8: =IF(Config!$C$16=0,"",Y8/Config!$C$16) -> 0 | AE8: =IF(Config!$C$17=0,"",Z8/Config!$C$17) -> 0 | AF8: =IF(Q8=0,"",AB8/Q8)
A9: 2026-06 | B9: =SUMIFS(Base_Semanal!$E$4:$E$107,Base_Semanal!$D$4:$D$107,$A9) -> 0 | C9: =SUMIFS(Base_Semanal!$F$4:$F$107,Base_Semanal!$D$4:$D$107,$A9) -> 0 | D9: =SUMIFS(Base_Semanal!$G$4:$G$107,Base_Semanal!$D$4:$D$107,$A9) -> 0 | E9: =SUMIFS(Base_Semanal!$H$4:$H$107,Base_Semanal!$D$4:$D$107,$A9) -> 0 | F9: =SUMIFS(Base_Semanal!$I$4:$I$107,Base_Semanal!$D$4:$D$107,$A9) -> 0 | G9: =E9+F9 -> 0 | H9: =IF(C9=0,"",D9/C9) | I9: =SUMIFS(Base_Semanal!$J$4:$J$107,Base_Semanal!$D$4:$D$107,$A9) -> 0 | J9: =SUMIFS(Base_Semanal!$K$4:$K$107,Base_Semanal!$D$4:$D$107,$A9) -> 0 | K9: =I9+J9 -> 0 | L9: =IF(G9=0,"",K9/G9) | M9: =SUMIFS(Base_Semanal!$L$4:$L$107,Base_Semanal!$D$4:$D$107,$A9) -> 0 | N9: =SUMIFS(Base_Semanal!$M$4:$M$107,Base_Semanal!$D$4:$D$107,$A9) -> 0 | O9: =M9+N9 -> 0 | P9: =SUMIFS(Base_Semanal!$N$4:$N$107,Base_Semanal!$D$4:$D$107,$A9) -> 0 | Q9: =SUMIFS(Base_Semanal!$O$4:$O$107,Base_Semanal!$D$4:$D$107,$A9) -> 0 | R9: =IF(SUMIFS(Base_Semanal!$P$4:$P$107,Base_Semanal!$D$4:$D$107,$A9)=0,"",SUMIFS(Base_Semanal!$Q$4:$Q$107,Base_Semanal!$D$4:$D$107,$A9)/SUMIFS(Base_Semanal!$P$4:$P$107,Base_Semanal!$D$4:$D$107,$A9)) | S9: =IF(SUMIFS(Base_Semanal!$R$4:$R$107,Base_Semanal!$D$4:$D$107,$A9)=0,"",SUMIFS(Base_Semanal!$S$4:$S$107,Base_Semanal!$D$4:$D$107,$A9)/SUMIFS(Base_Semanal!$R$4:$R$107,Base_Semanal!$D$4:$D$107,$A9)) | T9: =IF(SUMIFS(Base_Semanal!$P$4:$P$107,Base_Semanal!$D$4:$D$107,$A9)+SUMIFS(Base_Semanal!$R$4:$R$107,Base_Semanal!$D$4:$D$107,$A9)=0,"",(SUMIFS(Base_Semanal!$Q$4:$Q$107,Base_Semanal!$D$4:$D$107,$A9)+SUMIFS(Base_Semanal!$S$4:$S$107,Base_Semanal!$D$4:$D$107,$A9))/(SUMIFS(Base_Semanal!$P$4:$P$107,Base_Semanal!$D$4:$D$107,$A9)+SUMIFS(Base_Semanal!$R$4:$R$107,Base_Semanal!$D$4:$D$107,$A9))) | U9: =COUNTIFS(Contratos!$C$4:$C$503,$A9,Contratos!$E$4:$E$503,"Avaliação") -> 0 | V9: =SUMIFS(Contratos!$I$4:$I$503,Contratos!$C$4:$C$503,$A9,Contratos!$E$4:$E$503,"Avaliação") -> 0 | W9: =COUNTIFS(Contratos!$C$4:$C$503,$A9,Contratos!$E$4:$E$503,"Protocolo") -> 0 | X9: =SUMIFS(Contratos!$I$4:$I$503,Contratos!$C$4:$C$503,$A9,Contratos!$E$4:$E$503,"Protocolo") -> 0 | Y9: =SUMIFS(Financeiro!$G$4:$G$503,Financeiro!$C$4:$C$503,$A9,Financeiro!$D$4:$D$503,"Receita",Financeiro!$H$4:$H$503,"<>Cancelado") -> 0 | Z9: =SUMIFS(Financeiro!$G$4:$G$503,Financeiro!$C$4:$C$503,$A9,Financeiro!$D$4:$D$503,"Gasto",Financeiro!$H$4:$H$503,"<>Cancelado") -> 0 | AA9: =SUMIFS(Financeiro!$G$4:$G$503,Financeiro!$C$4:$C$503,$A9,Financeiro!$D$4:$D$503,"Imposto",Financeiro!$H$4:$H$503,"<>Cancelado") -> 0 | AB9: =SUMIFS(Financeiro!$G$4:$G$503,Financeiro!$C$4:$C$503,$A9,Financeiro!$D$4:$D$503,"Marketing",Financeiro!$H$4:$H$503,"<>Cancelado") -> 0 | AC9: =Y9-Z9-AA9-AB9 -> 0 | AD9: =IF(Config!$C$16=0,"",Y9/Config!$C$16) -> 0 | AE9: =IF(Config!$C$17=0,"",Z9/Config!$C$17) -> 0 | AF9: =IF(Q9=0,"",AB9/Q9)
A10: 2026-07 | B10: =SUMIFS(Base_Semanal!$E$4:$E$107,Base_Semanal!$D$4:$D$107,$A10) -> 0 | C10: =SUMIFS(Base_Semanal!$F$4:$F$107,Base_Semanal!$D$4:$D$107,$A10) -> 0 | D10: =SUMIFS(Base_Semanal!$G$4:$G$107,Base_Semanal!$D$4:$D$107,$A10) -> 0 | E10: =SUMIFS(Base_Semanal!$H$4:$H$107,Base_Semanal!$D$4:$D$107,$A10) -> 0 | F10: =SUMIFS(Base_Semanal!$I$4:$I$107,Base_Semanal!$D$4:$D$107,$A10) -> 0 | G10: =E10+F10 -> 0 | H10: =IF(C10=0,"",D10/C10) | I10: =SUMIFS(Base_Semanal!$J$4:$J$107,Base_Semanal!$D$4:$D$107,$A10) -> 0 | J10: =SUMIFS(Base_Semanal!$K$4:$K$107,Base_Semanal!$D$4:$D$107,$A10) -> 0 | K10: =I10+J10 -> 0 | L10: =IF(G10=0,"",K10/G10) | M10: =SUMIFS(Base_Semanal!$L$4:$L$107,Base_Semanal!$D$4:$D$107,$A10) -> 0 | N10: =SUMIFS(Base_Semanal!$M$4:$M$107,Base_Semanal!$D$4:$D$107,$A10) -> 0 | O10: =M10+N10 -> 0 | P10: =SUMIFS(Base_Semanal!$N$4:$N$107,Base_Semanal!$D$4:$D$107,$A10) -> 0 | Q10: =SUMIFS(Base_Semanal!$O$4:$O$107,Base_Semanal!$D$4:$D$107,$A10) -> 0 | R10: =IF(SUMIFS(Base_Semanal!$P$4:$P$107,Base_Semanal!$D$4:$D$107,$A10)=0,"",SUMIFS(Base_Semanal!$Q$4:$Q$107,Base_Semanal!$D$4:$D$107,$A10)/SUMIFS(Base_Semanal!$P$4:$P$107,Base_Semanal!$D$4:$D$107,$A10)) | S10: =IF(SUMIFS(Base_Semanal!$R$4:$R$107,Base_Semanal!$D$4:$D$107,$A10)=0,"",SUMIFS(Base_Semanal!$S$4:$S$107,Base_Semanal!$D$4:$D$107,$A10)/SUMIFS(Base_Semanal!$R$4:$R$107,Base_Semanal!$D$4:$D$107,$A10)) | T10: =IF(SUMIFS(Base_Semanal!$P$4:$P$107,Base_Semanal!$D$4:$D$107,$A10)+SUMIFS(Base_Semanal!$R$4:$R$107,Base_Semanal!$D$4:$D$107,$A10)=0,"",(SUMIFS(Base_Semanal!$Q$4:$Q$107,Base_Semanal!$D$4:$D$107,$A10)+SUMIFS(Base_Semanal!$S$4:$S$107,Base_Semanal!$D$4:$D$107,$A10))/(SUMIFS(Base_Semanal!$P$4:$P$107,Base_Semanal!$D$4:$D$107,$A10)+SUMIFS(Base_Semanal!$R$4:$R$107,Base_Semanal!$D$4:$D$107,$A10))) | U10: =COUNTIFS(Contratos!$C$4:$C$503,$A10,Contratos!$E$4:$E$503,"Avaliação") -> 0 | V10: =SUMIFS(Contratos!$I$4:$I$503,Contratos!$C$4:$C$503,$A10,Contratos!$E$4:$E$503,"Avaliação") -> 0 | W10: =COUNTIFS(Contratos!$C$4:$C$503,$A10,Contratos!$E$4:$E$503,"Protocolo") -> 0 | X10: =SUMIFS(Contratos!$I$4:$I$503,Contratos!$C$4:$C$503,$A10,Contratos!$E$4:$E$503,"Protocolo") -> 0 | Y10: =SUMIFS(Financeiro!$G$4:$G$503,Financeiro!$C$4:$C$503,$A10,Financeiro!$D$4:$D$503,"Receita",Financeiro!$H$4:$H$503,"<>Cancelado") -> 0 | Z10: =SUMIFS(Financeiro!$G$4:$G$503,Financeiro!$C$4:$C$503,$A10,Financeiro!$D$4:$D$503,"Gasto",Financeiro!$H$4:$H$503,"<>Cancelado") -> 0 | AA10: =SUMIFS(Financeiro!$G$4:$G$503,Financeiro!$C$4:$C$503,$A10,Financeiro!$D$4:$D$503,"Imposto",Financeiro!$H$4:$H$503,"<>Cancelado") -> 0 | AB10: =SUMIFS(Financeiro!$G$4:$G$503,Financeiro!$C$4:$C$503,$A10,Financeiro!$D$4:$D$503,"Marketing",Financeiro!$H$4:$H$503,"<>Cancelado") -> 0 | AC10: =Y10-Z10-AA10-AB10 -> 0 | AD10: =IF(Config!$C$16=0,"",Y10/Config!$C$16) -> 0 | AE10: =IF(Config!$C$17=0,"",Z10/Config!$C$17) -> 0 | AF10: =IF(Q10=0,"",AB10/Q10)
A11: 2026-08 | B11: =SUMIFS(Base_Semanal!$E$4:$E$107,Base_Semanal!$D$4:$D$107,$A11) -> 0 | C11: =SUMIFS(Base_Semanal!$F$4:$F$107,Base_Semanal!$D$4:$D$107,$A11) -> 0 | D11: =SUMIFS(Base_Semanal!$G$4:$G$107,Base_Semanal!$D$4:$D$107,$A11) -> 0 | E11: =SUMIFS(Base_Semanal!$H$4:$H$107,Base_Semanal!$D$4:$D$107,$A11) -> 0 | F11: =SUMIFS(Base_Semanal!$I$4:$I$107,Base_Semanal!$D$4:$D$107,$A11) -> 0 | G11: =E11+F11 -> 0 | H11: =IF(C11=0,"",D11/C11) | I11: =SUMIFS(Base_Semanal!$J$4:$J$107,Base_Semanal!$D$4:$D$107,$A11) -> 0 | J11: =SUMIFS(Base_Semanal!$K$4:$K$107,Base_Semanal!$D$4:$D$107,$A11) -> 0 | K11: =I11+J11 -> 0 | L11: =IF(G11=0,"",K11/G11) | M11: =SUMIFS(Base_Semanal!$L$4:$L$107,Base_Semanal!$D$4:$D$107,$A11) -> 0 | N11: =SUMIFS(Base_Semanal!$M$4:$M$107,Base_Semanal!$D$4:$D$107,$A11) -> 0 | O11: =M11+N11 -> 0 | P11: =SUMIFS(Base_Semanal!$N$4:$N$107,Base_Semanal!$D$4:$D$107,$A11) -> 0 | Q11: =SUMIFS(Base_Semanal!$O$4:$O$107,Base_Semanal!$D$4:$D$107,$A11) -> 0 | R11: =IF(SUMIFS(Base_Semanal!$P$4:$P$107,Base_Semanal!$D$4:$D$107,$A11)=0,"",SUMIFS(Base_Semanal!$Q$4:$Q$107,Base_Semanal!$D$4:$D$107,$A11)/SUMIFS(Base_Semanal!$P$4:$P$107,Base_Semanal!$D$4:$D$107,$A11)) | S11: =IF(SUMIFS(Base_Semanal!$R$4:$R$107,Base_Semanal!$D$4:$D$107,$A11)=0,"",SUMIFS(Base_Semanal!$S$4:$S$107,Base_Semanal!$D$4:$D$107,$A11)/SUMIFS(Base_Semanal!$R$4:$R$107,Base_Semanal!$D$4:$D$107,$A11)) | T11: =IF(SUMIFS(Base_Semanal!$P$4:$P$107,Base_Semanal!$D$4:$D$107,$A11)+SUMIFS(Base_Semanal!$R$4:$R$107,Base_Semanal!$D$4:$D$107,$A11)=0,"",(SUMIFS(Base_Semanal!$Q$4:$Q$107,Base_Semanal!$D$4:$D$107,$A11)+SUMIFS(Base_Semanal!$S$4:$S$107,Base_Semanal!$D$4:$D$107,$A11))/(SUMIFS(Base_Semanal!$P$4:$P$107,Base_Semanal!$D$4:$D$107,$A11)+SUMIFS(Base_Semanal!$R$4:$R$107,Base_Semanal!$D$4:$D$107,$A11))) | U11: =COUNTIFS(Contratos!$C$4:$C$503,$A11,Contratos!$E$4:$E$503,"Avaliação") -> 0 | V11: =SUMIFS(Contratos!$I$4:$I$503,Contratos!$C$4:$C$503,$A11,Contratos!$E$4:$E$503,"Avaliação") -> 0 | W11: =COUNTIFS(Contratos!$C$4:$C$503,$A11,Contratos!$E$4:$E$503,"Protocolo") -> 0 | X11: =SUMIFS(Contratos!$I$4:$I$503,Contratos!$C$4:$C$503,$A11,Contratos!$E$4:$E$503,"Protocolo") -> 0 | Y11: =SUMIFS(Financeiro!$G$4:$G$503,Financeiro!$C$4:$C$503,$A11,Financeiro!$D$4:$D$503,"Receita",Financeiro!$H$4:$H$503,"<>Cancelado") -> 0 | Z11: =SUMIFS(Financeiro!$G$4:$G$503,Financeiro!$C$4:$C$503,$A11,Financeiro!$D$4:$D$503,"Gasto",Financeiro!$H$4:$H$503,"<>Cancelado") -> 0 | AA11: =SUMIFS(Financeiro!$G$4:$G$503,Financeiro!$C$4:$C$503,$A11,Financeiro!$D$4:$D$503,"Imposto",Financeiro!$H$4:$H$503,"<>Cancelado") -> 0 | AB11: =SUMIFS(Financeiro!$G$4:$G$503,Financeiro!$C$4:$C$503,$A11,Financeiro!$D$4:$D$503,"Marketing",Financeiro!$H$4:$H$503,"<>Cancelado") -> 0 | AC11: =Y11-Z11-AA11-AB11 -> 0 | AD11: =IF(Config!$C$16=0,"",Y11/Config!$C$16) -> 0 | AE11: =IF(Config!$C$17=0,"",Z11/Config!$C$17) -> 0 | AF11: =IF(Q11=0,"",AB11/Q11)
A12: 2026-09 | B12: =SUMIFS(Base_Semanal!$E$4:$E$107,Base_Semanal!$D$4:$D$107,$A12) -> 83 | C12: =SUMIFS(Base_Semanal!$F$4:$F$107,Base_Semanal!$D$4:$D$107,$A12) -> 30 | D12: =SUMIFS(Base_Semanal!$G$4:$G$107,Base_Semanal!$D$4:$D$107,$A12) -> 3 | E12: =SUMIFS(Base_Semanal!$H$4:$H$107,Base_Semanal!$D$4:$D$107,$A12) -> 14 | F12: =SUMIFS(Base_Semanal!$I$4:$I$107,Base_Semanal!$D$4:$D$107,$A12) -> 11 | G12: =E12+F12 -> 25 | H12: =IF(C12=0,"",D12/C12) -> 0.1 | I12: =SUMIFS(Base_Semanal!$J$4:$J$107,Base_Semanal!$D$4:$D$107,$A12) -> 10 | J12: =SUMIFS(Base_Semanal!$K$4:$K$107,Base_Semanal!$D$4:$D$107,$A12) -> 7 | K12: =I12+J12 -> 17 | L12: =IF(G12=0,"",K12/G12) -> 0.68 | M12: =SUMIFS(Base_Semanal!$L$4:$L$107,Base_Semanal!$D$4:$D$107,$A12) -> 121 | N12: =SUMIFS(Base_Semanal!$M$4:$M$107,Base_Semanal!$D$4:$D$107,$A12) -> 109 | O12: =M12+N12 -> 230 | P12: =SUMIFS(Base_Semanal!$N$4:$N$107,Base_Semanal!$D$4:$D$107,$A12) -> 12 | Q12: =SUMIFS(Base_Semanal!$O$4:$O$107,Base_Semanal!$D$4:$D$107,$A12) -> 15 | R12: =IF(SUMIFS(Base_Semanal!$P$4:$P$107,Base_Semanal!$D$4:$D$107,$A12)=0,"",SUMIFS(Base_Semanal!$Q$4:$Q$107,Base_Semanal!$D$4:$D$107,$A12)/SUMIFS(Base_Semanal!$P$4:$P$107,Base_Semanal!$D$4:$D$107,$A12)) -> 0.925 | S12: =IF(SUMIFS(Base_Semanal!$R$4:$R$107,Base_Semanal!$D$4:$D$107,$A12)=0,"",SUMIFS(Base_Semanal!$S$4:$S$107,Base_Semanal!$D$4:$D$107,$A12)/SUMIFS(Base_Semanal!$R$4:$R$107,Base_Semanal!$D$4:$D$107,$A12)) -> 0.875 | T12: =IF(SUMIFS(Base_Semanal!$P$4:$P$107,Base_Semanal!$D$4:$D$107,$A12)+SUMIFS(Base_Semanal!$R$4:$R$107,Base_Semanal!$D$4:$D$107,$A12)=0,"",(SUMIFS(Base_Semanal!$Q$4:$Q$107,Base_Semanal!$D$4:$D$107,$A12)+SUMIFS(Base_Semanal!$S$4:$S$107,Base_Semanal!$D$4:$D$107,$A12))/(SUMIFS(Base_Semanal!$P$4:$P$107,Base_Semanal!$D$4:$D$107,$A12)+SUMIFS(Base_Semanal!$R$4:$R$107,Base_Semanal!$D$4:$D$107,$A12))) -> 0.9 | U12: =COUNTIFS(Contratos!$C$4:$C$503,$A12,Contratos!$E$4:$E$503,"Avaliação") -> 2 | V12: =SUMIFS(Contratos!$I$4:$I$503,Contratos!$C$4:$C$503,$A12,Contratos!$E$4:$E$503,"Avaliação") -> 300 | W12: =COUNTIFS(Contratos!$C$4:$C$503,$A12,Contratos!$E$4:$E$503,"Protocolo") -> 3 | X12: =SUMIFS(Contratos!$I$4:$I$503,Contratos!$C$4:$C$503,$A12,Contratos!$E$4:$E$503,"Protocolo") -> 10000 | Y12: =SUMIFS(Financeiro!$G$4:$G$503,Financeiro!$C$4:$C$503,$A12,Financeiro!$D$4:$D$503,"Receita",Financeiro!$H$4:$H$503,"<>Cancelado") -> 4283.33 | Z12: =SUMIFS(Financeiro!$G$4:$G$503,Financeiro!$C$4:$C$503,$A12,Financeiro!$D$4:$D$503,"Gasto",Financeiro!$H$4:$H$503,"<>Cancelado") -> 2800 | AA12: =SUMIFS(Financeiro!$G$4:$G$503,Financeiro!$C$4:$C$503,$A12,Financeiro!$D$4:$D$503,"Imposto",Financeiro!$H$4:$H$503,"<>Cancelado") -> 0 | AB12: =SUMIFS(Financeiro!$G$4:$G$503,Financeiro!$C$4:$C$503,$A12,Financeiro!$D$4:$D$503,"Marketing",Financeiro!$H$4:$H$503,"<>Cancelado") -> 600 | AC12: =Y12-Z12-AA12-AB12 -> 883.33 | AD12: =IF(Config!$C$16=0,"",Y12/Config!$C$16) -> 0.035694417 | AE12: =IF(Config!$C$17=0,"",Z12/Config!$C$17) -> 0.038888889 | AF12: =IF(Q12=0,"",AB12/Q12) -> 40
A13: 2026-10 | B13: =SUMIFS(Base_Semanal!$E$4:$E$107,Base_Semanal!$D$4:$D$107,$A13) -> 0 | C13: =SUMIFS(Base_Semanal!$F$4:$F$107,Base_Semanal!$D$4:$D$107,$A13) -> 0 | D13: =SUMIFS(Base_Semanal!$G$4:$G$107,Base_Semanal!$D$4:$D$107,$A13) -> 0 | E13: =SUMIFS(Base_Semanal!$H$4:$H$107,Base_Semanal!$D$4:$D$107,$A13) -> 0 | F13: =SUMIFS(Base_Semanal!$I$4:$I$107,Base_Semanal!$D$4:$D$107,$A13) -> 0 | G13: =E13+F13 -> 0 | H13: =IF(C13=0,"",D13/C13) | I13: =SUMIFS(Base_Semanal!$J$4:$J$107,Base_Semanal!$D$4:$D$107,$A13) -> 0 | J13: =SUMIFS(Base_Semanal!$K$4:$K$107,Base_Semanal!$D$4:$D$107,$A13) -> 0 | K13: =I13+J13 -> 0 | L13: =IF(G13=0,"",K13/G13) | M13: =SUMIFS(Base_Semanal!$L$4:$L$107,Base_Semanal!$D$4:$D$107,$A13) -> 0 | N13: =SUMIFS(Base_Semanal!$M$4:$M$107,Base_Semanal!$D$4:$D$107,$A13) -> 0 | O13: =M13+N13 -> 0 | P13: =SUMIFS(Base_Semanal!$N$4:$N$107,Base_Semanal!$D$4:$D$107,$A13) -> 0 | Q13: =SUMIFS(Base_Semanal!$O$4:$O$107,Base_Semanal!$D$4:$D$107,$A13) -> 0 | R13: =IF(SUMIFS(Base_Semanal!$P$4:$P$107,Base_Semanal!$D$4:$D$107,$A13)=0,"",SUMIFS(Base_Semanal!$Q$4:$Q$107,Base_Semanal!$D$4:$D$107,$A13)/SUMIFS(Base_Semanal!$P$4:$P$107,Base_Semanal!$D$4:$D$107,$A13)) -> 0.73333333 | S13: =IF(SUMIFS(Base_Semanal!$R$4:$R$107,Base_Semanal!$D$4:$D$107,$A13)=0,"",SUMIFS(Base_Semanal!$S$4:$S$107,Base_Semanal!$D$4:$D$107,$A13)/SUMIFS(Base_Semanal!$R$4:$R$107,Base_Semanal!$D$4:$D$107,$A13)) -> 0.63333333 | T13: =IF(SUMIFS(Base_Semanal!$P$4:$P$107,Base_Semanal!$D$4:$D$107,$A13)+SUMIFS(Base_Semanal!$R$4:$R$107,Base_Semanal!$D$4:$D$107,$A13)=0,"",(SUMIFS(Base_Semanal!$Q$4:$Q$107,Base_Semanal!$D$4:$D$107,$A13)+SUMIFS(Base_Semanal!$S$4:$S$107,Base_Semanal!$D$4:$D$107,$A13))/(SUMIFS(Base_Semanal!$P$4:$P$107,Base_Semanal!$D$4:$D$107,$A13)+SUMIFS(Base_Semanal!$R$4:$R$107,Base_Semanal!$D$4:$D$107,$A13))) -> 0.68333333 | U13: =COUNTIFS(Contratos!$C$4:$C$503,$A13,Contratos!$E$4:$E$503,"Avaliação") -> 1 | V13: =SUMIFS(Contratos!$I$4:$I$503,Contratos!$C$4:$C$503,$A13,Contratos!$E$4:$E$503,"Avaliação") -> 150 | W13: =COUNTIFS(Contratos!$C$4:$C$503,$A13,Contratos!$E$4:$E$503,"Protocolo") -> 1 | X13: =SUMIFS(Contratos!$I$4:$I$503,Contratos!$C$4:$C$503,$A13,Contratos!$E$4:$E$503,"Protocolo") -> 3000 | Y13: =SUMIFS(Financeiro!$G$4:$G$503,Financeiro!$C$4:$C$503,$A13,Financeiro!$D$4:$D$503,"Receita",Financeiro!$H$4:$H$503,"<>Cancelado") -> 1760 | Z13: =SUMIFS(Financeiro!$G$4:$G$503,Financeiro!$C$4:$C$503,$A13,Financeiro!$D$4:$D$503,"Gasto",Financeiro!$H$4:$H$503,"<>Cancelado") -> 4880 | AA13: =SUMIFS(Financeiro!$G$4:$G$503,Financeiro!$C$4:$C$503,$A13,Financeiro!$D$4:$D$503,"Imposto",Financeiro!$H$4:$H$503,"<>Cancelado") -> 1850 | AB13: =SUMIFS(Financeiro!$G$4:$G$503,Financeiro!$C$4:$C$503,$A13,Financeiro!$D$4:$D$503,"Marketing",Financeiro!$H$4:$H$503,"<>Cancelado") -> 700 | AC13: =Y13-Z13-AA13-AB13 -> -5670 | AD13: =IF(Config!$C$16=0,"",Y13/Config!$C$16) -> 0.014666667 | AE13: =IF(Config!$C$17=0,"",Z13/Config!$C$17) -> 0.067777778 | AF13: =IF(Q13=0,"",AB13/Q13)
A14: 2026-11 | B14: =SUMIFS(Base_Semanal!$E$4:$E$107,Base_Semanal!$D$4:$D$107,$A14) -> 0 | C14: =SUMIFS(Base_Semanal!$F$4:$F$107,Base_Semanal!$D$4:$D$107,$A14) -> 0 | D14: =SUMIFS(Base_Semanal!$G$4:$G$107,Base_Semanal!$D$4:$D$107,$A14) -> 0 | E14: =SUMIFS(Base_Semanal!$H$4:$H$107,Base_Semanal!$D$4:$D$107,$A14) -> 0 | F14: =SUMIFS(Base_Semanal!$I$4:$I$107,Base_Semanal!$D$4:$D$107,$A14) -> 0 | G14: =E14+F14 -> 0 | H14: =IF(C14=0,"",D14/C14) | I14: =SUMIFS(Base_Semanal!$J$4:$J$107,Base_Semanal!$D$4:$D$107,$A14) -> 0 | J14: =SUMIFS(Base_Semanal!$K$4:$K$107,Base_Semanal!$D$4:$D$107,$A14) -> 0 | K14: =I14+J14 -> 0 | L14: =IF(G14=0,"",K14/G14) | M14: =SUMIFS(Base_Semanal!$L$4:$L$107,Base_Semanal!$D$4:$D$107,$A14) -> 0 | N14: =SUMIFS(Base_Semanal!$M$4:$M$107,Base_Semanal!$D$4:$D$107,$A14) -> 0 | O14: =M14+N14 -> 0 | P14: =SUMIFS(Base_Semanal!$N$4:$N$107,Base_Semanal!$D$4:$D$107,$A14) -> 0 | Q14: =SUMIFS(Base_Semanal!$O$4:$O$107,Base_Semanal!$D$4:$D$107,$A14) -> 0 | R14: =IF(SUMIFS(Base_Semanal!$P$4:$P$107,Base_Semanal!$D$4:$D$107,$A14)=0,"",SUMIFS(Base_Semanal!$Q$4:$Q$107,Base_Semanal!$D$4:$D$107,$A14)/SUMIFS(Base_Semanal!$P$4:$P$107,Base_Semanal!$D$4:$D$107,$A14)) | S14: =IF(SUMIFS(Base_Semanal!$R$4:$R$107,Base_Semanal!$D$4:$D$107,$A14)=0,"",SUMIFS(Base_Semanal!$S$4:$S$107,Base_Semanal!$D$4:$D$107,$A14)/SUMIFS(Base_Semanal!$R$4:$R$107,Base_Semanal!$D$4:$D$107,$A14)) | T14: =IF(SUMIFS(Base_Semanal!$P$4:$P$107,Base_Semanal!$D$4:$D$107,$A14)+SUMIFS(Base_Semanal!$R$4:$R$107,Base_Semanal!$D$4:$D$107,$A14)=0,"",(SUMIFS(Base_Semanal!$Q$4:$Q$107,Base_Semanal!$D$4:$D$107,$A14)+SUMIFS(Base_Semanal!$S$4:$S$107,Base_Semanal!$D$4:$D$107,$A14))/(SUMIFS(Base_Semanal!$P$4:$P$107,Base_Semanal!$D$4:$D$107,$A14)+SUMIFS(Base_Semanal!$R$4:$R$107,Base_Semanal!$D$4:$D$107,$A14))) | U14: =COUNTIFS(Contratos!$C$4:$C$503,$A14,Contratos!$E$4:$E$503,"Avaliação") -> 0 | V14: =SUMIFS(Contratos!$I$4:$I$503,Contratos!$C$4:$C$503,$A14,Contratos!$E$4:$E$503,"Avaliação") -> 0 | W14: =COUNTIFS(Contratos!$C$4:$C$503,$A14,Contratos!$E$4:$E$503,"Protocolo") -> 0 | X14: =SUMIFS(Contratos!$I$4:$I$503,Contratos!$C$4:$C$503,$A14,Contratos!$E$4:$E$503,"Protocolo") -> 0 | Y14: =SUMIFS(Financeiro!$G$4:$G$503,Financeiro!$C$4:$C$503,$A14,Financeiro!$D$4:$D$503,"Receita",Financeiro!$H$4:$H$503,"<>Cancelado") -> 0 | Z14: =SUMIFS(Financeiro!$G$4:$G$503,Financeiro!$C$4:$C$503,$A14,Financeiro!$D$4:$D$503,"Gasto",Financeiro!$H$4:$H$503,"<>Cancelado") -> 0 | AA14: =SUMIFS(Financeiro!$G$4:$G$503,Financeiro!$C$4:$C$503,$A14,Financeiro!$D$4:$D$503,"Imposto",Financeiro!$H$4:$H$503,"<>Cancelado") -> 0 | AB14: =SUMIFS(Financeiro!$G$4:$G$503,Financeiro!$C$4:$C$503,$A14,Financeiro!$D$4:$D$503,"Marketing",Financeiro!$H$4:$H$503,"<>Cancelado") -> 0 | AC14: =Y14-Z14-AA14-AB14 -> 0 | AD14: =IF(Config!$C$16=0,"",Y14/Config!$C$16) -> 0 | AE14: =IF(Config!$C$17=0,"",Z14/Config!$C$17) -> 0 | AF14: =IF(Q14=0,"",AB14/Q14)
A15: 2026-12 | B15: =SUMIFS(Base_Semanal!$E$4:$E$107,Base_Semanal!$D$4:$D$107,$A15) -> 0 | C15: =SUMIFS(Base_Semanal!$F$4:$F$107,Base_Semanal!$D$4:$D$107,$A15) -> 0 | D15: =SUMIFS(Base_Semanal!$G$4:$G$107,Base_Semanal!$D$4:$D$107,$A15) -> 0 | E15: =SUMIFS(Base_Semanal!$H$4:$H$107,Base_Semanal!$D$4:$D$107,$A15) -> 0 | F15: =SUMIFS(Base_Semanal!$I$4:$I$107,Base_Semanal!$D$4:$D$107,$A15) -> 0 | G15: =E15+F15 -> 0 | H15: =IF(C15=0,"",D15/C15) | I15: =SUMIFS(Base_Semanal!$J$4:$J$107,Base_Semanal!$D$4:$D$107,$A15) -> 0 | J15: =SUMIFS(Base_Semanal!$K$4:$K$107,Base_Semanal!$D$4:$D$107,$A15) -> 0 | K15: =I15+J15 -> 0 | L15: =IF(G15=0,"",K15/G15) | M15: =SUMIFS(Base_Semanal!$L$4:$L$107,Base_Semanal!$D$4:$D$107,$A15) -> 0 | N15: =SUMIFS(Base_Semanal!$M$4:$M$107,Base_Semanal!$D$4:$D$107,$A15) -> 0 | O15: =M15+N15 -> 0 | P15: =SUMIFS(Base_Semanal!$N$4:$N$107,Base_Semanal!$D$4:$D$107,$A15) -> 0 | Q15: =SUMIFS(Base_Semanal!$O$4:$O$107,Base_Semanal!$D$4:$D$107,$A15) -> 0 | R15: =IF(SUMIFS(Base_Semanal!$P$4:$P$107,Base_Semanal!$D$4:$D$107,$A15)=0,"",SUMIFS(Base_Semanal!$Q$4:$Q$107,Base_Semanal!$D$4:$D$107,$A15)/SUMIFS(Base_Semanal!$P$4:$P$107,Base_Semanal!$D$4:$D$107,$A15)) | S15: =IF(SUMIFS(Base_Semanal!$R$4:$R$107,Base_Semanal!$D$4:$D$107,$A15)=0,"",SUMIFS(Base_Semanal!$S$4:$S$107,Base_Semanal!$D$4:$D$107,$A15)/SUMIFS(Base_Semanal!$R$4:$R$107,Base_Semanal!$D$4:$D$107,$A15)) | T15: =IF(SUMIFS(Base_Semanal!$P$4:$P$107,Base_Semanal!$D$4:$D$107,$A15)+SUMIFS(Base_Semanal!$R$4:$R$107,Base_Semanal!$D$4:$D$107,$A15)=0,"",(SUMIFS(Base_Semanal!$Q$4:$Q$107,Base_Semanal!$D$4:$D$107,$A15)+SUMIFS(Base_Semanal!$S$4:$S$107,Base_Semanal!$D$4:$D$107,$A15))/(SUMIFS(Base_Semanal!$P$4:$P$107,Base_Semanal!$D$4:$D$107,$A15)+SUMIFS(Base_Semanal!$R$4:$R$107,Base_Semanal!$D$4:$D$107,$A15))) | U15: =COUNTIFS(Contratos!$C$4:$C$503,$A15,Contratos!$E$4:$E$503,"Avaliação") -> 0 | V15: =SUMIFS(Contratos!$I$4:$I$503,Contratos!$C$4:$C$503,$A15,Contratos!$E$4:$E$503,"Avaliação") -> 0 | W15: =COUNTIFS(Contratos!$C$4:$C$503,$A15,Contratos!$E$4:$E$503,"Protocolo") -> 0 | X15: =SUMIFS(Contratos!$I$4:$I$503,Contratos!$C$4:$C$503,$A15,Contratos!$E$4:$E$503,"Protocolo") -> 0 | Y15: =SUMIFS(Financeiro!$G$4:$G$503,Financeiro!$C$4:$C$503,$A15,Financeiro!$D$4:$D$503,"Receita",Financeiro!$H$4:$H$503,"<>Cancelado") -> 0 | Z15: =SUMIFS(Financeiro!$G$4:$G$503,Financeiro!$C$4:$C$503,$A15,Financeiro!$D$4:$D$503,"Gasto",Financeiro!$H$4:$H$503,"<>Cancelado") -> 0 | AA15: =SUMIFS(Financeiro!$G$4:$G$503,Financeiro!$C$4:$C$503,$A15,Financeiro!$D$4:$D$503,"Imposto",Financeiro!$H$4:$H$503,"<>Cancelado") -> 0 | AB15: =SUMIFS(Financeiro!$G$4:$G$503,Financeiro!$C$4:$C$503,$A15,Financeiro!$D$4:$D$503,"Marketing",Financeiro!$H$4:$H$503,"<>Cancelado") -> 0 | AC15: =Y15-Z15-AA15-AB15 -> 0 | AD15: =IF(Config!$C$16=0,"",Y15/Config!$C$16) -> 0 | AE15: =IF(Config!$C$17=0,"",Z15/Config!$C$17) -> 0 | AF15: =IF(Q15=0,"",AB15/Q15)
... A27: 2027-12 | B27: =SUMIFS(Base_Semanal!$E$4:$E$107,Base_Semanal!$D$4:$D$107,$A27) -> 0 | C27: =SUMIFS(Base_Semanal!$F$4:$F$107,Base_Semanal!$D$4:$D$107,$A27) -> 0 | D27: =SUMIFS(Base_Semanal!$G$4:$G$107,Base_Semanal!$D$4:$D$107,$A27) -> 0 | E27: =SUMIFS(Base_Semanal!$H$4:$H$107,Base_Semanal!$D$4:$D$107,$A27) -> 0 | F27: =SUMIFS(Base_Semanal!$I$4:$I$107,Base_Semanal!$D$4:$D$107,$A27) -> 0 | G27: =E27+F27 -> 0 | H27: =IF(C27=0,"",D27/C27) | I27: =SUMIFS(Base_Semanal!$J$4:$J$107,Base_Semanal!$D$4:$D$107,$A27) -> 0 | J27: =SUMIFS(Base_Semanal!$K$4:$K$107,Base_Semanal!$D$4:$D$107,$A27) -> 0 | K27: =I27+J27 -> 0 | L27: =IF(G27=0,"",K27/G27) | M27: =SUMIFS(Base_Semanal!$L$4:$L$107,Base_Semanal!$D$4:$D$107,$A27) -> 0 | N27: =SUMIFS(Base_Semanal!$M$4:$M$107,Base_Semanal!$D$4:$D$107,$A27) -> 0 | O27: =M27+N27 -> 0 | P27: =SUMIFS(Base_Semanal!$N$4:$N$107,Base_Semanal!$D$4:$D$107,$A27) -> 0 | Q27: =SUMIFS(Base_Semanal!$O$4:$O$107,Base_Semanal!$D$4:$D$107,$A27) -> 0 | R27: =IF(SUMIFS(Base_Semanal!$P$4:$P$107,Base_Semanal!$D$4:$D$107,$A27)=0,"",SUMIFS(Base_Semanal!$Q$4:$Q$107,Base_Semanal!$D$4:$D$107,$A27)/SUMIFS(Base_Semanal!$P$4:$P$107,Base_Semanal!$D$4:$D$107,$A27)) | S27: =IF(SUMIFS(Base_Semanal!$R$4:$R$107,Base_Semanal!$D$4:$D$107,$A27)=0,"",SUMIFS(Base_Semanal!$S$4:$S$107,Base_Semanal!$D$4:$D$107,$A27)/SUMIFS(Base_Semanal!$R$4:$R$107,Base_Semanal!$D$4:$D$107,$A27)) | T27: =IF(SUMIFS(Base_Semanal!$P$4:$P$107,Base_Semanal!$D$4:$D$107,$A27)+SUMIFS(Base_Semanal!$R$4:$R$107,Base_Semanal!$D$4:$D$107,$A27)=0,"",(SUMIFS(Base_Semanal!$Q$4:$Q$107,Base_Semanal!$D$4:$D$107,$A27)+SUMIFS(Base_Semanal!$S$4:$S$107,Base_Semanal!$D$4:$D$107,$A27))/(SUMIFS(Base_Semanal!$P$4:$P$107,Base_Semanal!$D$4:$D$107,$A27)+SUMIFS(Base_Semanal!$R$4:$R$107,Base_Semanal!$D$4:$D$107,$A27))) | U27: =COUNTIFS(Contratos!$C$4:$C$503,$A27,Contratos!$E$4:$E$503,"Avaliação") -> 0 | V27: =SUMIFS(Contratos!$I$4:$I$503,Contratos!$C$4:$C$503,$A27,Contratos!$E$4:$E$503,"Avaliação") -> 0 | W27: =COUNTIFS(Contratos!$C$4:$C$503,$A27,Contratos!$E$4:$E$503,"Protocolo") -> 0 | X27: =SUMIFS(Contratos!$I$4:$I$503,Contratos!$C$4:$C$503,$A27,Contratos!$E$4:$E$503,"Protocolo") -> 0 | Y27: =SUMIFS(Financeiro!$G$4:$G$503,Financeiro!$C$4:$C$503,$A27,Financeiro!$D$4:$D$503,"Receita",Financeiro!$H$4:$H$503,"<>Cancelado") -> 0 | Z27: =SUMIFS(Financeiro!$G$4:$G$503,Financeiro!$C$4:$C$503,$A27,Financeiro!$D$4:$D$503,"Gasto",Financeiro!$H$4:$H$503,"<>Cancelado") -> 0 | AA27: =SUMIFS(Financeiro!$G$4:$G$503,Financeiro!$C$4:$C$503,$A27,Financeiro!$D$4:$D$503,"Imposto",Financeiro!$H$4:$H$503,"<>Cancelado") -> 0 | AB27: =SUMIFS(Financeiro!$G$4:$G$503,Financeiro!$C$4:$C$503,$A27,Financeiro!$D$4:$D$503,"Marketing",Financeiro!$H$4:$H$503,"<>Cancelado") -> 0 | AC27: =Y27-Z27-AA27-AB27 -> 0 | AD27: =IF(Config!$C$16=0,"",Y27/Config!$C$16) -> 0 | AE27: =IF(Config!$C$17=0,"",Z27/Config!$C$17) -> 0 | AF27: =IF(Q27=0,"",AB27/Q27)
